Workbook

Sheet Leia-me
A1: CRM relacional — Escritório › Gerente › Vendedor › Deal › Conta › Produto
A2: Todas as 4 tabelas do dataset ligadas com exatidão. Os números das abas de resumo são fórmulas sobre a aba Pipeline_Completo.
A4: PREMISSAS (editáveis)
A5: Data de referência ("hoje") | B5: 43100 | C5: Último dia com dados no dataset. Usada para calcular a idade dos deals abertos.
A6: Limite "Saudável" (dias) | B6: 88 | C6: Até aqui = dentro do tempo em que ~75% dos deals ganhos fecham (p75 do ciclo dos ganhos = 85 dias).
A7: Limite "Esfriando" (dias) | B7: 120 | C7: ~95% dos deals ganhos fecharam até 114 dias.
A8: Limite "Zumbi" (dias) | B8: 138 | C8: Maior ciclo de qualquer deal fechado no histórico. Acima disso nenhum deal jamais fechou.
A11: COMO AS TABELAS SE LIGAM
A12: sales_pipeline.sales_agent | B12: → sales_teams | C12: Cada deal tem 1 vendedor; cada vendedor tem 1 gerente e 1 escritório regional.
A13: sales_pipeline.product | B13: → products | C13: Preço de tabela e série. Corrigido: "GTXPro" (1.480 linhas) não existia em products → tratado como "GTX Pro".
A14: sales_pipeline.account | B14: → accounts | C14: Setor, receita, funcionários, país, empresa-mãe. 1.425 deals abertos NÃO têm conta preenchida.
A15: Hierarquia | B15: 3 › 6 › 35 | C15: 3 escritórios › 6 gerentes (2 por escritório) › 35 vendedores. 5 vendedores não têm nenhum deal.
A17: DEFINIÇÕES
A18: Receita ganha | C18: Soma de close_value dos deals Won (valor real fechado).
A19: Pipeline aberto (estimado) | C19: Deals Engaging + Prospecting não têm close_value. Usamos o preço de tabela do produto (nos ganhos, close_value ≈ preço de tabela, desvio médio < 1%).
A20: Win rate | C20: Won ÷ (Won + Lost). Atenção: deals iniciados em 2016 têm win rate inflado (82%) porque perdas antes de mar/2017 não estão no dataset.
A21: Relógio do deal | C21: Só para Engaging: Saudável / Esfriando / Última chance / Zumbi, pela idade na data de referência e pelos limites acima.
A22: Ciclo (dias) | C22: close_date − engage_date (deals fechados).
A24: ABAS
A25: Hierarquia | C25: Escritório › Gerente › Vendedor com todos os números de cada um, subtotais por gerente e escritório.
A26: Resumo_Escritorio / Resumo_Gerente | C26: Visão consolidada por nível.
A27: Produto_x_Gerente | C27: Receita ganha e pipeline aberto de cada produto, por equipe.
A28: Contas | C28: Cada conta com seus números e quantos vendedores/gerentes/escritórios mexem nela.
A29: Pipeline_Completo | C29: As 8.800 oportunidades com TODAS as colunas das 4 tabelas lado a lado (filtrável).
A30: Qualidade_Dados | C30: Problemas encontrados nos dados, com contagem.
A31: raw_* | C31: Os 4 CSVs originais, sem alteração, para auditoria.
A33: Legenda: texto azul com fundo amarelo = premissa editável. Demais números = fórmulas.

Sheet Hierarquia
A1: Escritório | B1: Gerente | C1: Vendedor | D1: Deals total | E1: Won | F1: Lost | G1: Engaging | H1: Prospecting | I1: Win rate | J1: Receita ganha (US$) | K1: Ticket médio ganho (US$) | L1: Pipeline aberto (US$) | M1: Engaging vivos (≤ limite zumbi) | N1: Valor vivos (US$) | O1: Zumbis | P1: Valor zumbi (US$) | Q1: % pipeline Engaging zumbi | R1: Abertos sem conta
A2: Central | B2: Dustin Brinkmann | C2: Anna Snelling | D2: =COUNTIFS(Pipeline_Completo!$D$2:$D$8801,$C2) -> 448 | E2: =COUNTIFS(Pipeline_Completo!$D$2:$D$8801,$C2,Pipeline_Completo!$O$2:$O$8801,"Won") -> 208 | F2: =COUNTIFS(Pipeline_Completo!$D$2:$D$8801,$C2,Pipeline_Completo!$O$2:$O$8801,"Lost") -> 128 | G2: =COUNTIFS(Pipeline_Completo!$D$2:$D$8801,$C2,Pipeline_Completo!$O$2:$O$8801,"Engaging") -> 57 | H2: =COUNTIFS(Pipeline_Completo!$D$2:$D$8801,$C2,Pipeline_Completo!$O$2:$O$8801,"Prospecting") -> 55 | I2: =IFERROR(E2/(E2+F2),"") -> 0.61904762 | J2: =SUMIFS(Pipeline_Completo!$R$2:$R$8801,Pipeline_Completo!$D$2:$D$8801,$C2,Pipeline_Completo!$O$2:$O$8801,"Won") -> 275056 | K2: =IFERROR(J2/E2,"") -> 1322.3846 | L2: =SUMIFS(Pipeline_Completo!$S$2:$S$8801,Pipeline_Completo!$D$2:$D$8801,$C2,Pipeline_Completo!$O$2:$O$8801,"Engaging")+SUMIFS(Pipeline_Completo!$S$2:$S$8801,Pipeline_Completo!$D$2:$D$8801,$C2,Pipeline_Completo!$O$2:$O$8801,"Prospecting") -> 173259 | M2: =COUNTIFS(Pipeline_Completo!$D$2:$D$8801,$C2,Pipeline_Completo!$V$2:$V$8801,"Saudável")+COUNTIFS(Pipeline_Completo!$D$2:$D$8801,$C2,Pipeline_Completo!$V$2:$V$8801,"Esfriando")+COUNTIFS(Pipeline_Completo!$D$2:$D$8801,$C2,Pipeline_Completo!$V$2:$V$8801,"Última chance") -> 1 | N2: =SUMIFS(Pipeline_Completo!$S$2:$S$8801,Pipeline_Completo!$D$2:$D$8801,$C2,Pipeline_Completo!$V$2:$V$8801,"Saudável")+SUMIFS(Pipeline_Completo!$S$2:$S$8801,Pipeline_Completo!$D$2:$D$8801,$C2,Pipeline_Completo!$V$2:$V$8801,"Esfriando")+SUMIFS(Pipeline_Completo!$S$2:$S$8801,Pipeline_Completo!$D$2:$D$8801,$C2,Pipeline_Completo!$V$2:$V$8801,"Última chance") -> 55 | O2: =COUNTIFS(Pipeline_Completo!$D$2:$D$8801,$C2,Pipeline_Completo!$V$2:$V$8801,"Zumbi") -> 56 | P2: =SUMIFS(Pipeline_Completo!$S$2:$S$8801,Pipeline_Completo!$D$2:$D$8801,$C2,Pipeline_Completo!$V$2:$V$8801,"Zumbi") -> 95359 | Q2: =IFERROR(P2/(N2+P2),"") -> 0.99942356 | R2: =COUNTIFS(Pipeline_Completo!$D$2:$D$8801,$C2,Pipeline_Completo!$O$2:$O$8801,"Engaging",Pipeline_Completo!$E$2:$E$8801,"")+COUNTIFS(Pipeline_Completo!$D$2:$D$8801,$C2,Pipeline_Completo!$O$2:$O$8801,"Prospecting",Pipeline_Completo!$E$2:$E$8801,"") -> 69
A3: Central | B3: Dustin Brinkmann | C3: Cecily Lampkin | D3: =COUNTIFS(Pipeline_Completo!$D$2:$D$8801,$C3) -> 203 | E3: =COUNTIFS(Pipeline_Completo!$D$2:$D$8801,$C3,Pipeline_Completo!$O$2:$O$8801,"Won") -> 107 | F3: =COUNTIFS(Pipeline_Completo!$D$2:$D$8801,$C3,Pipeline_Completo!$O$2:$O$8801,"Lost") -> 53 | G3: =COUNTIFS(Pipeline_Completo!$D$2:$D$8801,$C3,Pipeline_Completo!$O$2:$O$8801,"Engaging") -> 19 | H3: =COUNTIFS(Pipeline_Completo!$D$2:$D$8801,$C3,Pipeline_Completo!$O$2:$O$8801,"Prospecting") -> 24 | I3: =IFERROR(E3/(E3+F3),"") -> 0.66875 | J3: =SUMIFS(Pipeline_Completo!$R$2:$R$8801,Pipeline_Completo!$D$2:$D$8801,$C3,Pipeline_Completo!$O$2:$O$8801,"Won") -> 229800 | K3: =IFERROR(J3/E3,"") -> 2147.6636 | L3: =SUMIFS(Pipeline_Completo!$S$2:$S$8801,Pipeline_Completo!$D$2:$D$8801,$C3,Pipeline_Completo!$O$2:$O$8801,"Engaging")+SUMIFS(Pipeline_Completo!$S$2:$S$8801,Pipeline_Completo!$D$2:$D$8801,$C3,Pipeline_Completo!$O$2:$O$8801,"Prospecting") -> 86748 | M3: =COUNTIFS(Pipeline_Completo!$D$2:$D$8801,$C3,Pipeline_Completo!$V$2:$V$8801,"Saudável")+COUNTIFS(Pipeline_Completo!$D$2:$D$8801,$C3,Pipeline_Completo!$V$2:$V$8801,"Esfriando")+COUNTIFS(Pipeline_Completo!$D$2:$D$8801,$C3,Pipeline_Completo!$V$2:$V$8801,"Última chance") -> 0 | N3: =SUMIFS(Pipeline_Completo!$S$2:$S$8801,Pipeline_Completo!$D$2:$D$8801,$C3,Pipeline_Completo!$V$2:$V$8801,"Saudável")+SUMIFS(Pipeline_Completo!$S$2:$S$8801,Pipeline_Completo!$D$2:$D$8801,$C3,Pipeline_Completo!$V$2:$V$8801,"Esfriando")+SUMIFS(Pipeline_Completo!$S$2:$S$8801,Pipeline_Completo!$D$2:$D$8801,$C3,Pipeline_Completo!$V$2:$V$8801,"Última chance") -> 0 | O3: =COUNTIFS(Pipeline_Completo!$D$2:$D$8801,$C3,Pipeline_Completo!$V$2:$V$8801,"Zumbi") -> 19 | P3: =SUMIFS(Pipeline_Completo!$S$2:$S$8801,Pipeline_Completo!$D$2:$D$8801,$C3,Pipeline_Completo!$V$2:$V$8801,"Zumbi") -> 29565 | Q3: =IFERROR(P3/(N3+P3),"") -> 1 | R3: =COUNTIFS(Pipeline_Completo!$D$2:$D$8801,$C3,Pipeline_Completo!$O$2:$O$8801,"Engaging",Pipeline_Completo!$E$2:$E$8801,"")+COUNTIFS(Pipeline_Completo!$D$2:$D$8801,$C3,Pipeline_Completo!$O$2:$O$8801,"Prospecting",Pipeline_Completo!$E$2:$E$8801,"") -> 33
A4: Central | B4: Dustin Brinkmann | C4: Versie Hillebrand | D4: =COUNTIFS(Pipeline_Completo!$D$2:$D$8801,$C4) -> 361 | E4: =COUNTIFS(Pipeline_Completo!$D$2:$D$8801,$C4,Pipeline_Completo!$O$2:$O$8801,"Won") -> 176 | F4: =COUNTIFS(Pipeline_Completo!$D$2:$D$8801,$C4,Pipeline_Completo!$O$2:$O$8801,"Lost") -> 88 | G4: =COUNTIFS(Pipeline_Completo!$D$2:$D$8801,$C4,Pipeline_Completo!$O$2:$O$8801,"Engaging") -> 43 | H4: =COUNTIFS(Pipeline_Completo!$D$2:$D$8801,$C4,Pipeline_Completo!$O$2:$O$8801,"Prospecting") -> 54 | I4: =IFERROR(E4/(E4+F4),"") -> 0.66666667 | J4: =SUMIFS(Pipeline_Completo!$R$2:$R$8801,Pipeline_Completo!$D$2:$D$8801,$C4,Pipeline_Completo!$O$2:$O$8801,"Won") -> 187693 | K4: =IFERROR(J4/E4,"") -> 1066.4375 | L4: =SUMIFS(Pipeline_Completo!$S$2:$S$8801,Pipeline_Completo!$D$2:$D$8801,$C4,Pipeline_Completo!$O$2:$O$8801,"Engaging")+SUMIFS(Pipeline_Completo!$S$2:$S$8801,Pipeline_Completo!$D$2:$D$8801,$C4,Pipeline_Completo!$O$2:$O$8801,"Prospecting") -> 101409 | M4: =COUNTIFS(Pipeline_Completo!$D$2:$D$8801,$C4,Pipeline_Completo!$V$2:$V$8801,"Saudável")+COUNTIFS(Pipeline_Completo!$D$2:$D$8801,$C4,Pipeline_Completo!$V$2:$V$8801,"Esfriando")+COUNTIFS(Pipeline_Completo!$D$2:$D$8801,$C4,Pipeline_Completo!$V$2:$V$8801,"Última chance") -> 1 | N4: =SUMIFS(Pipeline_Completo!$S$2:$S$8801,Pipeline_Completo!$D$2:$D$8801,$C4,Pipeline_Completo!$V$2:$V$8801,"Saudável")+SUMIFS(Pipeline_Completo!$S$2:$S$8801,Pipeline_Completo!$D$2:$D$8801,$C4,Pipeline_Completo!$V$2:$V$8801,"Esfriando")+SUMIFS(Pipeline_Completo!$S$2:$S$8801,Pipeline_Completo!$D$2:$D$8801,$C4,Pipeline_Completo!$V$2:$V$8801,"Última chance") -> 55 | O4: =COUNTIFS(Pipeline_Completo!$D$2:$D$8801,$C4,Pipeline_Completo!$V$2:$V$8801,"Zumbi") -> 42 | P4: =SUMIFS(Pipeline_Completo!$S$2:$S$8801,Pipeline_Completo!$D$2:$D$8801,$C4,Pipeline_Completo!$V$2:$V$8801,"Zumbi") -> 48603 | Q4: =IFERROR(P4/(N4+P4),"") -> 0.99886966 | R4: =COUNTIFS(Pipeline_Completo!$D$2:$D$8801,$C4,Pipeline_Completo!$O$2:$O$8801,"Engaging",Pipeline_Completo!$E$2:$E$8801,"")+COUNTIFS(Pipeline_Completo!$D$2:$D$8801,$C4,Pipeline_Completo!$O$2:$O$8801,"Prospecting",Pipeline_Completo!$E$2:$E$8801,"") -> 69
A5: Central | B5: Dustin Brinkmann | C5: Lajuana Vencill | D5: =COUNTIFS(Pipeline_Completo!$D$2:$D$8801,$C5) -> 311 | E5: =COUNTIFS(Pipeline_Completo!$D$2:$D$8801,$C5,Pipeline_Completo!$O$2:$O$8801,"Won") -> 127 | F5: =COUNTIFS(Pipeline_Completo!$D$2:$D$8801,$C5,Pipeline_Completo!$O$2:$O$8801,"Lost") -> 104 | G5: =COUNTIFS(Pipeline_Completo!$D$2:$D$8801,$C5,Pipeline_Completo!$O$2:$O$8801,"Engaging") -> 40 | H5: =COUNTIFS(Pipeline_Completo!$D$2:$D$8801,$C5,Pipeline_Completo!$O$2:$O$8801,"Prospecting") -> 40 | I5: =IFERROR(E5/(E5+F5),"") -> 0.54978355 | J5: =SUMIFS(Pipeline_Completo!$R$2:$R$8801,Pipeline_Completo!$D$2:$D$8801,$C5,Pipeline_Completo!$O$2:$O$8801,"Won") -> 194632 | K5: =IFERROR(J5/E5,"") -> 1532.5354 | L5: =SUMIFS(Pipeline_Completo!$S$2:$S$8801,Pipeline_Completo!$D$2:$D$8801,$C5,Pipeline_Completo!$O$2:$O$8801,"Engaging")+SUMIFS(Pipeline_Completo!$S$2:$S$8801,Pipeline_Completo!$D$2:$D$8801,$C5,Pipeline_Completo!$O$2:$O$8801,"Prospecting") -> 116039 | M5: =COUNTIFS(Pipeline_Completo!$D$2:$D$8801,$C5,Pipeline_Completo!$V$2:$V$8801,"Saudável")+COUNTIFS(Pipeline_Completo!$D$2:$D$8801,$C5,Pipeline_Completo!$V$2:$V$8801,"Esfriando")+COUNTIFS(Pipeline_Completo!$D$2:$D$8801,$C5,Pipeline_Completo!$V$2:$V$8801,"Última chance") -> 1 | N5: =SUMIFS(Pipeline_Completo!$S$2:$S$8801,Pipeline_Completo!$D$2:$D$8801,$C5,Pipeline_Completo!$V$2:$V$8801,"Saudável")+SUMIFS(Pipeline_Completo!$S$2:$S$8801,Pipeline_Completo!$D$2:$D$8801,$C5,Pipeline_Completo!$V$2:$V$8801,"Esfriando")+SUMIFS(Pipeline_Completo!$S$2:$S$8801,Pipeline_Completo!$D$2:$D$8801,$C5,Pipeline_Completo!$V$2:$V$8801,"Última chance") -> 550 | O5: =COUNTIFS(Pipeline_Completo!$D$2:$D$8801,$C5,Pipeline_Completo!$V$2:$V$8801,"Zumbi") -> 39 | P5: =SUMIFS(Pipeline_Completo!$S$2:$S$8801,Pipeline_Completo!$D$2:$D$8801,$C5,Pipeline_Completo!$V$2:$V$8801,"Zumbi") -> 57968 | Q5: =IFERROR(P5/(N5+P5),"") -> 0.99060118 | R5: =COUNTIFS(Pipeline_Completo!$D$2:$D$8801,$C5,Pipeline_Completo!$O$2:$O$8801,"Engaging",Pipeline_Completo!$E$2:$E$8801,"")+COUNTIFS(Pipeline_Completo!$D$2:$D$8801,$C5,Pipeline_Completo!$O$2:$O$8801,"Prospecting",Pipeline_Completo!$E$2:$E$8801,"") -> 57
A6: Central | B6: Dustin Brinkmann | C6: Moses Frase | D6: =COUNTIFS(Pipeline_Completo!$D$2:$D$8801,$C6) -> 260 | E6: =COUNTIFS(Pipeline_Completo!$D$2:$D$8801,$C6,Pipeline_Completo!$O$2:$O$8801,"Won") -> 129 | F6: =COUNTIFS(Pipeline_Completo!$D$2:$D$8801,$C6,Pipeline_Completo!$O$2:$O$8801,"Lost") -> 66 | G6: =COUNTIFS(Pipeline_Completo!$D$2:$D$8801,$C6,Pipeline_Completo!$O$2:$O$8801,"Engaging") -> 34 | H6: =COUNTIFS(Pipeline_Completo!$D$2:$D$8801,$C6,Pipeline_Completo!$O$2:$O$8801,"Prospecting") -> 31 | I6: =IFERROR(E6/(E6+F6),"") -> 0.66153846 | J6: =SUMIFS(Pipeline_Completo!$R$2:$R$8801,Pipeline_Completo!$D$2:$D$8801,$C6,Pipeline_Completo!$O$2:$O$8801,"Won") -> 207182 | K6: =IFERROR(J6/E6,"") -> 1606.062 | L6: =SUMIFS(Pipeline_Completo!$S$2:$S$8801,Pipeline_Completo!$D$2:$D$8801,$C6,Pipeline_Completo!$O$2:$O$8801,"Engaging")+SUMIFS(Pipeline_Completo!$S$2:$S$8801,Pipeline_Completo!$D$2:$D$8801,$C6,Pipeline_Completo!$O$2:$O$8801,"Prospecting") -> 108161 | M6: =COUNTIFS(Pipeline_Completo!$D$2:$D$8801,$C6,Pipeline_Completo!$V$2:$V$8801,"Saudável")+COUNTIFS(Pipeline_Completo!$D$2:$D$8801,$C6,Pipeline_Completo!$V$2:$V$8801,"Esfriando")+COUNTIFS(Pipeline_Completo!$D$2:$D$8801,$C6,Pipeline_Completo!$V$2:$V$8801,"Última chance") -> 0 | N6: =SUMIFS(Pipeline_Completo!$S$2:$S$8801,Pipeline_Completo!$D$2:$D$8801,$C6,Pipeline_Completo!$V$2:$V$8801,"Saudável")+SUMIFS(Pipeline_Completo!$S$2:$S$8801,Pipeline_Completo!$D$2:$D$8801,$C6,Pipeline_Completo!$V$2:$V$8801,"Esfriando")+SUMIFS(Pipeline_Completo!$S$2:$S$8801,Pipeline_Completo!$D$2:$D$8801,$C6,Pipeline_Completo!$V$2:$V$8801,"Última chance") -> 0 | O6: =COUNTIFS(Pipeline_Completo!$D$2:$D$8801,$C6,Pipeline_Completo!$V$2:$V$8801,"Zumbi") -> 34 | P6: =SUMIFS(Pipeline_Completo!$S$2:$S$8801,Pipeline_Completo!$D$2:$D$8801,$C6,Pipeline_Completo!$V$2:$V$8801,"Zumbi") -> 50552 | Q6: =IFERROR(P6/(N6+P6),"") -> 1 | R6: =COUNTIFS(Pipeline_Completo!$D$2:$D$8801,$C6,Pipeline_Completo!$O$2:$O$8801,"Engaging",Pipeline_Completo!$E$2:$E$8801,"")+COUNTIFS(Pipeline_Completo!$D$2:$D$8801,$C6,Pipeline_Completo!$O$2:$O$8801,"Prospecting",Pipeline_Completo!$E$2:$E$8801,"") -> 44
A7: Central | B7: Dustin Brinkmann | C7: Subtotal Dustin Brinkmann | D7: =COUNTIFS(Pipeline_Completo!$C$2:$C$8801,$B7) -> 1583 | E7: =COUNTIFS(Pipeline_Completo!$C$2:$C$8801,$B7,Pipeline_Completo!$O$2:$O$8801,"Won") -> 747 | F7: =COUNTIFS(Pipeline_Completo!$C$2:$C$8801,$B7,Pipeline_Completo!$O$2:$O$8801,"Lost") -> 439 | G7: =COUNTIFS(Pipeline_Completo!$C$2:$C$8801,$B7,Pipeline_Completo!$O$2:$O$8801,"Engaging") -> 193 | H7: =COUNTIFS(Pipeline_Completo!$C$2:$C$8801,$B7,Pipeline_Completo!$O$2:$O$8801,"Prospecting") -> 204 | I7: =IFERROR(E7/(E7+F7),"") -> 0.62984823 | J7: =SUMIFS(Pipeline_Completo!$R$2:$R$8801,Pipeline_Completo!$C$2:$C$8801,$B7,Pipeline_Completo!$O$2:$O$8801,"Won") -> 1094363 | K7: =IFERROR(J7/E7,"") -> 1465.0107 | L7: =SUMIFS(Pipeline_Completo!$S$2:$S$8801,Pipeline_Completo!$C$2:$C$8801,$B7,Pipeline_Completo!$O$2:$O$8801,"Engaging")+SUMIFS(Pipeline_Completo!$S$2:$S$8801,Pipeline_Completo!$C$2:$C$8801,$B7,Pipeline_Completo!$O$2:$O$8801,"Prospecting") -> 585616 | M7: =COUNTIFS(Pipeline_Completo!$C$2:$C$8801,$B7,Pipeline_Completo!$V$2:$V$8801,"Saudável")+COUNTIFS(Pipeline_Completo!$C$2:$C$8801,$B7,Pipeline_Completo!$V$2:$V$8801,"Esfriando")+COUNTIFS(Pipeline_Completo!$C$2:$C$8801,$B7,Pipeline_Completo!$V$2:$V$8801,"Última chance") -> 3 | N7: =SUMIFS(Pipeline_Completo!$S$2:$S$8801,Pipeline_Completo!$C$2:$C$8801,$B7,Pipeline_Completo!$V$2:$V$8801,"Saudável")+SUMIFS(Pipeline_Completo!$S$2:$S$8801,Pipeline_Completo!$C$2:$C$8801,$B7,Pipeline_Completo!$V$2:$V$8801,"Esfriando")+SUMIFS(Pipeline_Completo!$S$2:$S$8801,Pipeline_Completo!$C$2:$C$8801,$B7,Pipeline_Completo!$V$2:$V$8801,"Última chance") -> 660 | O7: =COUNTIFS(Pipeline_Completo!$C$2:$C$8801,$B7,Pipeline_Completo!$V$2:$V$8801,"Zumbi") -> 190 | P7: =SUMIFS(Pipeline_Completo!$S$2:$S$8801,Pipeline_Completo!$C$2:$C$8801,$B7,Pipeline_Completo!$V$2:$V$8801,"Zumbi") -> 282047 | Q7: =IFERROR(P7/(N7+P7),"") -> 0.99766543 | R7: =COUNTIFS(Pipeline_Completo!$C$2:$C$8801,$B7,Pipeline_Completo!$O$2:$O$8801,"Engaging",Pipeline_Completo!$E$2:$E$8801,"")+COUNTIFS(Pipeline_Completo!$C$2:$C$8801,$B7,Pipeline_Completo!$O$2:$O$8801,"Prospecting",Pipeline_Completo!$E$2:$E$8801,"") -> 272
A8: Central | B8: Melvin Marxen | C8: Jonathan Berthelot | D8: =COUNTIFS(Pipeline_Completo!$D$2:$D$8801,$C8) -> 345 | E8: =COUNTIFS(Pipeline_Completo!$D$2:$D$8801,$C8,Pipeline_Completo!$O$2:$O$8801,"Won") -> 171 | F8: =COUNTIFS(Pipeline_Completo!$D$2:$D$8801,$C8,Pipeline_Completo!$O$2:$O$8801,"Lost") -> 93 | G8: =COUNTIFS(Pipeline_Completo!$D$2:$D$8801,$C8,Pipeline_Completo!$O$2:$O$8801,"Engaging") -> 33 | H8: =COUNTIFS(Pipeline_Completo!$D$2:$D$8801,$C8,Pipeline_Completo!$O$2:$O$8801,"Prospecting") -> 48 | I8: =IFERROR(E8/(E8+F8),"") -> 0.64772727 | J8: =SUMIFS(Pipeline_Completo!$R$2:$R$8801,Pipeline_Completo!$D$2:$D$8801,$C8,Pipeline_Completo!$O$2:$O$8801,"Won") -> 284886 | K8: =IFERROR(J8/E8,"") -> 1666 | L8: =SUMIFS(Pipeline_Completo!$S$2:$S$8801,Pipeline_Completo!$D$2:$D$8801,$C8,Pipeline_Completo!$O$2:$O$8801,"Engaging")+SUMIFS(Pipeline_Completo!$S$2:$S$8801,Pipeline_Completo!$D$2:$D$8801,$C8,Pipeline_Completo!$O$2:$O$8801,"Prospecting") -> 127420 | M8: =COUNTIFS(Pipeline_Completo!$D$2:$D$8801,$C8,Pipeline_Completo!$V$2:$V$8801,"Saudável")+COUNTIFS(Pipeline_Completo!$D$2:$D$8801,$C8,Pipeline_Completo!$V$2:$V$8801,"Esfriando")+COUNTIFS(Pipeline_Completo!$D$2:$D$8801,$C8,Pipeline_Completo!$V$2:$V$8801,"Última chance") -> 0 | N8: =SUMIFS(Pipeline_Completo!$S$2:$S$8801,Pipeline_Completo!$D$2:$D$8801,$C8,Pipeline_Completo!$V$2:$V$8801,"Saudável")+SUMIFS(Pipeline_Completo!$S$2:$S$8801,Pipeline_Completo!$D$2:$D$8801,$C8,Pipeline_Completo!$V$2:$V$8801,"Esfriando")+SUMIFS(Pipeline_Completo!$S$2:$S$8801,Pipeline_Completo!$D$2:$D$8801,$C8,Pipeline_Completo!$V$2:$V$8801,"Última chance") -> 0 | O8: =COUNTIFS(Pipeline_Completo!$D$2:$D$8801,$C8,Pipeline_Completo!$V$2:$V$8801,"Zumbi") -> 33 | P8: =SUMIFS(Pipeline_Completo!$S$2:$S$8801,Pipeline_Completo!$D$2:$D$8801,$C8,Pipeline_Completo!$V$2:$V$8801,"Zumbi") -> 39704 | Q8: =IFERROR(P8/(N8+P8),"") -> 1 | R8: =COUNTIFS(Pipeline_Completo!$D$2:$D$8801,$C8,Pipeline_Completo!$O$2:$O$8801,"Engaging",Pipeline_Completo!$E$2:$E$8801,"")+COUNTIFS(Pipeline_Completo!$D$2:$D$8801,$C8,Pipeline_Completo!$O$2:$O$8801,"Prospecting",Pipeline_Completo!$E$2:$E$8801,"") -> 58
A9: Central | B9: Melvin Marxen | C9: Marty Freudenburg | D9: =COUNTIFS(Pipeline_Completo!$D$2:$D$8801,$C9) -> 281 | E9: =COUNTIFS(Pipeline_Completo!$D$2:$D$8801,$C9,Pipeline_Completo!$O$2:$O$8801,"Won") -> 122 | F9: =COUNTIFS(Pipeline_Completo!$D$2:$D$8801,$C9,Pipeline_Completo!$O$2:$O$8801,"Lost") -> 72 | G9: =COUNTIFS(Pipeline_Completo!$D$2:$D$8801,$C9,Pipeline_Completo!$O$2:$O$8801,"Engaging") -> 33 | H9: =COUNTIFS(Pipeline_Completo!$D$2:$D$8801,$C9,Pipeline_Completo!$O$2:$O$8801,"Prospecting") -> 54 | I9: =IFERROR(E9/(E9+F9),"") -> 0.62886598 | J9: =SUMIFS(Pipeline_Completo!$R$2:$R$8801,Pipeline_Completo!$D$2:$D$8801,$C9,Pipeline_Completo!$O$2:$O$8801,"Won") -> 291195 | K9: =IFERROR(J9/E9,"") -> 2386.8443 | L9: =SUMIFS(Pipeline_Completo!$S$2:$S$8801,Pipeline_Completo!$D$2:$D$8801,$C9,Pipeline_Completo!$O$2:$O$8801,"Engaging")+SUMIFS(Pipeline_Completo!$S$2:$S$8801,Pipeline_Completo!$D$2:$D$8801,$C9,Pipeline_Completo!$O$2:$O$8801,"Prospecting") -> 229445 | M9: =COUNTIFS(Pipeline_Completo!$D$2:$D$8801,$C9,Pipeline_Completo!$V$2:$V$8801,"Saudável")+COUNTIFS(Pipeline_Completo!$D$2:$D$8801,$C9,Pipeline_Completo!$V$2:$V$8801,"Esfriando")+COUNTIFS(Pipeline_Completo!$D$2:$D$8801,$C9,Pipeline_Completo!$V$2:$V$8801,"Última chance") -> 0 | N9: =SUMIFS(Pipeline_Completo!$S$2:$S$8801,Pipeline_Completo!$D$2:$D$8801,$C9,Pipeline_Completo!$V$2:$V$8801,"Saudável")+SUMIFS(Pipeline_Completo!$S$2:$S$8801,Pipeline_Completo!$D$2:$D$8801,$C9,Pipeline_Completo!$V$2:$V$8801,"Esfriando")+SUMIFS(Pipeline_Completo!$S$2:$S$8801,Pipeline_Completo!$D$2:$D$8801,$C9,Pipeline_Completo!$V$2:$V$8801,"Última chance") -> 0 | O9: =COUNTIFS(Pipeline_Completo!$D$2:$D$8801,$C9,Pipeline_Completo!$V$2:$V$8801,"Zumbi") -> 33 | P9: =SUMIFS(Pipeline_Completo!$S$2:$S$8801,Pipeline_Completo!$D$2:$D$8801,$C9,Pipeline_Completo!$V$2:$V$8801,"Zumbi") -> 108803 | Q9: =IFERROR(P9/(N9+P9),"") -> 1 | R9: =COUNTIFS(Pipeline_Completo!$D$2:$D$8801,$C9,Pipeline_Completo!$O$2:$O$8801,"Engaging",Pipeline_Completo!$E$2:$E$8801,"")+COUNTIFS(Pipeline_Completo!$D$2:$D$8801,$C9,Pipeline_Completo!$O$2:$O$8801,"Prospecting",Pipeline_Completo!$E$2:$E$8801,"") -> 53
A10: Central | B10: Melvin Marxen | C10: Gladys Colclough | D10: =COUNTIFS(Pipeline_Completo!$D$2:$D$8801,$C10) -> 317 | E10: =COUNTIFS(Pipeline_Completo!$D$2:$D$8801,$C10,Pipeline_Completo!$O$2:$O$8801,"Won") -> 135 | F10: =COUNTIFS(Pipeline_Completo!$D$2:$D$8801,$C10,Pipeline_Completo!$O$2:$O$8801,"Lost") -> 97 | G10: =COUNTIFS(Pipeline_Completo!$D$2:$D$8801,$C10,Pipeline_Completo!$O$2:$O$8801,"Engaging") -> 36 | H10: =COUNTIFS(Pipeline_Completo!$D$2:$D$8801,$C10,Pipeline_Completo!$O$2:$O$8801,"Prospecting") -> 49 | I10: =IFERROR(E10/(E10+F10),"") -> 0.58189655 | J10: =SUMIFS(Pipeline_Completo!$R$2:$R$8801,Pipeline_Completo!$D$2:$D$8801,$C10,Pipeline_Completo!$O$2:$O$8801,"Won") -> 345674 | K10: =IFERROR(J10/E10,"") -> 2560.5481 | L10: =SUMIFS(Pipeline_Completo!$S$2:$S$8801,Pipeline_Completo!$D$2:$D$8801,$C10,Pipeline_Completo!$O$2:$O$8801,"Engaging")+SUMIFS(Pipeline_Completo!$S$2:$S$8801,Pipeline_Completo!$D$2:$D$8801,$C10,Pipeline_Completo!$O$2:$O$8801,"Prospecting") -> 192142 | M10: =COUNTIFS(Pipeline_Completo!$D$2:$D$8801,$C10,Pipeline_Completo!$V$2:$V$8801,"Saudável")+COUNTIFS(Pipeline_Completo!$D$2:$D$8801,$C10,Pipeline_Completo!$V$2:$V$8801,"Esfriando")+COUNTIFS(Pipeline_Completo!$D$2:$D$8801,$C10,Pipeline_Completo!$V$2:$V$8801,"Última chance") -> 0 | N10: =SUMIFS(Pipeline_Completo!$S$2:$S$8801,Pipeline_Completo!$D$2:$D$8801,$C10,Pipeline_Completo!$V$2:$V$8801,"Saudável")+SUMIFS(Pipeline_Completo!$S$2:$S$8801,Pipeline_Completo!$D$2:$D$8801,$C10,Pipeline_Completo!$V$2:$V$8801,"Esfriando")+SUMIFS(Pipeline_Completo!$S$2:$S$8801,Pipeline_Completo!$D$2:$D$8801,$C10,Pipeline_Completo!$V$2:$V$8801,"Última chance") -> 0 | O10: =COUNTIFS(Pipeline_Completo!$D$2:$D$8801,$C10,Pipeline_Completo!$V$2:$V$8801,"Zumbi") -> 36 | P10: =SUMIFS(Pipeline_Completo!$S$2:$S$8801,Pipeline_Completo!$D$2:$D$8801,$C10,Pipeline_Completo!$V$2:$V$8801,"Zumbi") -> 62513 | Q10: =IFERROR(P10/(N10+P10),"") -> 1 | R10: =COUNTIFS(Pipeline_Completo!$D$2:$D$8801,$C10,Pipeline_Completo!$O$2:$O$8801,"Engaging",Pipeline_Completo!$E$2:$E$8801,"")+COUNTIFS(Pipeline_Completo!$D$2:$D$8801,$C10,Pipeline_Completo!$O$2:$O$8801,"Prospecting",Pipeline_Completo!$E$2:$E$8801,"") -> 55
A11: Central | B11: Melvin Marxen | C11: Niesha Huffines | D11: =COUNTIFS(Pipeline_Completo!$D$2:$D$8801,$C11) -> 239 | E11: =COUNTIFS(Pipeline_Completo!$D$2:$D$8801,$C11,Pipeline_Completo!$O$2:$O$8801,"Won") -> 105 | F11: =COUNTIFS(Pipeline_Completo!$D$2:$D$8801,$C11,Pipeline_Completo!$O$2:$O$8801,"Lost") -> 70 | G11: =COUNTIFS(Pipeline_Completo!$D$2:$D$8801,$C11,Pipeline_Completo!$O$2:$O$8801,"Engaging") -> 30 | H11: =COUNTIFS(Pipeline_Completo!$D$2:$D$8801,$C11,Pipeline_Completo!$O$2:$O$8801,"Prospecting") -> 34 | I11: =IFERROR(E11/(E11+F11),"") -> 0.6 | J11: =SUMIFS(Pipeline_Completo!$R$2:$R$8801,Pipeline_Completo!$D$2:$D$8801,$C11,Pipeline_Completo!$O$2:$O$8801,"Won") -> 176961 | K11: =IFERROR(J11/E11,"") -> 1685.3429 | L11: =SUMIFS(Pipeline_Completo!$S$2:$S$8801,Pipeline_Completo!$D$2:$D$8801,$C11,Pipeline_Completo!$O$2:$O$8801,"Engaging")+SUMIFS(Pipeline_Completo!$S$2:$S$8801,Pipeline_Completo!$D$2:$D$8801,$C11,Pipeline_Completo!$O$2:$O$8801,"Prospecting") -> 107745 | M11: =COUNTIFS(Pipeline_Completo!$D$2:$D$8801,$C11,Pipeline_Completo!$V$2:$V$8801,"Saudável")+COUNTIFS(Pipeline_Completo!$D$2:$D$8801,$C11,Pipeline_Completo!$V$2:$V$8801,"Esfriando")+COUNTIFS(Pipeline_Completo!$D$2:$D$8801,$C11,Pipeline_Completo!$V$2:$V$8801,"Última chance") -> 2 | N11: =SUMIFS(Pipeline_Completo!$S$2:$S$8801,Pipeline_Completo!$D$2:$D$8801,$C11,Pipeline_Completo!$V$2:$V$8801,"Saudável")+SUMIFS(Pipeline_Completo!$S$2:$S$8801,Pipeline_Completo!$D$2:$D$8801,$C11,Pipeline_Completo!$V$2:$V$8801,"Esfriando")+SUMIFS(Pipeline_Completo!$S$2:$S$8801,Pipeline_Completo!$D$2:$D$8801,$C11,Pipeline_Completo!$V$2:$V$8801,"Última chance") -> 5917 | O11: =COUNTIFS(Pipeline_Completo!$D$2:$D$8801,$C11,Pipeline_Completo!$V$2:$V$8801,"Zumbi") -> 28 | P11: =SUMIFS(Pipeline_Completo!$S$2:$S$8801,Pipeline_Completo!$D$2:$D$8801,$C11,Pipeline_Completo!$V$2:$V$8801,"Zumbi") -> 51012 | Q11: =IFERROR(P11/(N11+P11),"") -> 0.89606352 | R11: =COUNTIFS(Pipeline_Completo!$D$2:$D$8801,$C11,Pipeline_Completo!$O$2:$O$8801,"Engaging",Pipeline_Completo!$E$2:$E$8801,"")+COUNTIFS(Pipeline_Completo!$D$2:$D$8801,$C11,Pipeline_Completo!$O$2:$O$8801,"Prospecting",Pipeline_Completo!$E$2:$E$8801,"") -> 39
A12: Central | B12: Melvin Marxen | C12: Darcel Schlecht | D12: =COUNTIFS(Pipeline_Completo!$D$2:$D$8801,$C12) -> 747 | E12: =COUNTIFS(Pipeline_Completo!$D$2:$D$8801,$C12,Pipeline_Completo!$O$2:$O$8801,"Won") -> 349 | F12: =COUNTIFS(Pipeline_Completo!$D$2:$D$8801,$C12,Pipeline_Completo!$O$2:$O$8801,"Lost") -> 204 | G12: =COUNTIFS(Pipeline_Completo!$D$2:$D$8801,$C12,Pipeline_Completo!$O$2:$O$8801,"Engaging") -> 83 | H12: =COUNTIFS(Pipeline_Completo!$D$2:$D$8801,$C12,Pipeline_Completo!$O$2:$O$8801,"Prospecting") -> 111 | I12: =IFERROR(E12/(E12+F12),"") -> 0.63110307 | J12: =SUMIFS(Pipeline_Completo!$R$2:$R$8801,Pipeline_Completo!$D$2:$D$8801,$C12,Pipeline_Completo!$O$2:$O$8801,"Won") -> 1153214 | K12: =IFERROR(J12/E12,"") -> 3304.3381 | L12: =SUMIFS(Pipeline_Completo!$S$2:$S$8801,Pipeline_Completo!$D$2:$D$8801,$C12,Pipeline_Completo!$O$2:$O$8801,"Engaging")+SUMIFS(Pipeline_Completo!$S$2:$S$8801,Pipeline_Completo!$D$2:$D$8801,$C12,Pipeline_Completo!$O$2:$O$8801,"Prospecting") -> 656040 | M12: =COUNTIFS(Pipeline_Completo!$D$2:$D$8801,$C12,Pipeline_Completo!$V$2:$V$8801,"Saudável")+COUNTIFS(Pipeline_Completo!$D$2:$D$8801,$C12,Pipeline_Completo!$V$2:$V$8801,"Esfriando")+COUNTIFS(Pipeline_Completo!$D$2:$D$8801,$C12,Pipeline_Completo!$V$2:$V$8801,"Última chance") -> 0 | N12: =SUMIFS(Pipeline_Completo!$S$2:$S$8801,Pipeline_Completo!$D$2:$D$8801,$C12,Pipeline_Completo!$V$2:$V$8801,"Saudável")+SUMIFS(Pipeline_Completo!$S$2:$S$8801,Pipeline_Completo!$D$2:$D$8801,$C12,Pipeline_Completo!$V$2:$V$8801,"Esfriando")+SUMIFS(Pipeline_Completo!$S$2:$S$8801,Pipeline_Completo!$D$2:$D$8801,$C12,Pipeline_Completo!$V$2:$V$8801,"Última chance") -> 0 | O12: =COUNTIFS(Pipeline_Completo!$D$2:$D$8801,$C12,Pipeline_Completo!$V$2:$V$8801,"Zumbi") -> 83 | P12: =SUMIFS(Pipeline_Completo!$S$2:$S$8801,Pipeline_Completo!$D$2:$D$8801,$C12,Pipeline_Completo!$V$2:$V$8801,"Zumbi") -> 273766 | Q12: =IFERROR(P12/(N12+P12),"") -> 1 | R12: =COUNTIFS(Pipeline_Completo!$D$2:$D$8801,$C12,Pipeline_Completo!$O$2:$O$8801,"Engaging",Pipeline_Completo!$E$2:$E$8801,"")+COUNTIFS(Pipeline_Completo!$D$2:$D$8801,$C12,Pipeline_Completo!$O$2:$O$8801,"Prospecting",Pipeline_Completo!$E$2:$E$8801,"") -> 134
A13: Central | B13: Melvin Marxen | C13: Mei-Mei Johns | D13: =COUNTIFS(Pipeline_Completo!$D$2:$D$8801,$C13) -> 0 | E13: =COUNTIFS(Pipeline_Completo!$D$2:$D$8801,$C13,Pipeline_Completo!$O$2:$O$8801,"Won") -> 0 | F13: =COUNTIFS(Pipeline_Completo!$D$2:$D$8801,$C13,Pipeline_Completo!$O$2:$O$8801,"Lost") -> 0 | G13: =COUNTIFS(Pipeline_Completo!$D$2:$D$8801,$C13,Pipeline_Completo!$O$2:$O$8801,"Engaging") -> 0 | H13: =COUNTIFS(Pipeline_Completo!$D$2:$D$8801,$C13,Pipeline_Completo!$O$2:$O$8801,"Prospecting") -> 0 | I13: =IFERROR(E13/(E13+F13),"") | J13: =SUMIFS(Pipeline_Completo!$R$2:$R$8801,Pipeline_Completo!$D$2:$D$8801,$C13,Pipeline_Completo!$O$2:$O$8801,"Won") -> 0 | K13: =IFERROR(J13/E13,"") | L13: =SUMIFS(Pipeline_Completo!$S$2:$S$8801,Pipeline_Completo!$D$2:$D$8801,$C13,Pipeline_Completo!$O$2:$O$8801,"Engaging")+SUMIFS(Pipeline_Completo!$S$2:$S$8801,Pipeline_Completo!$D$2:$D$8801,$C13,Pipeline_Completo!$O$2:$O$8801,"Prospecting") -> 0 | M13: =COUNTIFS(Pipeline_Completo!$D$2:$D$8801,$C13,Pipeline_Completo!$V$2:$V$8801,"Saudável")+COUNTIFS(Pipeline_Completo!$D$2:$D$8801,$C13,Pipeline_Completo!$V$2:$V$8801,"Esfriando")+COUNTIFS(Pipeline_Completo!$D$2:$D$8801,$C13,Pipeline_Completo!$V$2:$V$8801,"Última chance") -> 0 | N13: =SUMIFS(Pipeline_Completo!$S$2:$S$8801,Pipeline_Completo!$D$2:$D$8801,$C13,Pipeline_Completo!$V$2:$V$8801,"Saudável")+SUMIFS(Pipeline_Completo!$S$2:$S$8801,Pipeline_Completo!$D$2:$D$8801,$C13,Pipeline_Completo!$V$2:$V$8801,"Esfriando")+SUMIFS(Pipeline_Completo!$S$2:$S$8801,Pipeline_Completo!$D$2:$D$8801,$C13,Pipeline_Completo!$V$2:$V$8801,"Última chance") -> 0 | O13: =COUNTIFS(Pipeline_Completo!$D$2:$D$8801,$C13,Pipeline_Completo!$V$2:$V$8801,"Zumbi") -> 0 | P13: =SUMIFS(Pipeline_Completo!$S$2:$S$8801,Pipeline_Completo!$D$2:$D$8801,$C13,Pipeline_Completo!$V$2:$V$8801,"Zumbi") -> 0 | Q13: =IFERROR(P13/(N13+P13),"") | R13: =COUNTIFS(Pipeline_Completo!$D$2:$D$8801,$C13,Pipeline_Completo!$O$2:$O$8801,"Engaging",Pipeline_Completo!$E$2:$E$8801,"")+COUNTIFS(Pipeline_Completo!$D$2:$D$8801,$C13,Pipeline_Completo!$O$2:$O$8801,"Prospecting",Pipeline_Completo!$E$2:$E$8801,"") -> 0
A14: Central | B14: Melvin Marxen | C14: Subtotal Melvin Marxen | D14: =COUNTIFS(Pipeline_Completo!$C$2:$C$8801,$B14) -> 1929 | E14: =COUNTIFS(Pipeline_Completo!$C$2:$C$8801,$B14,Pipeline_Completo!$O$2:$O$8801,"Won") -> 882 | F14: =COUNTIFS(Pipeline_Completo!$C$2:$C$8801,$B14,Pipeline_Completo!$O$2:$O$8801,"Lost") -> 536 | G14: =COUNTIFS(Pipeline_Completo!$C$2:$C$8801,$B14,Pipeline_Completo!$O$2:$O$8801,"Engaging") -> 215 | H14: =COUNTIFS(Pipeline_Completo!$C$2:$C$8801,$B14,Pipeline_Completo!$O$2:$O$8801,"Prospecting") -> 296 | I14: =IFERROR(E14/(E14+F14),"") -> 0.62200282 | J14: =SUMIFS(Pipeline_Completo!$R$2:$R$8801,Pipeline_Completo!$C$2:$C$8801,$B14,Pipeline_Completo!$O$2:$O$8801,"Won") -> 2251930 | K14: =IFERROR(J14/E14,"") -> 2553.2086 | L14: =SUMIFS(Pipeline_Completo!$S$2:$S$8801,Pipeline_Completo!$C$2:$C$8801,$B14,Pipeline_Completo!$O$2:$O$8801,"Engaging")+SUMIFS(Pipeline_Completo!$S$2:$S$8801,Pipeline_Completo!$C$2:$C$8801,$B14,Pipeline_Completo!$O$2:$O$8801,"Prospecting") -> 1312792 | M14: =COUNTIFS(Pipeline_Completo!$C$2:$C$8801,$B14,Pipeline_Completo!$V$2:$V$8801,"Saudável")+COUNTIFS(Pipeline_Completo!$C$2:$C$8801,$B14,Pipeline_Completo!$V$2:$V$8801,"Esfriando")+COUNTIFS(Pipeline_Completo!$C$2:$C$8801,$B14,Pipeline_Completo!$V$2:$V$8801,"Última chance") -> 2 | N14: =SUMIFS(Pipeline_Completo!$S$2:$S$8801,Pipeline_Completo!$C$2:$C$8801,$B14,Pipeline_Completo!$V$2:$V$8801,"Saudável")+SUMIFS(Pipeline_Completo!$S$2:$S$8801,Pipeline_Completo!$C$2:$C$8801,$B14,Pipeline_Completo!$V$2:$V$8801,"Esfriando")+SUMIFS(Pipeline_Completo!$S$2:$S$8801,Pipeline_Completo!$C$2:$C$8801,$B14,Pipeline_Completo!$V$2:$V$8801,"Última chance") -> 5917 | O14: =COUNTIFS(Pipeline_Completo!$C$2:$C$8801,$B14,Pipeline_Completo!$V$2:$V$8801,"Zumbi") -> 213 | P14: =SUMIFS(Pipeline_Completo!$S$2:$S$8801,Pipeline_Completo!$C$2:$C$8801,$B14,Pipeline_Completo!$V$2:$V$8801,"Zumbi") -> 535798 | Q14: =IFERROR(P14/(N14+P14),"") -> 0.98907728 | R14: =COUNTIFS(Pipeline_Completo!$C$2:$C$8801,$B14,Pipeline_Completo!$O$2:$O$8801,"Engaging",Pipeline_Completo!$E$2:$E$8801,"")+COUNTIFS(Pipeline_Completo!$C$2:$C$8801,$B14,Pipeline_Completo!$O$2:$O$8801,"Prospecting",Pipeline_Completo!$E$2:$E$8801,"") -> 339
A15: Central | C15: TOTAL escritório Central | D15: =COUNTIFS(Pipeline_Completo!$B$2:$B$8801,$A15) -> 3512 | E15: =COUNTIFS(Pipeline_Completo!$B$2:$B$8801,$A15,Pipeline_Completo!$O$2:$O$8801,"Won") -> 1629 | F15: =COUNTIFS(Pipeline_Completo!$B$2:$B$8801,$A15,Pipeline_Completo!$O$2:$O$8801,"Lost") -> 975 | G15: =COUNTIFS(Pipeline_Completo!$B$2:$B$8801,$A15,Pipeline_Completo!$O$2:$O$8801,"Engaging") -> 408 | H15: =COUNTIFS(Pipeline_Completo!$B$2:$B$8801,$A15,Pipeline_Completo!$O$2:$O$8801,"Prospecting") -> 500 | I15: =IFERROR(E15/(E15+F15),"") -> 0.62557604 | J15: =SUMIFS(Pipeline_Completo!$R$2:$R$8801,Pipeline_Completo!$B$2:$B$8801,$A15,Pipeline_Completo!$O$2:$O$8801,"Won") -> 3346293 | K15: =IFERROR(J15/E15,"") -> 2054.2007 | L15: =SUMIFS(Pipeline_Completo!$S$2:$S$8801,Pipeline_Completo!$B$2:$B$8801,$A15,Pipeline_Completo!$O$2:$O$8801,"Engaging")+SUMIFS(Pipeline_Completo!$S$2:$S$8801,Pipeline_Completo!$B$2:$B$8801,$A15,Pipeline_Completo!$O$2:$O$8801,"Prospecting") -> 1898408 | M15: =COUNTIFS(Pipeline_Completo!$B$2:$B$8801,$A15,Pipeline_Completo!$V$2:$V$8801,"Saudável")+COUNTIFS(Pipeline_Completo!$B$2:$B$8801,$A15,Pipeline_Completo!$V$2:$V$8801,"Esfriando")+COUNTIFS(Pipeline_Completo!$B$2:$B$8801,$A15,Pipeline_Completo!$V$2:$V$8801,"Última chance") -> 5 | N15: =SUMIFS(Pipeline_Completo!$S$2:$S$8801,Pipeline_Completo!$B$2:$B$8801,$A15,Pipeline_Completo!$V$2:$V$8801,"Saudável")+SUMIFS(Pipeline_Completo!$S$2:$S$8801,Pipeline_Completo!$B$2:$B$8801,$A15,Pipeline_Completo!$V$2:$V$8801,"Esfriando")+SUMIFS(Pipeline_Completo!$S$2:$S$8801,Pipeline_Completo!$B$2:$B$8801,$A15,Pipeline_Completo!$V$2:$V$8801,"Última chance") -> 6577 | O15: =COUNTIFS(Pipeline_Completo!$B$2:$B$8801,$A15,Pipeline_Completo!$V$2:$V$8801,"Zumbi") -> 403 | P15: =SUMIFS(Pipeline_Completo!$S$2:$S$8801,Pipeline_Completo!$B$2:$B$8801,$A15,Pipeline_Completo!$V$2:$V$8801,"Zumbi") -> 817845 | Q15: =IFERROR(P15/(N15+P15),"") -> 0.99202229 | R15: =COUNTIFS(Pipeline_Completo!$B$2:$B$8801,$A15,Pipeline_Completo!$O$2:$O$8801,"Engaging",Pipeline_Completo!$E$2:$E$8801,"")+COUNTIFS(Pipeline_Completo!$B$2:$B$8801,$A15,Pipeline_Completo!$O$2:$O$8801,"Prospecting",Pipeline_Completo!$E$2:$E$8801,"") -> 611
A17: East | B17: Cara Losch | C17: Violet Mclelland | D17: =COUNTIFS(Pipeline_Completo!$D$2:$D$8801,$C17) -> 261 | E17: =COUNTIFS(Pipeline_Completo!$D$2:$D$8801,$C17,Pipeline_Completo!$O$2:$O$8801,"Won") -> 122 | F17: =COUNTIFS(Pipeline_Completo!$D$2:$D$8801,$C17,Pipeline_Completo!$O$2:$O$8801,"Lost") -> 71 | G17: =COUNTIFS(Pipeline_Completo!$D$2:$D$8801,$C17,Pipeline_Completo!$O$2:$O$8801,"Engaging") -> 68 | H17: =COUNTIFS(Pipeline_Completo!$D$2:$D$8801,$C17,Pipeline_Completo!$O$2:$O$8801,"Prospecting") -> 0 | I17: =IFERROR(E17/(E17+F17),"") -> 0.63212435 | J17: =SUMIFS(Pipeline_Completo!$R$2:$R$8801,Pipeline_Completo!$D$2:$D$8801,$C17,Pipeline_Completo!$O$2:$O$8801,"Won") -> 123431 | K17: =IFERROR(J17/E17,"") -> 1011.7295 | L17: =SUMIFS(Pipeline_Completo!$S$2:$S$8801,Pipeline_Completo!$D$2:$D$8801,$C17,Pipeline_Completo!$O$2:$O$8801,"Engaging")+SUMIFS(Pipeline_Completo!$S$2:$S$8801,Pipeline_Completo!$D$2:$D$8801,$C17,Pipeline_Completo!$O$2:$O$8801,"Prospecting") -> 80150 | M17: =COUNTIFS(Pipeline_Completo!$D$2:$D$8801,$C17,Pipeline_Completo!$V$2:$V$8801,"Saudável")+COUNTIFS(Pipeline_Completo!$D$2:$D$8801,$C17,Pipeline_Completo!$V$2:$V$8801,"Esfriando")+COUNTIFS(Pipeline_Completo!$D$2:$D$8801,$C17,Pipeline_Completo!$V$2:$V$8801,"Última chance") -> 17 | N17: =SUMIFS(Pipeline_Completo!$S$2:$S$8801,Pipeline_Completo!$D$2:$D$8801,$C17,Pipeline_Completo!$V$2:$V$8801,"Saudável")+SUMIFS(Pipeline_Completo!$S$2:$S$8801,Pipeline_Completo!$D$2:$D$8801,$C17,Pipeline_Completo!$V$2:$V$8801,"Esfriando")+SUMIFS(Pipeline_Completo!$S$2:$S$8801,Pipeline_Completo!$D$2:$D$8801,$C17,Pipeline_Completo!$V$2:$V$8801,"Última chance") -> 12606 | O17: =COUNTIFS(Pipeline_Completo!$D$2:$D$8801,$C17,Pipeline_Completo!$V$2:$V$8801,"Zumbi") -> 51 | P17: =SUMIFS(Pipeline_Completo!$S$2:$S$8801,Pipeline_Completo!$D$2:$D$8801,$C17,Pipeline_Completo!$V$2:$V$8801,"Zumbi") -> 67544 | Q17: =IFERROR(P17/(N17+P17),"") -> 0.8427199 | R17: =COUNTIFS(Pipeline_Completo!$D$2:$D$8801,$C17,Pipeline_Completo!$O$2:$O$8801,"Engaging",Pipeline_Completo!$E$2:$E$8801,"")+COUNTIFS(Pipeline_Completo!$D$2:$D$8801,$C17,Pipeline_Completo!$O$2:$O$8801,"Prospecting",Pipeline_Completo!$E$2:$E$8801,"") -> 48
A18: East | B18: Cara Losch | C18: Corliss Cosme | D18: =COUNTIFS(Pipeline_Completo!$D$2:$D$8801,$C18) -> 310 | E18: =COUNTIFS(Pipeline_Completo!$D$2:$D$8801,$C18,Pipeline_Completo!$O$2:$O$8801,"Won") -> 150 | F18: =COUNTIFS(Pipeline_Completo!$D$2:$D$8801,$C18,Pipeline_Completo!$O$2:$O$8801,"Lost") -> 79 | G18: =COUNTIFS(Pipeline_Completo!$D$2:$D$8801,$C18,Pipeline_Completo!$O$2:$O$8801,"Engaging") -> 81 | H18: =COUNTIFS(Pipeline_Completo!$D$2:$D$8801,$C18,Pipeline_Completo!$O$2:$O$8801,"Prospecting") -> 0 | I18: =IFERROR(E18/(E18+F18),"") -> 0.65502183 | J18: =SUMIFS(Pipeline_Completo!$R$2:$R$8801,Pipeline_Completo!$D$2:$D$8801,$C18,Pipeline_Completo!$O$2:$O$8801,"Won") -> 421036 | K18: =IFERROR(J18/E18,"") -> 2806.9067 | L18: =SUMIFS(Pipeline_Completo!$S$2:$S$8801,Pipeline_Completo!$D$2:$D$8801,$C18,Pipeline_Completo!$O$2:$O$8801,"Engaging")+SUMIFS(Pipeline_Completo!$S$2:$S$8801,Pipeline_Completo!$D$2:$D$8801,$C18,Pipeline_Completo!$O$2:$O$8801,"Prospecting") -> 216840 | M18: =COUNTIFS(Pipeline_Completo!$D$2:$D$8801,$C18,Pipeline_Completo!$V$2:$V$8801,"Saudável")+COUNTIFS(Pipeline_Completo!$D$2:$D$8801,$C18,Pipeline_Completo!$V$2:$V$8801,"Esfriando")+COUNTIFS(Pipeline_Completo!$D$2:$D$8801,$C18,Pipeline_Completo!$V$2:$V$8801,"Última chance") -> 18 | N18: =SUMIFS(Pipeline_Completo!$S$2:$S$8801,Pipeline_Completo!$D$2:$D$8801,$C18,Pipeline_Completo!$V$2:$V$8801,"Saudável")+SUMIFS(Pipeline_Completo!$S$2:$S$8801,Pipeline_Completo!$D$2:$D$8801,$C18,Pipeline_Completo!$V$2:$V$8801,"Esfriando")+SUMIFS(Pipeline_Completo!$S$2:$S$8801,Pipeline_Completo!$D$2:$D$8801,$C18,Pipeline_Completo!$V$2:$V$8801,"Última chance") -> 56886 | O18: =COUNTIFS(Pipeline_Completo!$D$2:$D$8801,$C18,Pipeline_Completo!$V$2:$V$8801,"Zumbi") -> 63 | P18: =SUMIFS(Pipeline_Completo!$S$2:$S$8801,Pipeline_Completo!$D$2:$D$8801,$C18,Pipeline_Completo!$V$2:$V$8801,"Zumbi") -> 159954 | Q18: =IFERROR(P18/(N18+P18),"") -> 0.7376591 | R18: =COUNTIFS(Pipeline_Completo!$D$2:$D$8801,$C18,Pipeline_Completo!$O$2:$O$8801,"Engaging",Pipeline_Completo!$E$2:$E$8801,"")+COUNTIFS(Pipeline_Completo!$D$2:$D$8801,$C18,Pipeline_Completo!$O$2:$O$8801,"Prospecting",Pipeline_Completo!$E$2:$E$8801,"") -> 54
A19: East | B19: Cara Losch | C19: Rosie Papadopoulos | D19: =COUNTIFS(Pipeline_Completo!$D$2:$D$8801,$C19) -> 160 | E19: =COUNTIFS(Pipeline_Completo!$D$2:$D$8801,$C19,Pipeline_Completo!$O$2:$O$8801,"Won") -> 78 | F19: =COUNTIFS(Pipeline_Completo!$D$2:$D$8801,$C19,Pipeline_Completo!$O$2:$O$8801,"Lost") -> 43 | G19: =COUNTIFS(Pipeline_Completo!$D$2:$D$8801,$C19,Pipeline_Completo!$O$2:$O$8801,"Engaging") -> 39 | H19: =COUNTIFS(Pipeline_Completo!$D$2:$D$8801,$C19,Pipeline_Completo!$O$2:$O$8801,"Prospecting") -> 0 | I19: =IFERROR(E19/(E19+F19),"") -> 0.6446281 | J19: =SUMIFS(Pipeline_Completo!$R$2:$R$8801,Pipeline_Completo!$D$2:$D$8801,$C19,Pipeline_Completo!$O$2:$O$8801,"Won") -> 230169 | K19: =IFERROR(J19/E19,"") -> 2950.8846 | L19: =SUMIFS(Pipeline_Completo!$S$2:$S$8801,Pipeline_Completo!$D$2:$D$8801,$C19,Pipeline_Completo!$O$2:$O$8801,"Engaging")+SUMIFS(Pipeline_Completo!$S$2:$S$8801,Pipeline_Completo!$D$2:$D$8801,$C19,Pipeline_Completo!$O$2:$O$8801,"Prospecting") -> 116685 | M19: =COUNTIFS(Pipeline_Completo!$D$2:$D$8801,$C19,Pipeline_Completo!$V$2:$V$8801,"Saudável")+COUNTIFS(Pipeline_Completo!$D$2:$D$8801,$C19,Pipeline_Completo!$V$2:$V$8801,"Esfriando")+COUNTIFS(Pipeline_Completo!$D$2:$D$8801,$C19,Pipeline_Completo!$V$2:$V$8801,"Última chance") -> 6 | N19: =SUMIFS(Pipeline_Completo!$S$2:$S$8801,Pipeline_Completo!$D$2:$D$8801,$C19,Pipeline_Completo!$V$2:$V$8801,"Saudável")+SUMIFS(Pipeline_Completo!$S$2:$S$8801,Pipeline_Completo!$D$2:$D$8801,$C19,Pipeline_Completo!$V$2:$V$8801,"Esfriando")+SUMIFS(Pipeline_Completo!$S$2:$S$8801,Pipeline_Completo!$D$2:$D$8801,$C19,Pipeline_Completo!$V$2:$V$8801,"Última chance") -> 23227 | O19: =COUNTIFS(Pipeline_Completo!$D$2:$D$8801,$C19,Pipeline_Completo!$V$2:$V$8801,"Zumbi") -> 33 | P19: =SUMIFS(Pipeline_Completo!$S$2:$S$8801,Pipeline_Completo!$D$2:$D$8801,$C19,Pipeline_Completo!$V$2:$V$8801,"Zumbi") -> 93458 | Q19: =IFERROR(P19/(N19+P19),"") -> 0.80094271 | R19: =COUNTIFS(Pipeline_Completo!$D$2:$D$8801,$C19,Pipeline_Completo!$O$2:$O$8801,"Engaging",Pipeline_Completo!$E$2:$E$8801,"")+COUNTIFS(Pipeline_Completo!$D$2:$D$8801,$C19,Pipeline_Completo!$O$2:$O$8801,"Prospecting",Pipeline_Completo!$E$2:$E$8801,"") -> 24
A20: East | B20: Cara Losch | C20: Garret Kinder | D20: =COUNTIFS(Pipeline_Completo!$D$2:$D$8801,$C20) -> 123 | E20: =COUNTIFS(Pipeline_Completo!$D$2:$D$8801,$C20,Pipeline_Completo!$O$2:$O$8801,"Won") -> 75 | F20: =COUNTIFS(Pipeline_Completo!$D$2:$D$8801,$C20,Pipeline_Completo!$O$2:$O$8801,"Lost") -> 48 | G20: =COUNTIFS(Pipeline_Completo!$D$2:$D$8801,$C20,Pipeline_Completo!$O$2:$O$8801,"Engaging") -> 0 | H20: =COUNTIFS(Pipeline_Completo!$D$2:$D$8801,$C20,Pipeline_Completo!$O$2:$O$8801,"Prospecting") -> 0 | I20: =IFERROR(E20/(E20+F20),"") -> 0.6097561 | J20: =SUMIFS(Pipeline_Completo!$R$2:$R$8801,Pipeline_Completo!$D$2:$D$8801,$C20,Pipeline_Completo!$O$2:$O$8801,"Won") -> 197773 | K20: =IFERROR(J20/E20,"") -> 2636.9733 | L20: =SUMIFS(Pipeline_Completo!$S$2:$S$8801,Pipeline_Completo!$D$2:$D$8801,$C20,Pipeline_Completo!$O$2:$O$8801,"Engaging")+SUMIFS(Pipeline_Completo!$S$2:$S$8801,Pipeline_Completo!$D$2:$D$8801,$C20,Pipeline_Completo!$O$2:$O$8801,"Prospecting") -> 0 | M20: =COUNTIFS(Pipeline_Completo!$D$2:$D$8801,$C20,Pipeline_Completo!$V$2:$V$8801,"Saudável")+COUNTIFS(Pipeline_Completo!$D$2:$D$8801,$C20,Pipeline_Completo!$V$2:$V$8801,"Esfriando")+COUNTIFS(Pipeline_Completo!$D$2:$D$8801,$C20,Pipeline_Completo!$V$2:$V$8801,"Última chance") -> 0 | N20: =SUMIFS(Pipeline_Completo!$S$2:$S$8801,Pipeline_Completo!$D$2:$D$8801,$C20,Pipeline_Completo!$V$2:$V$8801,"Saudável")+SUMIFS(Pipeline_Completo!$S$2:$S$8801,Pipeline_Completo!$D$2:$D$8801,$C20,Pipeline_Completo!$V$2:$V$8801,"Esfriando")+SUMIFS(Pipeline_Completo!$S$2:$S$8801,Pipeline_Completo!$D$2:$D$8801,$C20,Pipeline_Completo!$V$2:$V$8801,"Última chance") -> 0 | O20: =COUNTIFS(Pipeline_Completo!$D$2:$D$8801,$C20,Pipeline_Completo!$V$2:$V$8801,"Zumbi") -> 0 | P20: =SUMIFS(Pipeline_Completo!$S$2:$S$8801,Pipeline_Completo!$D$2:$D$8801,$C20,Pipeline_Completo!$V$2:$V$8801,"Zumbi") -> 0 | Q20: =IFERROR(P20/(N20+P20),"") | R20: =COUNTIFS(Pipeline_Completo!$D$2:$D$8801,$C20,Pipeline_Completo!$O$2:$O$8801,"Engaging",Pipeline_Completo!$E$2:$E$8801,"")+COUNTIFS(Pipeline_Completo!$D$2:$D$8801,$C20,Pipeline_Completo!$O$2:$O$8801,"Prospecting",Pipeline_Completo!$E$2:$E$8801,"") -> 0
A21: East | B21: Cara Losch | C21: Wilburn Farren | D21: =COUNTIFS(Pipeline_Completo!$D$2:$D$8801,$C21) -> 110 | E21: =COUNTIFS(Pipeline_Completo!$D$2:$D$8801,$C21,Pipeline_Completo!$O$2:$O$8801,"Won") -> 55 | F21: =COUNTIFS(Pipeline_Completo!$D$2:$D$8801,$C21,Pipeline_Completo!$O$2:$O$8801,"Lost") -> 24 | G21: =COUNTIFS(Pipeline_Completo!$D$2:$D$8801,$C21,Pipeline_Completo!$O$2:$O$8801,"Engaging") -> 31 | H21: =COUNTIFS(Pipeline_Completo!$D$2:$D$8801,$C21,Pipeline_Completo!$O$2:$O$8801,"Prospecting") -> 0 | I21: =IFERROR(E21/(E21+F21),"") -> 0.69620253 | J21: =SUMIFS(Pipeline_Completo!$R$2:$R$8801,Pipeline_Completo!$D$2:$D$8801,$C21,Pipeline_Completo!$O$2:$O$8801,"Won") -> 157640 | K21: =IFERROR(J21/E21,"") -> 2866.1818 | L21: =SUMIFS(Pipeline_Completo!$S$2:$S$8801,Pipeline_Completo!$D$2:$D$8801,$C21,Pipeline_Completo!$O$2:$O$8801,"Engaging")+SUMIFS(Pipeline_Completo!$S$2:$S$8801,Pipeline_Completo!$D$2:$D$8801,$C21,Pipeline_Completo!$O$2:$O$8801,"Prospecting") -> 82275 | M21: =COUNTIFS(Pipeline_Completo!$D$2:$D$8801,$C21,Pipeline_Completo!$V$2:$V$8801,"Saudável")+COUNTIFS(Pipeline_Completo!$D$2:$D$8801,$C21,Pipeline_Completo!$V$2:$V$8801,"Esfriando")+COUNTIFS(Pipeline_Completo!$D$2:$D$8801,$C21,Pipeline_Completo!$V$2:$V$8801,"Última chance") -> 9 | N21: =SUMIFS(Pipeline_Completo!$S$2:$S$8801,Pipeline_Completo!$D$2:$D$8801,$C21,Pipeline_Completo!$V$2:$V$8801,"Saudável")+SUMIFS(Pipeline_Completo!$S$2:$S$8801,Pipeline_Completo!$D$2:$D$8801,$C21,Pipeline_Completo!$V$2:$V$8801,"Esfriando")+SUMIFS(Pipeline_Completo!$S$2:$S$8801,Pipeline_Completo!$D$2:$D$8801,$C21,Pipeline_Completo!$V$2:$V$8801,"Última chance") -> 30795 | O21: =COUNTIFS(Pipeline_Completo!$D$2:$D$8801,$C21,Pipeline_Completo!$V$2:$V$8801,"Zumbi") -> 22 | P21: =SUMIFS(Pipeline_Completo!$S$2:$S$8801,Pipeline_Completo!$D$2:$D$8801,$C21,Pipeline_Completo!$V$2:$V$8801,"Zumbi") -> 51480 | Q21: =IFERROR(P21/(N21+P21),"") -> 0.62570647 | R21: =COUNTIFS(Pipeline_Completo!$D$2:$D$8801,$C21,Pipeline_Completo!$O$2:$O$8801,"Engaging",Pipeline_Completo!$E$2:$E$8801,"")+COUNTIFS(Pipeline_Completo!$D$2:$D$8801,$C21,Pipeline_Completo!$O$2:$O$8801,"Prospecting",Pipeline_Completo!$E$2:$E$8801,"") -> 28
A22: East | B22: Cara Losch | C22: Elizabeth Anderson | D22: =COUNTIFS(Pipeline_Completo!$D$2:$D$8801,$C22) -> 0 | E22: =COUNTIFS(Pipeline_Completo!$D$2:$D$8801,$C22,Pipeline_Completo!$O$2:$O$8801,"Won") -> 0 | F22: =COUNTIFS(Pipeline_Completo!$D$2:$D$8801,$C22,Pipeline_Completo!$O$2:$O$8801,"Lost") -> 0 | G22: =COUNTIFS(Pipeline_Completo!$D$2:$D$8801,$C22,Pipeline_Completo!$O$2:$O$8801,"Engaging") -> 0 | H22: =COUNTIFS(Pipeline_Completo!$D$2:$D$8801,$C22,Pipeline_Completo!$O$2:$O$8801,"Prospecting") -> 0 | I22: =IFERROR(E22/(E22+F22),"") | J22: =SUMIFS(Pipeline_Completo!$R$2:$R$8801,Pipeline_Completo!$D$2:$D$8801,$C22,Pipeline_Completo!$O$2:$O$8801,"Won") -> 0 | K22: =IFERROR(J22/E22,"") | L22: =SUMIFS(Pipeline_Completo!$S$2:$S$8801,Pipeline_Completo!$D$2:$D$8801,$C22,Pipeline_Completo!$O$2:$O$8801,"Engaging")+SUMIFS(Pipeline_Completo!$S$2:$S$8801,Pipeline_Completo!$D$2:$D$8801,$C22,Pipeline_Completo!$O$2:$O$8801,"Prospecting") -> 0 | M22: =COUNTIFS(Pipeline_Completo!$D$2:$D$8801,$C22,Pipeline_Completo!$V$2:$V$8801,"Saudável")+COUNTIFS(Pipeline_Completo!$D$2:$D$8801,$C22,Pipeline_Completo!$V$2:$V$8801,"Esfriando")+COUNTIFS(Pipeline_Completo!$D$2:$D$8801,$C22,Pipeline_Completo!$V$2:$V$8801,"Última chance") -> 0 | N22: =SUMIFS(Pipeline_Completo!$S$2:$S$8801,Pipeline_Completo!$D$2:$D$8801,$C22,Pipeline_Completo!$V$2:$V$8801,"Saudável")+SUMIFS(Pipeline_Completo!$S$2:$S$8801,Pipeline_Completo!$D$2:$D$8801,$C22,Pipeline_Completo!$V$2:$V$8801,"Esfriando")+SUMIFS(Pipeline_Completo!$S$2:$S$8801,Pipeline_Completo!$D$2:$D$8801,$C22,Pipeline_Completo!$V$2:$V$8801,"Última chance") -> 0 | O22: =COUNTIFS(Pipeline_Completo!$D$2:$D$8801,$C22,Pipeline_Completo!$V$2:$V$8801,"Zumbi") -> 0 | P22: =SUMIFS(Pipeline_Completo!$S$2:$S$8801,Pipeline_Completo!$D$2:$D$8801,$C22,Pipeline_Completo!$V$2:$V$8801,"Zumbi") -> 0 | Q22: =IFERROR(P22/(N22+P22),"") | R22: =COUNTIFS(Pipeline_Completo!$D$2:$D$8801,$C22,Pipeline_Completo!$O$2:$O$8801,"Engaging",Pipeline_Completo!$E$2:$E$8801,"")+COUNTIFS(Pipeline_Completo!$D$2:$D$8801,$C22,Pipeline_Completo!$O$2:$O$8801,"Prospecting",Pipeline_Completo!$E$2:$E$8801,"") -> 0
A23: East | B23: Cara Losch | C23: Subtotal Cara Losch | D23: =COUNTIFS(Pipeline_Completo!$C$2:$C$8801,$B23) -> 964 | E23: =COUNTIFS(Pipeline_Completo!$C$2:$C$8801,$B23,Pipeline_Completo!$O$2:$O$8801,"Won") -> 480 | F23: =COUNTIFS(Pipeline_Completo!$C$2:$C$8801,$B23,Pipeline_Completo!$O$2:$O$8801,"Lost") -> 265 | G23: =COUNTIFS(Pipeline_Completo!$C$2:$C$8801,$B23,Pipeline_Completo!$O$2:$O$8801,"Engaging") -> 219 | H23: =COUNTIFS(Pipeline_Completo!$C$2:$C$8801,$B23,Pipeline_Completo!$O$2:$O$8801,"Prospecting") -> 0 | I23: =IFERROR(E23/(E23+F23),"") -> 0.6442953 | J23: =SUMIFS(Pipeline_Completo!$R$2:$R$8801,Pipeline_Completo!$C$2:$C$8801,$B23,Pipeline_Completo!$O$2:$O$8801,"Won") -> 1130049 | K23: =IFERROR(J23/E23,"") -> 2354.2688 | L23: =SUMIFS(Pipeline_Completo!$S$2:$S$8801,Pipeline_Completo!$C$2:$C$8801,$B23,Pipeline_Completo!$O$2:$O$8801,"Engaging")+SUMIFS(Pipeline_Completo!$S$2:$S$8801,Pipeline_Completo!$C$2:$C$8801,$B23,Pipeline_Completo!$O$2:$O$8801,"Prospecting") -> 495950 | M23: =COUNTIFS(Pipeline_Completo!$C$2:$C$8801,$B23,Pipeline_Completo!$V$2:$V$8801,"Saudável")+COUNTIFS(Pipeline_Completo!$C$2:$C$8801,$B23,Pipeline_Completo!$V$2:$V$8801,"Esfriando")+COUNTIFS(Pipeline_Completo!$C$2:$C$8801,$B23,Pipeline_Completo!$V$2:$V$8801,"Última chance") -> 50 | N23: =SUMIFS(Pipeline_Completo!$S$2:$S$8801,Pipeline_Completo!$C$2:$C$8801,$B23,Pipeline_Completo!$V$2:$V$8801,"Saudável")+SUMIFS(Pipeline_Completo!$S$2:$S$8801,Pipeline_Completo!$C$2:$C$8801,$B23,Pipeline_Completo!$V$2:$V$8801,"Esfriando")+SUMIFS(Pipeline_Completo!$S$2:$S$8801,Pipeline_Completo!$C$2:$C$8801,$B23,Pipeline_Completo!$V$2:$V$8801,"Última chance") -> 123514 | O23: =COUNTIFS(Pipeline_Completo!$C$2:$C$8801,$B23,Pipeline_Completo!$V$2:$V$8801,"Zumbi") -> 169 | P23: =SUMIFS(Pipeline_Completo!$S$2:$S$8801,Pipeline_Completo!$C$2:$C$8801,$B23,Pipeline_Completo!$V$2:$V$8801,"Zumbi") -> 372436 | Q23: =IFERROR(P23/(N23+P23),"") -> 0.75095473 | R23: =COUNTIFS(Pipeline_Completo!$C$2:$C$8801,$B23,Pipeline_Completo!$O$2:$O$8801,"Engaging",Pipeline_Completo!$E$2:$E$8801,"")+COUNTIFS(Pipeline_Completo!$C$2:$C$8801,$B23,Pipeline_Completo!$O$2:$O$8801,"Prospecting",Pipeline_Completo!$E$2:$E$8801,"") -> 154
A24: East | B24: Rocco Neubert | C24: Daniell Hammack | D24: =COUNTIFS(Pipeline_Completo!$D$2:$D$8801,$C24) -> 259 | E24: =COUNTIFS(Pipeline_Completo!$D$2:$D$8801,$C24,Pipeline_Completo!$O$2:$O$8801,"Won") -> 114 | F24: =COUNTIFS(Pipeline_Completo!$D$2:$D$8801,$C24,Pipeline_Completo!$O$2:$O$8801,"Lost") -> 73 | G24: =COUNTIFS(Pipeline_Completo!$D$2:$D$8801,$C24,Pipeline_Completo!$O$2:$O$8801,"Engaging") -> 72 | H24: =COUNTIFS(Pipeline_Completo!$D$2:$D$8801,$C24,Pipeline_Completo!$O$2:$O$8801,"Prospecting") -> 0 | I24: =IFERROR(E24/(E24+F24),"") -> 0.60962567 | J24: =SUMIFS(Pipeline_Completo!$R$2:$R$8801,Pipeline_Completo!$D$2:$D$8801,$C24,Pipeline_Completo!$O$2:$O$8801,"Won") -> 364229 | K24: =IFERROR(J24/E24,"") -> 3194.9912 | L24: =SUMIFS(Pipeline_Completo!$S$2:$S$8801,Pipeline_Completo!$D$2:$D$8801,$C24,Pipeline_Completo!$O$2:$O$8801,"Engaging")+SUMIFS(Pipeline_Completo!$S$2:$S$8801,Pipeline_Completo!$D$2:$D$8801,$C24,Pipeline_Completo!$O$2:$O$8801,"Prospecting") -> 209320 | M24: =COUNTIFS(Pipeline_Completo!$D$2:$D$8801,$C24,Pipeline_Completo!$V$2:$V$8801,"Saudável")+COUNTIFS(Pipeline_Completo!$D$2:$D$8801,$C24,Pipeline_Completo!$V$2:$V$8801,"Esfriando")+COUNTIFS(Pipeline_Completo!$D$2:$D$8801,$C24,Pipeline_Completo!$V$2:$V$8801,"Última chance") -> 21 | N24: =SUMIFS(Pipeline_Completo!$S$2:$S$8801,Pipeline_Completo!$D$2:$D$8801,$C24,Pipeline_Completo!$V$2:$V$8801,"Saudável")+SUMIFS(Pipeline_Completo!$S$2:$S$8801,Pipeline_Completo!$D$2:$D$8801,$C24,Pipeline_Completo!$V$2:$V$8801,"Esfriando")+SUMIFS(Pipeline_Completo!$S$2:$S$8801,Pipeline_Completo!$D$2:$D$8801,$C24,Pipeline_Completo!$V$2:$V$8801,"Última chance") -> 54302 | O24: =COUNTIFS(Pipeline_Completo!$D$2:$D$8801,$C24,Pipeline_Completo!$V$2:$V$8801,"Zumbi") -> 51 | P24: =SUMIFS(Pipeline_Completo!$S$2:$S$8801,Pipeline_Completo!$D$2:$D$8801,$C24,Pipeline_Completo!$V$2:$V$8801,"Zumbi") -> 155018 | Q24: =IFERROR(P24/(N24+P24),"") -> 0.74057902 | R24: =COUNTIFS(Pipeline_Completo!$D$2:$D$8801,$C24,Pipeline_Completo!$O$2:$O$8801,"Engaging",Pipeline_Completo!$E$2:$E$8801,"")+COUNTIFS(Pipeline_Completo!$D$2:$D$8801,$C24,Pipeline_Completo!$O$2:$O$8801,"Prospecting",Pipeline_Completo!$E$2:$E$8801,"") -> 47
A25: East | B25: Rocco Neubert | C25: Cassey Cress | D25: =COUNTIFS(Pipeline_Completo!$D$2:$D$8801,$C25) -> 346 | E25: =COUNTIFS(Pipeline_Completo!$D$2:$D$8801,$C25,Pipeline_Completo!$O$2:$O$8801,"Won") -> 163 | F25: =COUNTIFS(Pipeline_Completo!$D$2:$D$8801,$C25,Pipeline_Completo!$O$2:$O$8801,"Lost") -> 98 | G25: =COUNTIFS(Pipeline_Completo!$D$2:$D$8801,$C25,Pipeline_Completo!$O$2:$O$8801,"Engaging") -> 85 | H25: =COUNTIFS(Pipeline_Completo!$D$2:$D$8801,$C25,Pipeline_Completo!$O$2:$O$8801,"Prospecting") -> 0 | I25: =IFERROR(E25/(E25+F25),"") -> 0.62452107 | J25: =SUMIFS(Pipeline_Completo!$R$2:$R$8801,Pipeline_Completo!$D$2:$D$8801,$C25,Pipeline_Completo!$O$2:$O$8801,"Won") -> 450489 | K25: =IFERROR(J25/E25,"") -> 2763.7362 | L25: =SUMIFS(Pipeline_Completo!$S$2:$S$8801,Pipeline_Completo!$D$2:$D$8801,$C25,Pipeline_Completo!$O$2:$O$8801,"Engaging")+SUMIFS(Pipeline_Completo!$S$2:$S$8801,Pipeline_Completo!$D$2:$D$8801,$C25,Pipeline_Completo!$O$2:$O$8801,"Prospecting") -> 220860 | M25: =COUNTIFS(Pipeline_Completo!$D$2:$D$8801,$C25,Pipeline_Completo!$V$2:$V$8801,"Saudável")+COUNTIFS(Pipeline_Completo!$D$2:$D$8801,$C25,Pipeline_Completo!$V$2:$V$8801,"Esfriando")+COUNTIFS(Pipeline_Completo!$D$2:$D$8801,$C25,Pipeline_Completo!$V$2:$V$8801,"Última chance") -> 23 | N25: =SUMIFS(Pipeline_Completo!$S$2:$S$8801,Pipeline_Completo!$D$2:$D$8801,$C25,Pipeline_Completo!$V$2:$V$8801,"Saudável")+SUMIFS(Pipeline_Completo!$S$2:$S$8801,Pipeline_Completo!$D$2:$D$8801,$C25,Pipeline_Completo!$V$2:$V$8801,"Esfriando")+SUMIFS(Pipeline_Completo!$S$2:$S$8801,Pipeline_Completo!$D$2:$D$8801,$C25,Pipeline_Completo!$V$2:$V$8801,"Última chance") -> 48662 | O25: =COUNTIFS(Pipeline_Completo!$D$2:$D$8801,$C25,Pipeline_Completo!$V$2:$V$8801,"Zumbi") -> 62 | P25: =SUMIFS(Pipeline_Completo!$S$2:$S$8801,Pipeline_Completo!$D$2:$D$8801,$C25,Pipeline_Completo!$V$2:$V$8801,"Zumbi") -> 172198 | Q25: =IFERROR(P25/(N25+P25),"") -> 0.77967038 | R25: =COUNTIFS(Pipeline_Completo!$D$2:$D$8801,$C25,Pipeline_Completo!$O$2:$O$8801,"Engaging",Pipeline_Completo!$E$2:$E$8801,"")+COUNTIFS(Pipeline_Completo!$D$2:$D$8801,$C25,Pipeline_Completo!$O$2:$O$8801,"Prospecting",Pipeline_Completo!$E$2:$E$8801,"") -> 56
A26: East | B26: Rocco Neubert | C26: Donn Cantrell | D26: =COUNTIFS(Pipeline_Completo!$D$2:$D$8801,$C26) -> 275 | E26: =COUNTIFS(Pipeline_Completo!$D$2:$D$8801,$C26,Pipeline_Completo!$O$2:$O$8801,"Won") -> 158 | F26: =COUNTIFS(Pipeline_Completo!$D$2:$D$8801,$C26,Pipeline_Completo!$O$2:$O$8801,"Lost") -> 117 | G26: =COUNTIFS(Pipeline_Completo!$D$2:$D$8801,$C26,Pipeline_Completo!$O$2:$O$8801,"Engaging") -> 0 | H26: =COUNTIFS(Pipeline_Completo!$D$2:$D$8801,$C26,Pipeline_Completo!$O$2:$O$8801,"Prospecting") -> 0 | I26: =IFERROR(E26/(E26+F26),"") -> 0.57454545 | J26: =SUMIFS(Pipeline_Completo!$R$2:$R$8801,Pipeline_Completo!$D$2:$D$8801,$C26,Pipeline_Completo!$O$2:$O$8801,"Won") -> 445860 | K26: =IFERROR(J26/E26,"") -> 2821.8987 | L26: =SUMIFS(Pipeline_Completo!$S$2:$S$8801,Pipeline_Completo!$D$2:$D$8801,$C26,Pipeline_Completo!$O$2:$O$8801,"Engaging")+SUMIFS(Pipeline_Completo!$S$2:$S$8801,Pipeline_Completo!$D$2:$D$8801,$C26,Pipeline_Completo!$O$2:$O$8801,"Prospecting") -> 0 | M26: =COUNTIFS(Pipeline_Completo!$D$2:$D$8801,$C26,Pipeline_Completo!$V$2:$V$8801,"Saudável")+COUNTIFS(Pipeline_Completo!$D$2:$D$8801,$C26,Pipeline_Completo!$V$2:$V$8801,"Esfriando")+COUNTIFS(Pipeline_Completo!$D$2:$D$8801,$C26,Pipeline_Completo!$V$2:$V$8801,"Última chance") -> 0 | N26: =SUMIFS(Pipeline_Completo!$S$2:$S$8801,Pipeline_Completo!$D$2:$D$8801,$C26,Pipeline_Completo!$V$2:$V$8801,"Saudável")+SUMIFS(Pipeline_Completo!$S$2:$S$8801,Pipeline_Completo!$D$2:$D$8801,$C26,Pipeline_Completo!$V$2:$V$8801,"Esfriando")+SUMIFS(Pipeline_Completo!$S$2:$S$8801,Pipeline_Completo!$D$2:$D$8801,$C26,Pipeline_Completo!$V$2:$V$8801,"Última chance") -> 0 | O26: =COUNTIFS(Pipeline_Completo!$D$2:$D$8801,$C26,Pipeline_Completo!$V$2:$V$8801,"Zumbi") -> 0 | P26: =SUMIFS(Pipeline_Completo!$S$2:$S$8801,Pipeline_Completo!$D$2:$D$8801,$C26,Pipeline_Completo!$V$2:$V$8801,"Zumbi") -> 0 | Q26: =IFERROR(P26/(N26+P26),"") | R26: =COUNTIFS(Pipeline_Completo!$D$2:$D$8801,$C26,Pipeline_Completo!$O$2:$O$8801,"Engaging",Pipeline_Completo!$E$2:$E$8801,"")+COUNTIFS(Pipeline_Completo!$D$2:$D$8801,$C26,Pipeline_Completo!$O$2:$O$8801,"Prospecting",Pipeline_Completo!$E$2:$E$8801,"") -> 0
A27: East | B27: Rocco Neubert | C27: Reed Clapper | D27: =COUNTIFS(Pipeline_Completo!$D$2:$D$8801,$C27) -> 237 | E27: =COUNTIFS(Pipeline_Completo!$D$2:$D$8801,$C27,Pipeline_Completo!$O$2:$O$8801,"Won") -> 155 | F27: =COUNTIFS(Pipeline_Completo!$D$2:$D$8801,$C27,Pipeline_Completo!$O$2:$O$8801,"Lost") -> 82 | G27: =COUNTIFS(Pipeline_Completo!$D$2:$D$8801,$C27,Pipeline_Completo!$O$2:$O$8801,"Engaging") -> 0 | H27: =COUNTIFS(Pipeline_Completo!$D$2:$D$8801,$C27,Pipeline_Completo!$O$2:$O$8801,"Prospecting") -> 0 | I27: =IFERROR(E27/(E27+F27),"") -> 0.65400844 | J27: =SUMIFS(Pipeline_Completo!$R$2:$R$8801,Pipeline_Completo!$D$2:$D$8801,$C27,Pipeline_Completo!$O$2:$O$8801,"Won") -> 438336 | K27: =IFERROR(J27/E27,"") -> 2827.9742 | L27: =SUMIFS(Pipeline_Completo!$S$2:$S$8801,Pipeline_Completo!$D$2:$D$8801,$C27,Pipeline_Completo!$O$2:$O$8801,"Engaging")+SUMIFS(Pipeline_Completo!$S$2:$S$8801,Pipeline_Completo!$D$2:$D$8801,$C27,Pipeline_Completo!$O$2:$O$8801,"Prospecting") -> 0 | M27: =COUNTIFS(Pipeline_Completo!$D$2:$D$8801,$C27,Pipeline_Completo!$V$2:$V$8801,"Saudável")+COUNTIFS(Pipeline_Completo!$D$2:$D$8801,$C27,Pipeline_Completo!$V$2:$V$8801,"Esfriando")+COUNTIFS(Pipeline_Completo!$D$2:$D$8801,$C27,Pipeline_Completo!$V$2:$V$8801,"Última chance") -> 0 | N27: =SUMIFS(Pipeline_Completo!$S$2:$S$8801,Pipeline_Completo!$D$2:$D$8801,$C27,Pipeline_Completo!$V$2:$V$8801,"Saudável")+SUMIFS(Pipeline_Completo!$S$2:$S$8801,Pipeline_Completo!$D$2:$D$8801,$C27,Pipeline_Completo!$V$2:$V$8801,"Esfriando")+SUMIFS(Pipeline_Completo!$S$2:$S$8801,Pipeline_Completo!$D$2:$D$8801,$C27,Pipeline_Completo!$V$2:$V$8801,"Última chance") -> 0 | O27: =COUNTIFS(Pipeline_Completo!$D$2:$D$8801,$C27,Pipeline_Completo!$V$2:$V$8801,"Zumbi") -> 0 | P27: =SUMIFS(Pipeline_Completo!$S$2:$S$8801,Pipeline_Completo!$D$2:$D$8801,$C27,Pipeline_Completo!$V$2:$V$8801,"Zumbi") -> 0 | Q27: =IFERROR(P27/(N27+P27),"") | R27: =COUNTIFS(Pipeline_Completo!$D$2:$D$8801,$C27,Pipeline_Completo!$O$2:$O$8801,"Engaging",Pipeline_Completo!$E$2:$E$8801,"")+COUNTIFS(Pipeline_Completo!$D$2:$D$8801,$C27,Pipeline_Completo!$O$2:$O$8801,"Prospecting",Pipeline_Completo!$E$2:$E$8801,"") -> 0
A28: East | B28: Rocco Neubert | C28: Boris Faz | D28: =COUNTIFS(Pipeline_Completo!$D$2:$D$8801,$C28) -> 210 | E28: =COUNTIFS(Pipeline_Completo!$D$2:$D$8801,$C28,Pipeline_Completo!$O$2:$O$8801,"Won") -> 101 | F28: =COUNTIFS(Pipeline_Completo!$D$2:$D$8801,$C28,Pipeline_Completo!$O$2:$O$8801,"Lost") -> 52 | G28: =COUNTIFS(Pipeline_Completo!$D$2:$D$8801,$C28,Pipeline_Completo!$O$2:$O$8801,"Engaging") -> 57 | H28: =COUNTIFS(Pipeline_Completo!$D$2:$D$8801,$C28,Pipeline_Completo!$O$2:$O$8801,"Prospecting") -> 0 | I28: =IFERROR(E28/(E28+F28),"") -> 0.66013072 | J28: =SUMIFS(Pipeline_Completo!$R$2:$R$8801,Pipeline_Completo!$D$2:$D$8801,$C28,Pipeline_Completo!$O$2:$O$8801,"Won") -> 261631 | K28: =IFERROR(J28/E28,"") -> 2590.4059 | L28: =SUMIFS(Pipeline_Completo!$S$2:$S$8801,Pipeline_Completo!$D$2:$D$8801,$C28,Pipeline_Completo!$O$2:$O$8801,"Engaging")+SUMIFS(Pipeline_Completo!$S$2:$S$8801,Pipeline_Completo!$D$2:$D$8801,$C28,Pipeline_Completo!$O$2:$O$8801,"Prospecting") -> 143456 | M28: =COUNTIFS(Pipeline_Completo!$D$2:$D$8801,$C28,Pipeline_Completo!$V$2:$V$8801,"Saudável")+COUNTIFS(Pipeline_Completo!$D$2:$D$8801,$C28,Pipeline_Completo!$V$2:$V$8801,"Esfriando")+COUNTIFS(Pipeline_Completo!$D$2:$D$8801,$C28,Pipeline_Completo!$V$2:$V$8801,"Última chance") -> 13 | N28: =SUMIFS(Pipeline_Completo!$S$2:$S$8801,Pipeline_Completo!$D$2:$D$8801,$C28,Pipeline_Completo!$V$2:$V$8801,"Saudável")+SUMIFS(Pipeline_Completo!$S$2:$S$8801,Pipeline_Completo!$D$2:$D$8801,$C28,Pipeline_Completo!$V$2:$V$8801,"Esfriando")+SUMIFS(Pipeline_Completo!$S$2:$S$8801,Pipeline_Completo!$D$2:$D$8801,$C28,Pipeline_Completo!$V$2:$V$8801,"Última chance") -> 34180 | O28: =COUNTIFS(Pipeline_Completo!$D$2:$D$8801,$C28,Pipeline_Completo!$V$2:$V$8801,"Zumbi") -> 44 | P28: =SUMIFS(Pipeline_Completo!$S$2:$S$8801,Pipeline_Completo!$D$2:$D$8801,$C28,Pipeline_Completo!$V$2:$V$8801,"Zumbi") -> 109276 | Q28: =IFERROR(P28/(N28+P28),"") -> 0.76173879 | R28: =COUNTIFS(Pipeline_Completo!$D$2:$D$8801,$C28,Pipeline_Completo!$O$2:$O$8801,"Engaging",Pipeline_Completo!$E$2:$E$8801,"")+COUNTIFS(Pipeline_Completo!$D$2:$D$8801,$C28,Pipeline_Completo!$O$2:$O$8801,"Prospecting",Pipeline_Completo!$E$2:$E$8801,"") -> 39
A29: East | B29: Rocco Neubert | C29: Natalya Ivanova | D29: =COUNTIFS(Pipeline_Completo!$D$2:$D$8801,$C29) -> 0 | E29: =COUNTIFS(Pipeline_Completo!$D$2:$D$8801,$C29,Pipeline_Completo!$O$2:$O$8801,"Won") -> 0 | F29: =COUNTIFS(Pipeline_Completo!$D$2:$D$8801,$C29,Pipeline_Completo!$O$2:$O$8801,"Lost") -> 0 | G29: =COUNTIFS(Pipeline_Completo!$D$2:$D$8801,$C29,Pipeline_Completo!$O$2:$O$8801,"Engaging") -> 0 | H29: =COUNTIFS(Pipeline_Completo!$D$2:$D$8801,$C29,Pipeline_Completo!$O$2:$O$8801,"Prospecting") -> 0 | I29: =IFERROR(E29/(E29+F29),"") | J29: =SUMIFS(Pipeline_Completo!$R$2:$R$8801,Pipeline_Completo!$D$2:$D$8801,$C29,Pipeline_Completo!$O$2:$O$8801,"Won") -> 0 | K29: =IFERROR(J29/E29,"") | L29: =SUMIFS(Pipeline_Completo!$S$2:$S$8801,Pipeline_Completo!$D$2:$D$8801,$C29,Pipeline_Completo!$O$2:$O$8801,"Engaging")+SUMIFS(Pipeline_Completo!$S$2:$S$8801,Pipeline_Completo!$D$2:$D$8801,$C29,Pipeline_Completo!$O$2:$O$8801,"Prospecting") -> 0 | M29: =COUNTIFS(Pipeline_Completo!$D$2:$D$8801,$C29,Pipeline_Completo!$V$2:$V$8801,"Saudável")+COUNTIFS(Pipeline_Completo!$D$2:$D$8801,$C29,Pipeline_Completo!$V$2:$V$8801,"Esfriando")+COUNTIFS(Pipeline_Completo!$D$2:$D$8801,$C29,Pipeline_Completo!$V$2:$V$8801,"Última chance") -> 0 | N29: =SUMIFS(Pipeline_Completo!$S$2:$S$8801,Pipeline_Completo!$D$2:$D$8801,$C29,Pipeline_Completo!$V$2:$V$8801,"Saudável")+SUMIFS(Pipeline_Completo!$S$2:$S$8801,Pipeline_Completo!$D$2:$D$8801,$C29,Pipeline_Completo!$V$2:$V$8801,"Esfriando")+SUMIFS(Pipeline_Completo!$S$2:$S$8801,Pipeline_Completo!$D$2:$D$8801,$C29,Pipeline_Completo!$V$2:$V$8801,"Última chance") -> 0 | O29: =COUNTIFS(Pipeline_Completo!$D$2:$D$8801,$C29,Pipeline_Completo!$V$2:$V$8801,"Zumbi") -> 0 | P29: =SUMIFS(Pipeline_Completo!$S$2:$S$8801,Pipeline_Completo!$D$2:$D$8801,$C29,Pipeline_Completo!$V$2:$V$8801,"Zumbi") -> 0 | Q29: =IFERROR(P29/(N29+P29),"") | R29: =COUNTIFS(Pipeline_Completo!$D$2:$D$8801,$C29,Pipeline_Completo!$O$2:$O$8801,"Engaging",Pipeline_Completo!$E$2:$E$8801,"")+COUNTIFS(Pipeline_Completo!$D$2:$D$8801,$C29,Pipeline_Completo!$O$2:$O$8801,"Prospecting",Pipeline_Completo!$E$2:$E$8801,"") -> 0
A30: East | B30: Rocco Neubert | C30: Subtotal Rocco Neubert | D30: =COUNTIFS(Pipeline_Completo!$C$2:$C$8801,$B30) -> 1327 | E30: =COUNTIFS(Pipeline_Completo!$C$2:$C$8801,$B30,Pipeline_Completo!$O$2:$O$8801,"Won") -> 691 | F30: =COUNTIFS(Pipeline_Completo!$C$2:$C$8801,$B30,Pipeline_Completo!$O$2:$O$8801,"Lost") -> 422 | G30: =COUNTIFS(Pipeline_Completo!$C$2:$C$8801,$B30,Pipeline_Completo!$O$2:$O$8801,"Engaging") -> 214 | H30: =COUNTIFS(Pipeline_Completo!$C$2:$C$8801,$B30,Pipeline_Completo!$O$2:$O$8801,"Prospecting") -> 0 | I30: =IFERROR(E30/(E30+F30),"") -> 0.62084456 | J30: =SUMIFS(Pipeline_Completo!$R$2:$R$8801,Pipeline_Completo!$C$2:$C$8801,$B30,Pipeline_Completo!$O$2:$O$8801,"Won") -> 1960545 | K30: =IFERROR(J30/E30,"") -> 2837.2576 | L30: =SUMIFS(Pipeline_Completo!$S$2:$S$8801,Pipeline_Completo!$C$2:$C$8801,$B30,Pipeline_Completo!$O$2:$O$8801,"Engaging")+SUMIFS(Pipeline_Completo!$S$2:$S$8801,Pipeline_Completo!$C$2:$C$8801,$B30,Pipeline_Completo!$O$2:$O$8801,"Prospecting") -> 573636 | M30: =COUNTIFS(Pipeline_Completo!$C$2:$C$8801,$B30,Pipeline_Completo!$V$2:$V$8801,"Saudável")+COUNTIFS(Pipeline_Completo!$C$2:$C$8801,$B30,Pipeline_Completo!$V$2:$V$8801,"Esfriando")+COUNTIFS(Pipeline_Completo!$C$2:$C$8801,$B30,Pipeline_Completo!$V$2:$V$8801,"Última chance") -> 57 | N30: =SUMIFS(Pipeline_Completo!$S$2:$S$8801,Pipeline_Completo!$C$2:$C$8801,$B30,Pipeline_Completo!$V$2:$V$8801,"Saudável")+SUMIFS(Pipeline_Completo!$S$2:$S$8801,Pipeline_Completo!$C$2:$C$8801,$B30,Pipeline_Completo!$V$2:$V$8801,"Esfriando")+SUMIFS(Pipeline_Completo!$S$2:$S$8801,Pipeline_Completo!$C$2:$C$8801,$B30,Pipeline_Completo!$V$2:$V$8801,"Última chance") -> 137144 | O30: =COUNTIFS(Pipeline_Completo!$C$2:$C$8801,$B30,Pipeline_Completo!$V$2:$V$8801,"Zumbi") -> 157 | P30: =SUMIFS(Pipeline_Completo!$S$2:$S$8801,Pipeline_Completo!$C$2:$C$8801,$B30,Pipeline_Completo!$V$2:$V$8801,"Zumbi") -> 436492 | Q30: =IFERROR(P30/(N30+P30),"") -> 0.76092156 | R30: =COUNTIFS(Pipeline_Completo!$C$2:$C$8801,$B30,Pipeline_Completo!$O$2:$O$8801,"Engaging",Pipeline_Completo!$E$2:$E$8801,"")+COUNTIFS(Pipeline_Completo!$C$2:$C$8801,$B30,Pipeline_Completo!$O$2:$O$8801,"Prospecting",Pipeline_Completo!$E$2:$E$8801,"") -> 142
A31: East | C31: TOTAL escritório East | D31: =COUNTIFS(Pipeline_Completo!$B$2:$B$8801,$A31) -> 2291 | E31: =COUNTIFS(Pipeline_Completo!$B$2:$B$8801,$A31,Pipeline_Completo!$O$2:$O$8801,"Won") -> 1171 | F31: =COUNTIFS(Pipeline_Completo!$B$2:$B$8801,$A31,Pipeline_Completo!$O$2:$O$8801,"Lost") -> 687 | G31: =COUNTIFS(Pipeline_Completo!$B$2:$B$8801,$A31,Pipeline_Completo!$O$2:$O$8801,"Engaging") -> 433 | H31: =COUNTIFS(Pipeline_Completo!$B$2:$B$8801,$A31,Pipeline_Completo!$O$2:$O$8801,"Prospecting") -> 0 | I31: =IFERROR(E31/(E31+F31),"") -> 0.63024758 | J31: =SUMIFS(Pipeline_Completo!$R$2:$R$8801,Pipeline_Completo!$B$2:$B$8801,$A31,Pipeline_Completo!$O$2:$O$8801,"Won") -> 3090594 | K31: =IFERROR(J31/E31,"") -> 2639.2775 | L31: =SUMIFS(Pipeline_Completo!$S$2:$S$8801,Pipeline_Completo!$B$2:$B$8801,$A31,Pipeline_Completo!$O$2:$O$8801,"Engaging")+SUMIFS(Pipeline_Completo!$S$2:$S$8801,Pipeline_Completo!$B$2:$B$8801,$A31,Pipeline_Completo!$O$2:$O$8801,"Prospecting") -> 1069586 | M31: =COUNTIFS(Pipeline_Completo!$B$2:$B$8801,$A31,Pipeline_Completo!$V$2:$V$8801,"Saudável")+COUNTIFS(Pipeline_Completo!$B$2:$B$8801,$A31,Pipeline_Completo!$V$2:$V$8801,"Esfriando")+COUNTIFS(Pipeline_Completo!$B$2:$B$8801,$A31,Pipeline_Completo!$V$2:$V$8801,"Última chance") -> 107 | N31: =SUMIFS(Pipeline_Completo!$S$2:$S$8801,Pipeline_Completo!$B$2:$B$8801,$A31,Pipeline_Completo!$V$2:$V$8801,"Saudável")+SUMIFS(Pipeline_Completo!$S$2:$S$8801,Pipeline_Completo!$B$2:$B$8801,$A31,Pipeline_Completo!$V$2:$V$8801,"Esfriando")+SUMIFS(Pipeline_Completo!$S$2:$S$8801,Pipeline_Completo!$B$2:$B$8801,$A31,Pipeline_Completo!$V$2:$V$8801,"Última chance") -> 260658 | O31: =COUNTIFS(Pipeline_Completo!$B$2:$B$8801,$A31,Pipeline_Completo!$V$2:$V$8801,"Zumbi") -> 326 | P31: =SUMIFS(Pipeline_Completo!$S$2:$S$8801,Pipeline_Completo!$B$2:$B$8801,$A31,Pipeline_Completo!$V$2:$V$8801,"Zumbi") -> 808928 | Q31: =IFERROR(P31/(N31+P31),"") -> 0.7563001 | R31: =COUNTIFS(Pipeline_Completo!$B$2:$B$8801,$A31,Pipeline_Completo!$O$2:$O$8801,"Engaging",Pipeline_Completo!$E$2:$E$8801,"")+COUNTIFS(Pipeline_Completo!$B$2:$B$8801,$A31,Pipeline_Completo!$O$2:$O$8801,"Prospecting",Pipeline_Completo!$E$2:$E$8801,"") -> 296
A33: West | B33: Celia Rouche | C33: Vicki Laflamme | D33: =COUNTIFS(Pipeline_Completo!$D$2:$D$8801,$C33) -> 451 | E33: =COUNTIFS(Pipeline_Completo!$D$2:$D$8801,$C33,Pipeline_Completo!$O$2:$O$8801,"Won") -> 221 | F33: =COUNTIFS(Pipeline_Completo!$D$2:$D$8801,$C33,Pipeline_Completo!$O$2:$O$8801,"Lost") -> 126 | G33: =COUNTIFS(Pipeline_Completo!$D$2:$D$8801,$C33,Pipeline_Completo!$O$2:$O$8801,"Engaging") -> 104 | H33: =COUNTIFS(Pipeline_Completo!$D$2:$D$8801,$C33,Pipeline_Completo!$O$2:$O$8801,"Prospecting") -> 0 | I33: =IFERROR(E33/(E33+F33),"") -> 0.63688761 | J33: =SUMIFS(Pipeline_Completo!$R$2:$R$8801,Pipeline_Completo!$D$2:$D$8801,$C33,Pipeline_Completo!$O$2:$O$8801,"Won") -> 478396 | K33: =IFERROR(J33/E33,"") -> 2164.6878 | L33: =SUMIFS(Pipeline_Completo!$S$2:$S$8801,Pipeline_Completo!$D$2:$D$8801,$C33,Pipeline_Completo!$O$2:$O$8801,"Engaging")+SUMIFS(Pipeline_Completo!$S$2:$S$8801,Pipeline_Completo!$D$2:$D$8801,$C33,Pipeline_Completo!$O$2:$O$8801,"Prospecting") -> 227326 | M33: =COUNTIFS(Pipeline_Completo!$D$2:$D$8801,$C33,Pipeline_Completo!$V$2:$V$8801,"Saudável")+COUNTIFS(Pipeline_Completo!$D$2:$D$8801,$C33,Pipeline_Completo!$V$2:$V$8801,"Esfriando")+COUNTIFS(Pipeline_Completo!$D$2:$D$8801,$C33,Pipeline_Completo!$V$2:$V$8801,"Última chance") -> 24 | N33: =SUMIFS(Pipeline_Completo!$S$2:$S$8801,Pipeline_Completo!$D$2:$D$8801,$C33,Pipeline_Completo!$V$2:$V$8801,"Saudável")+SUMIFS(Pipeline_Completo!$S$2:$S$8801,Pipeline_Completo!$D$2:$D$8801,$C33,Pipeline_Completo!$V$2:$V$8801,"Esfriando")+SUMIFS(Pipeline_Completo!$S$2:$S$8801,Pipeline_Completo!$D$2:$D$8801,$C33,Pipeline_Completo!$V$2:$V$8801,"Última chance") -> 51022 | O33: =COUNTIFS(Pipeline_Completo!$D$2:$D$8801,$C33,Pipeline_Completo!$V$2:$V$8801,"Zumbi") -> 80 | P33: =SUMIFS(Pipeline_Completo!$S$2:$S$8801,Pipeline_Completo!$D$2:$D$8801,$C33,Pipeline_Completo!$V$2:$V$8801,"Zumbi") -> 176304 | Q33: =IFERROR(P33/(N33+P33),"") -> 0.77555581 | R33: =COUNTIFS(Pipeline_Completo!$D$2:$D$8801,$C33,Pipeline_Completo!$O$2:$O$8801,"Engaging",Pipeline_Completo!$E$2:$E$8801,"")+COUNTIFS(Pipeline_Completo!$D$2:$D$8801,$C33,Pipeline_Completo!$O$2:$O$8801,"Prospecting",Pipeline_Completo!$E$2:$E$8801,"") -> 77
A34: West | B34: Celia Rouche | C34: Rosalina Dieter | D34: =COUNTIFS(Pipeline_Completo!$D$2:$D$8801,$C34) -> 160 | E34: =COUNTIFS(Pipeline_Completo!$D$2:$D$8801,$C34,Pipeline_Completo!$O$2:$O$8801,"Won") -> 72 | F34: =COUNTIFS(Pipeline_Completo!$D$2:$D$8801,$C34,Pipeline_Completo!$O$2:$O$8801,"Lost") -> 38 | G34: =COUNTIFS(Pipeline_Completo!$D$2:$D$8801,$C34,Pipeline_Completo!$O$2:$O$8801,"Engaging") -> 50 | H34: =COUNTIFS(Pipeline_Completo!$D$2:$D$8801,$C34,Pipeline_Completo!$O$2:$O$8801,"Prospecting") -> 0 | I34: =IFERROR(E34/(E34+F34),"") -> 0.65454545 | J34: =SUMIFS(Pipeline_Completo!$R$2:$R$8801,Pipeline_Completo!$D$2:$D$8801,$C34,Pipeline_Completo!$O$2:$O$8801,"Won") -> 235403 | K34: =IFERROR(J34/E34,"") -> 3269.4861 | L34: =SUMIFS(Pipeline_Completo!$S$2:$S$8801,Pipeline_Completo!$D$2:$D$8801,$C34,Pipeline_Completo!$O$2:$O$8801,"Engaging")+SUMIFS(Pipeline_Completo!$S$2:$S$8801,Pipeline_Completo!$D$2:$D$8801,$C34,Pipeline_Completo!$O$2:$O$8801,"Prospecting") -> 119664 | M34: =COUNTIFS(Pipeline_Completo!$D$2:$D$8801,$C34,Pipeline_Completo!$V$2:$V$8801,"Saudável")+COUNTIFS(Pipeline_Completo!$D$2:$D$8801,$C34,Pipeline_Completo!$V$2:$V$8801,"Esfriando")+COUNTIFS(Pipeline_Completo!$D$2:$D$8801,$C34,Pipeline_Completo!$V$2:$V$8801,"Última chance") -> 16 | N34: =SUMIFS(Pipeline_Completo!$S$2:$S$8801,Pipeline_Completo!$D$2:$D$8801,$C34,Pipeline_Completo!$V$2:$V$8801,"Saudável")+SUMIFS(Pipeline_Completo!$S$2:$S$8801,Pipeline_Completo!$D$2:$D$8801,$C34,Pipeline_Completo!$V$2:$V$8801,"Esfriando")+SUMIFS(Pipeline_Completo!$S$2:$S$8801,Pipeline_Completo!$D$2:$D$8801,$C34,Pipeline_Completo!$V$2:$V$8801,"Última chance") -> 37233 | O34: =COUNTIFS(Pipeline_Completo!$D$2:$D$8801,$C34,Pipeline_Completo!$V$2:$V$8801,"Zumbi") -> 34 | P34: =SUMIFS(Pipeline_Completo!$S$2:$S$8801,Pipeline_Completo!$D$2:$D$8801,$C34,Pipeline_Completo!$V$2:$V$8801,"Zumbi") -> 82431 | Q34: =IFERROR(P34/(N34+P34),"") -> 0.68885379 | R34: =COUNTIFS(Pipeline_Completo!$D$2:$D$8801,$C34,Pipeline_Completo!$O$2:$O$8801,"Engaging",Pipeline_Completo!$E$2:$E$8801,"")+COUNTIFS(Pipeline_Completo!$D$2:$D$8801,$C34,Pipeline_Completo!$O$2:$O$8801,"Prospecting",Pipeline_Completo!$E$2:$E$8801,"") -> 34
A35: West | B35: Celia Rouche | C35: Hayden Neloms | D35: =COUNTIFS(Pipeline_Completo!$D$2:$D$8801,$C35) -> 202 | E35: =COUNTIFS(Pipeline_Completo!$D$2:$D$8801,$C35,Pipeline_Completo!$O$2:$O$8801,"Won") -> 107 | F35: =COUNTIFS(Pipeline_Completo!$D$2:$D$8801,$C35,Pipeline_Completo!$O$2:$O$8801,"Lost") -> 45 | G35: =COUNTIFS(Pipeline_Completo!$D$2:$D$8801,$C35,Pipeline_Completo!$O$2:$O$8801,"Engaging") -> 50 | H35: =COUNTIFS(Pipeline_Completo!$D$2:$D$8801,$C35,Pipeline_Completo!$O$2:$O$8801,"Prospecting") -> 0 | I35: =IFERROR(E35/(E35+F35),"") -> 0.70394737 | J35: =SUMIFS(Pipeline_Completo!$R$2:$R$8801,Pipeline_Completo!$D$2:$D$8801,$C35,Pipeline_Completo!$O$2:$O$8801,"Won") -> 272111 | K35: =IFERROR(J35/E35,"") -> 2543.0935 | L35: =SUMIFS(Pipeline_Completo!$S$2:$S$8801,Pipeline_Completo!$D$2:$D$8801,$C35,Pipeline_Completo!$O$2:$O$8801,"Engaging")+SUMIFS(Pipeline_Completo!$S$2:$S$8801,Pipeline_Completo!$D$2:$D$8801,$C35,Pipeline_Completo!$O$2:$O$8801,"Prospecting") -> 123530 | M35: =COUNTIFS(Pipeline_Completo!$D$2:$D$8801,$C35,Pipeline_Completo!$V$2:$V$8801,"Saudável")+COUNTIFS(Pipeline_Completo!$D$2:$D$8801,$C35,Pipeline_Completo!$V$2:$V$8801,"Esfriando")+COUNTIFS(Pipeline_Completo!$D$2:$D$8801,$C35,Pipeline_Completo!$V$2:$V$8801,"Última chance") -> 6 | N35: =SUMIFS(Pipeline_Completo!$S$2:$S$8801,Pipeline_Completo!$D$2:$D$8801,$C35,Pipeline_Completo!$V$2:$V$8801,"Saudável")+SUMIFS(Pipeline_Completo!$S$2:$S$8801,Pipeline_Completo!$D$2:$D$8801,$C35,Pipeline_Completo!$V$2:$V$8801,"Esfriando")+SUMIFS(Pipeline_Completo!$S$2:$S$8801,Pipeline_Completo!$D$2:$D$8801,$C35,Pipeline_Completo!$V$2:$V$8801,"Última chance") -> 10136 | O35: =COUNTIFS(Pipeline_Completo!$D$2:$D$8801,$C35,Pipeline_Completo!$V$2:$V$8801,"Zumbi") -> 44 | P35: =SUMIFS(Pipeline_Completo!$S$2:$S$8801,Pipeline_Completo!$D$2:$D$8801,$C35,Pipeline_Completo!$V$2:$V$8801,"Zumbi") -> 113394 | Q35: =IFERROR(P35/(N35+P35),"") -> 0.91794706 | R35: =COUNTIFS(Pipeline_Completo!$D$2:$D$8801,$C35,Pipeline_Completo!$O$2:$O$8801,"Engaging",Pipeline_Completo!$E$2:$E$8801,"")+COUNTIFS(Pipeline_Completo!$D$2:$D$8801,$C35,Pipeline_Completo!$O$2:$O$8801,"Prospecting",Pipeline_Completo!$E$2:$E$8801,"") -> 36
A36: West | B36: Celia Rouche | C36: Markita Hansen | D36: =COUNTIFS(Pipeline_Completo!$D$2:$D$8801,$C36) -> 306 | E36: =COUNTIFS(Pipeline_Completo!$D$2:$D$8801,$C36,Pipeline_Completo!$O$2:$O$8801,"Won") -> 130 | F36: =COUNTIFS(Pipeline_Completo!$D$2:$D$8801,$C36,Pipeline_Completo!$O$2:$O$8801,"Lost") -> 97 | G36: =COUNTIFS(Pipeline_Completo!$D$2:$D$8801,$C36,Pipeline_Completo!$O$2:$O$8801,"Engaging") -> 79 | H36: =COUNTIFS(Pipeline_Completo!$D$2:$D$8801,$C36,Pipeline_Completo!$O$2:$O$8801,"Prospecting") -> 0 | I36: =IFERROR(E36/(E36+F36),"") -> 0.57268722 | J36: =SUMIFS(Pipeline_Completo!$R$2:$R$8801,Pipeline_Completo!$D$2:$D$8801,$C36,Pipeline_Completo!$O$2:$O$8801,"Won") -> 328792 | K36: =IFERROR(J36/E36,"") -> 2529.1692 | L36: =SUMIFS(Pipeline_Completo!$S$2:$S$8801,Pipeline_Completo!$D$2:$D$8801,$C36,Pipeline_Completo!$O$2:$O$8801,"Engaging")+SUMIFS(Pipeline_Completo!$S$2:$S$8801,Pipeline_Completo!$D$2:$D$8801,$C36,Pipeline_Completo!$O$2:$O$8801,"Prospecting") -> 282756 | M36: =COUNTIFS(Pipeline_Completo!$D$2:$D$8801,$C36,Pipeline_Completo!$V$2:$V$8801,"Saudável")+COUNTIFS(Pipeline_Completo!$D$2:$D$8801,$C36,Pipeline_Completo!$V$2:$V$8801,"Esfriando")+COUNTIFS(Pipeline_Completo!$D$2:$D$8801,$C36,Pipeline_Completo!$V$2:$V$8801,"Última chance") -> 19 | N36: =SUMIFS(Pipeline_Completo!$S$2:$S$8801,Pipeline_Completo!$D$2:$D$8801,$C36,Pipeline_Completo!$V$2:$V$8801,"Saudável")+SUMIFS(Pipeline_Completo!$S$2:$S$8801,Pipeline_Completo!$D$2:$D$8801,$C36,Pipeline_Completo!$V$2:$V$8801,"Esfriando")+SUMIFS(Pipeline_Completo!$S$2:$S$8801,Pipeline_Completo!$D$2:$D$8801,$C36,Pipeline_Completo!$V$2:$V$8801,"Última chance") -> 32105 | O36: =COUNTIFS(Pipeline_Completo!$D$2:$D$8801,$C36,Pipeline_Completo!$V$2:$V$8801,"Zumbi") -> 60 | P36: =SUMIFS(Pipeline_Completo!$S$2:$S$8801,Pipeline_Completo!$D$2:$D$8801,$C36,Pipeline_Completo!$V$2:$V$8801,"Zumbi") -> 250651 | Q36: =IFERROR(P36/(N36+P36),"") -> 0.88645687 | R36: =COUNTIFS(Pipeline_Completo!$D$2:$D$8801,$C36,Pipeline_Completo!$O$2:$O$8801,"Engaging",Pipeline_Completo!$E$2:$E$8801,"")+COUNTIFS(Pipeline_Completo!$D$2:$D$8801,$C36,Pipeline_Completo!$O$2:$O$8801,"Prospecting",Pipeline_Completo!$E$2:$E$8801,"") -> 52
A37: West | B37: Celia Rouche | C37: Elease Gluck | D37: =COUNTIFS(Pipeline_Completo!$D$2:$D$8801,$C37) -> 177 | E37: =COUNTIFS(Pipeline_Completo!$D$2:$D$8801,$C37,Pipeline_Completo!$O$2:$O$8801,"Won") -> 80 | F37: =COUNTIFS(Pipeline_Completo!$D$2:$D$8801,$C37,Pipeline_Completo!$O$2:$O$8801,"Lost") -> 46 | G37: =COUNTIFS(Pipeline_Completo!$D$2:$D$8801,$C37,Pipeline_Completo!$O$2:$O$8801,"Engaging") -> 51 | H37: =COUNTIFS(Pipeline_Completo!$D$2:$D$8801,$C37,Pipeline_Completo!$O$2:$O$8801,"Prospecting") -> 0 | I37: =IFERROR(E37/(E37+F37),"") -> 0.63492063 | J37: =SUMIFS(Pipeline_Completo!$R$2:$R$8801,Pipeline_Completo!$D$2:$D$8801,$C37,Pipeline_Completo!$O$2:$O$8801,"Won") -> 289195 | K37: =IFERROR(J37/E37,"") -> 3614.9375 | L37: =SUMIFS(Pipeline_Completo!$S$2:$S$8801,Pipeline_Completo!$D$2:$D$8801,$C37,Pipeline_Completo!$O$2:$O$8801,"Engaging")+SUMIFS(Pipeline_Completo!$S$2:$S$8801,Pipeline_Completo!$D$2:$D$8801,$C37,Pipeline_Completo!$O$2:$O$8801,"Prospecting") -> 251649 | M37: =COUNTIFS(Pipeline_Completo!$D$2:$D$8801,$C37,Pipeline_Completo!$V$2:$V$8801,"Saudável")+COUNTIFS(Pipeline_Completo!$D$2:$D$8801,$C37,Pipeline_Completo!$V$2:$V$8801,"Esfriando")+COUNTIFS(Pipeline_Completo!$D$2:$D$8801,$C37,Pipeline_Completo!$V$2:$V$8801,"Última chance") -> 12 | N37: =SUMIFS(Pipeline_Completo!$S$2:$S$8801,Pipeline_Completo!$D$2:$D$8801,$C37,Pipeline_Completo!$V$2:$V$8801,"Saudável")+SUMIFS(Pipeline_Completo!$S$2:$S$8801,Pipeline_Completo!$D$2:$D$8801,$C37,Pipeline_Completo!$V$2:$V$8801,"Esfriando")+SUMIFS(Pipeline_Completo!$S$2:$S$8801,Pipeline_Completo!$D$2:$D$8801,$C37,Pipeline_Completo!$V$2:$V$8801,"Última chance") -> 20659 | O37: =COUNTIFS(Pipeline_Completo!$D$2:$D$8801,$C37,Pipeline_Completo!$V$2:$V$8801,"Zumbi") -> 39 | P37: =SUMIFS(Pipeline_Completo!$S$2:$S$8801,Pipeline_Completo!$D$2:$D$8801,$C37,Pipeline_Completo!$V$2:$V$8801,"Zumbi") -> 230990 | Q37: =IFERROR(P37/(N37+P37),"") -> 0.9179055 | R37: =COUNTIFS(Pipeline_Completo!$D$2:$D$8801,$C37,Pipeline_Completo!$O$2:$O$8801,"Engaging",Pipeline_Completo!$E$2:$E$8801,"")+COUNTIFS(Pipeline_Completo!$D$2:$D$8801,$C37,Pipeline_Completo!$O$2:$O$8801,"Prospecting",Pipeline_Completo!$E$2:$E$8801,"") -> 33
A38: West | B38: Celia Rouche | C38: Carol Thompson | D38: =COUNTIFS(Pipeline_Completo!$D$2:$D$8801,$C38) -> 0 | E38: =COUNTIFS(Pipeline_Completo!$D$2:$D$8801,$C38,Pipeline_Completo!$O$2:$O$8801,"Won") -> 0 | F38: =COUNTIFS(Pipeline_Completo!$D$2:$D$8801,$C38,Pipeline_Completo!$O$2:$O$8801,"Lost") -> 0 | G38: =COUNTIFS(Pipeline_Completo!$D$2:$D$8801,$C38,Pipeline_Completo!$O$2:$O$8801,"Engaging") -> 0 | H38: =COUNTIFS(Pipeline_Completo!$D$2:$D$8801,$C38,Pipeline_Completo!$O$2:$O$8801,"Prospecting") -> 0 | I38: =IFERROR(E38/(E38+F38),"") | J38: =SUMIFS(Pipeline_Completo!$R$2:$R$8801,Pipeline_Completo!$D$2:$D$8801,$C38,Pipeline_Completo!$O$2:$O$8801,"Won") -> 0 | K38: =IFERROR(J38/E38,"") | L38: =SUMIFS(Pipeline_Completo!$S$2:$S$8801,Pipeline_Completo!$D$2:$D$8801,$C38,Pipeline_Completo!$O$2:$O$8801,"Engaging")+SUMIFS(Pipeline_Completo!$S$2:$S$8801,Pipeline_Completo!$D$2:$D$8801,$C38,Pipeline_Completo!$O$2:$O$8801,"Prospecting") -> 0 | M38: =COUNTIFS(Pipeline_Completo!$D$2:$D$8801,$C38,Pipeline_Completo!$V$2:$V$8801,"Saudável")+COUNTIFS(Pipeline_Completo!$D$2:$D$8801,$C38,Pipeline_Completo!$V$2:$V$8801,"Esfriando")+COUNTIFS(Pipeline_Completo!$D$2:$D$8801,$C38,Pipeline_Completo!$V$2:$V$8801,"Última chance") -> 0 | N38: =SUMIFS(Pipeline_Completo!$S$2:$S$8801,Pipeline_Completo!$D$2:$D$8801,$C38,Pipeline_Completo!$V$2:$V$8801,"Saudável")+SUMIFS(Pipeline_Completo!$S$2:$S$8801,Pipeline_Completo!$D$2:$D$8801,$C38,Pipeline_Completo!$V$2:$V$8801,"Esfriando")+SUMIFS(Pipeline_Completo!$S$2:$S$8801,Pipeline_Completo!$D$2:$D$8801,$C38,Pipeline_Completo!$V$2:$V$8801,"Última chance") -> 0 | O38: =COUNTIFS(Pipeline_Completo!$D$2:$D$8801,$C38,Pipeline_Completo!$V$2:$V$8801,"Zumbi") -> 0 | P38: =SUMIFS(Pipeline_Completo!$S$2:$S$8801,Pipeline_Completo!$D$2:$D$8801,$C38,Pipeline_Completo!$V$2:$V$8801,"Zumbi") -> 0 | Q38: =IFERROR(P38/(N38+P38),"") | R38: =COUNTIFS(Pipeline_Completo!$D$2:$D$8801,$C38,Pipeline_Completo!$O$2:$O$8801,"Engaging",Pipeline_Completo!$E$2:$E$8801,"")+COUNTIFS(Pipeline_Completo!$D$2:$D$8801,$C38,Pipeline_Completo!$O$2:$O$8801,"Prospecting",Pipeline_Completo!$E$2:$E$8801,"") -> 0
A39: West | B39: Celia Rouche | C39: Subtotal Celia Rouche | D39: =COUNTIFS(Pipeline_Completo!$C$2:$C$8801,$B39) -> 1296 | E39: =COUNTIFS(Pipeline_Completo!$C$2:$C$8801,$B39,Pipeline_Completo!$O$2:$O$8801,"Won") -> 610 | F39: =COUNTIFS(Pipeline_Completo!$C$2:$C$8801,$B39,Pipeline_Completo!$O$2:$O$8801,"Lost") -> 352 | G39: =COUNTIFS(Pipeline_Completo!$C$2:$C$8801,$B39,Pipeline_Completo!$O$2:$O$8801,"Engaging") -> 334 | H39: =COUNTIFS(Pipeline_Completo!$C$2:$C$8801,$B39,Pipeline_Completo!$O$2:$O$8801,"Prospecting") -> 0 | I39: =IFERROR(E39/(E39+F39),"") -> 0.63409563 | J39: =SUMIFS(Pipeline_Completo!$R$2:$R$8801,Pipeline_Completo!$C$2:$C$8801,$B39,Pipeline_Completo!$O$2:$O$8801,"Won") -> 1603897 | K39: =IFERROR(J39/E39,"") -> 2629.3393 | L39: =SUMIFS(Pipeline_Completo!$S$2:$S$8801,Pipeline_Completo!$C$2:$C$8801,$B39,Pipeline_Completo!$O$2:$O$8801,"Engaging")+SUMIFS(Pipeline_Completo!$S$2:$S$8801,Pipeline_Completo!$C$2:$C$8801,$B39,Pipeline_Completo!$O$2:$O$8801,"Prospecting") -> 1004925 | M39: =COUNTIFS(Pipeline_Completo!$C$2:$C$8801,$B39,Pipeline_Completo!$V$2:$V$8801,"Saudável")+COUNTIFS(Pipeline_Completo!$C$2:$C$8801,$B39,Pipeline_Completo!$V$2:$V$8801,"Esfriando")+COUNTIFS(Pipeline_Completo!$C$2:$C$8801,$B39,Pipeline_Completo!$V$2:$V$8801,"Última chance") -> 77 | N39: =SUMIFS(Pipeline_Completo!$S$2:$S$8801,Pipeline_Completo!$C$2:$C$8801,$B39,Pipeline_Completo!$V$2:$V$8801,"Saudável")+SUMIFS(Pipeline_Completo!$S$2:$S$8801,Pipeline_Completo!$C$2:$C$8801,$B39,Pipeline_Completo!$V$2:$V$8801,"Esfriando")+SUMIFS(Pipeline_Completo!$S$2:$S$8801,Pipeline_Completo!$C$2:$C$8801,$B39,Pipeline_Completo!$V$2:$V$8801,"Última chance") -> 151155 | O39: =COUNTIFS(Pipeline_Completo!$C$2:$C$8801,$B39,Pipeline_Completo!$V$2:$V$8801,"Zumbi") -> 257 | P39: =SUMIFS(Pipeline_Completo!$S$2:$S$8801,Pipeline_Completo!$C$2:$C$8801,$B39,Pipeline_Completo!$V$2:$V$8801,"Zumbi") -> 853770 | Q39: =IFERROR(P39/(N39+P39),"") -> 0.84958579 | R39: =COUNTIFS(Pipeline_Completo!$C$2:$C$8801,$B39,Pipeline_Completo!$O$2:$O$8801,"Engaging",Pipeline_Completo!$E$2:$E$8801,"")+COUNTIFS(Pipeline_Completo!$C$2:$C$8801,$B39,Pipeline_Completo!$O$2:$O$8801,"Prospecting",Pipeline_Completo!$E$2:$E$8801,"") -> 232
A40: West | B40: Summer Sewald | C40: James Ascencio | D40: =COUNTIFS(Pipeline_Completo!$D$2:$D$8801,$C40) -> 267 | E40: =COUNTIFS(Pipeline_Completo!$D$2:$D$8801,$C40,Pipeline_Completo!$O$2:$O$8801,"Won") -> 135 | F40: =COUNTIFS(Pipeline_Completo!$D$2:$D$8801,$C40,Pipeline_Completo!$O$2:$O$8801,"Lost") -> 71 | G40: =COUNTIFS(Pipeline_Completo!$D$2:$D$8801,$C40,Pipeline_Completo!$O$2:$O$8801,"Engaging") -> 61 | H40: =COUNTIFS(Pipeline_Completo!$D$2:$D$8801,$C40,Pipeline_Completo!$O$2:$O$8801,"Prospecting") -> 0 | I40: =IFERROR(E40/(E40+F40),"") -> 0.65533981 | J40: =SUMIFS(Pipeline_Completo!$R$2:$R$8801,Pipeline_Completo!$D$2:$D$8801,$C40,Pipeline_Completo!$O$2:$O$8801,"Won") -> 413533 | K40: =IFERROR(J40/E40,"") -> 3063.2074 | L40: =SUMIFS(Pipeline_Completo!$S$2:$S$8801,Pipeline_Completo!$D$2:$D$8801,$C40,Pipeline_Completo!$O$2:$O$8801,"Engaging")+SUMIFS(Pipeline_Completo!$S$2:$S$8801,Pipeline_Completo!$D$2:$D$8801,$C40,Pipeline_Completo!$O$2:$O$8801,"Prospecting") -> 192216 | M40: =COUNTIFS(Pipeline_Completo!$D$2:$D$8801,$C40,Pipeline_Completo!$V$2:$V$8801,"Saudável")+COUNTIFS(Pipeline_Completo!$D$2:$D$8801,$C40,Pipeline_Completo!$V$2:$V$8801,"Esfriando")+COUNTIFS(Pipeline_Completo!$D$2:$D$8801,$C40,Pipeline_Completo!$V$2:$V$8801,"Última chance") -> 14 | N40: =SUMIFS(Pipeline_Completo!$S$2:$S$8801,Pipeline_Completo!$D$2:$D$8801,$C40,Pipeline_Completo!$V$2:$V$8801,"Saudável")+SUMIFS(Pipeline_Completo!$S$2:$S$8801,Pipeline_Completo!$D$2:$D$8801,$C40,Pipeline_Completo!$V$2:$V$8801,"Esfriando")+SUMIFS(Pipeline_Completo!$S$2:$S$8801,Pipeline_Completo!$D$2:$D$8801,$C40,Pipeline_Completo!$V$2:$V$8801,"Última chance") -> 58024 | O40: =COUNTIFS(Pipeline_Completo!$D$2:$D$8801,$C40,Pipeline_Completo!$V$2:$V$8801,"Zumbi") -> 47 | P40: =SUMIFS(Pipeline_Completo!$S$2:$S$8801,Pipeline_Completo!$D$2:$D$8801,$C40,Pipeline_Completo!$V$2:$V$8801,"Zumbi") -> 134192 | Q40: =IFERROR(P40/(N40+P40),"") -> 0.69813127 | R40: =COUNTIFS(Pipeline_Completo!$D$2:$D$8801,$C40,Pipeline_Completo!$O$2:$O$8801,"Engaging",Pipeline_Completo!$E$2:$E$8801,"")+COUNTIFS(Pipeline_Completo!$D$2:$D$8801,$C40,Pipeline_Completo!$O$2:$O$8801,"Prospecting",Pipeline_Completo!$E$2:$E$8801,"") -> 44
A41: West | B41: Summer Sewald | C41: Kary Hendrixson | D41: =COUNTIFS(Pipeline_Completo!$D$2:$D$8801,$C41) -> 438 | E41: =COUNTIFS(Pipeline_Completo!$D$2:$D$8801,$C41,Pipeline_Completo!$O$2:$O$8801,"Won") -> 209 | F41: =COUNTIFS(Pipeline_Completo!$D$2:$D$8801,$C41,Pipeline_Completo!$O$2:$O$8801,"Lost") -> 126 | G41: =COUNTIFS(Pipeline_Completo!$D$2:$D$8801,$C41,Pipeline_Completo!$O$2:$O$8801,"Engaging") -> 103 | H41: =COUNTIFS(Pipeline_Completo!$D$2:$D$8801,$C41,Pipeline_Completo!$O$2:$O$8801,"Prospecting") -> 0 | I41: =IFERROR(E41/(E41+F41),"") -> 0.6238806 | J41: =SUMIFS(Pipeline_Completo!$R$2:$R$8801,Pipeline_Completo!$D$2:$D$8801,$C41,Pipeline_Completo!$O$2:$O$8801,"Won") -> 454298 | K41: =IFERROR(J41/E41,"") -> 2173.6746 | L41: =SUMIFS(Pipeline_Completo!$S$2:$S$8801,Pipeline_Completo!$D$2:$D$8801,$C41,Pipeline_Completo!$O$2:$O$8801,"Engaging")+SUMIFS(Pipeline_Completo!$S$2:$S$8801,Pipeline_Completo!$D$2:$D$8801,$C41,Pipeline_Completo!$O$2:$O$8801,"Prospecting") -> 276517 | M41: =COUNTIFS(Pipeline_Completo!$D$2:$D$8801,$C41,Pipeline_Completo!$V$2:$V$8801,"Saudável")+COUNTIFS(Pipeline_Completo!$D$2:$D$8801,$C41,Pipeline_Completo!$V$2:$V$8801,"Esfriando")+COUNTIFS(Pipeline_Completo!$D$2:$D$8801,$C41,Pipeline_Completo!$V$2:$V$8801,"Última chance") -> 21 | N41: =SUMIFS(Pipeline_Completo!$S$2:$S$8801,Pipeline_Completo!$D$2:$D$8801,$C41,Pipeline_Completo!$V$2:$V$8801,"Saudável")+SUMIFS(Pipeline_Completo!$S$2:$S$8801,Pipeline_Completo!$D$2:$D$8801,$C41,Pipeline_Completo!$V$2:$V$8801,"Esfriando")+SUMIFS(Pipeline_Completo!$S$2:$S$8801,Pipeline_Completo!$D$2:$D$8801,$C41,Pipeline_Completo!$V$2:$V$8801,"Última chance") -> 47250 | O41: =COUNTIFS(Pipeline_Completo!$D$2:$D$8801,$C41,Pipeline_Completo!$V$2:$V$8801,"Zumbi") -> 82 | P41: =SUMIFS(Pipeline_Completo!$S$2:$S$8801,Pipeline_Completo!$D$2:$D$8801,$C41,Pipeline_Completo!$V$2:$V$8801,"Zumbi") -> 229267 | Q41: =IFERROR(P41/(N41+P41),"") -> 0.82912443 | R41: =COUNTIFS(Pipeline_Completo!$D$2:$D$8801,$C41,Pipeline_Completo!$O$2:$O$8801,"Engaging",Pipeline_Completo!$E$2:$E$8801,"")+COUNTIFS(Pipeline_Completo!$D$2:$D$8801,$C41,Pipeline_Completo!$O$2:$O$8801,"Prospecting",Pipeline_Completo!$E$2:$E$8801,"") -> 66
A42: West | B42: Summer Sewald | C42: Kami Bicknell | D42: =COUNTIFS(Pipeline_Completo!$D$2:$D$8801,$C42) -> 362 | E42: =COUNTIFS(Pipeline_Completo!$D$2:$D$8801,$C42,Pipeline_Completo!$O$2:$O$8801,"Won") -> 174 | F42: =COUNTIFS(Pipeline_Completo!$D$2:$D$8801,$C42,Pipeline_Completo!$O$2:$O$8801,"Lost") -> 98 | G42: =COUNTIFS(Pipeline_Completo!$D$2:$D$8801,$C42,Pipeline_Completo!$O$2:$O$8801,"Engaging") -> 90 | H42: =COUNTIFS(Pipeline_Completo!$D$2:$D$8801,$C42,Pipeline_Completo!$O$2:$O$8801,"Prospecting") -> 0 | I42: =IFERROR(E42/(E42+F42),"") -> 0.63970588 | J42: =SUMIFS(Pipeline_Completo!$R$2:$R$8801,Pipeline_Completo!$D$2:$D$8801,$C42,Pipeline_Completo!$O$2:$O$8801,"Won") -> 316456 | K42: =IFERROR(J42/E42,"") -> 1818.7126 | L42: =SUMIFS(Pipeline_Completo!$S$2:$S$8801,Pipeline_Completo!$D$2:$D$8801,$C42,Pipeline_Completo!$O$2:$O$8801,"Engaging")+SUMIFS(Pipeline_Completo!$S$2:$S$8801,Pipeline_Completo!$D$2:$D$8801,$C42,Pipeline_Completo!$O$2:$O$8801,"Prospecting") -> 190990 | M42: =COUNTIFS(Pipeline_Completo!$D$2:$D$8801,$C42,Pipeline_Completo!$V$2:$V$8801,"Saudável")+COUNTIFS(Pipeline_Completo!$D$2:$D$8801,$C42,Pipeline_Completo!$V$2:$V$8801,"Esfriando")+COUNTIFS(Pipeline_Completo!$D$2:$D$8801,$C42,Pipeline_Completo!$V$2:$V$8801,"Última chance") -> 25 | N42: =SUMIFS(Pipeline_Completo!$S$2:$S$8801,Pipeline_Completo!$D$2:$D$8801,$C42,Pipeline_Completo!$V$2:$V$8801,"Saudável")+SUMIFS(Pipeline_Completo!$S$2:$S$8801,Pipeline_Completo!$D$2:$D$8801,$C42,Pipeline_Completo!$V$2:$V$8801,"Esfriando")+SUMIFS(Pipeline_Completo!$S$2:$S$8801,Pipeline_Completo!$D$2:$D$8801,$C42,Pipeline_Completo!$V$2:$V$8801,"Última chance") -> 63247 | O42: =COUNTIFS(Pipeline_Completo!$D$2:$D$8801,$C42,Pipeline_Completo!$V$2:$V$8801,"Zumbi") -> 65 | P42: =SUMIFS(Pipeline_Completo!$S$2:$S$8801,Pipeline_Completo!$D$2:$D$8801,$C42,Pipeline_Completo!$V$2:$V$8801,"Zumbi") -> 127743 | Q42: =IFERROR(P42/(N42+P42),"") -> 0.66884654 | R42: =COUNTIFS(Pipeline_Completo!$D$2:$D$8801,$C42,Pipeline_Completo!$O$2:$O$8801,"Engaging",Pipeline_Completo!$E$2:$E$8801,"")+COUNTIFS(Pipeline_Completo!$D$2:$D$8801,$C42,Pipeline_Completo!$O$2:$O$8801,"Prospecting",Pipeline_Completo!$E$2:$E$8801,"") -> 61
A43: West | B43: Summer Sewald | C43: Zane Levy | D43: =COUNTIFS(Pipeline_Completo!$D$2:$D$8801,$C43) -> 349 | E43: =COUNTIFS(Pipeline_Completo!$D$2:$D$8801,$C43,Pipeline_Completo!$O$2:$O$8801,"Won") -> 161 | F43: =COUNTIFS(Pipeline_Completo!$D$2:$D$8801,$C43,Pipeline_Completo!$O$2:$O$8801,"Lost") -> 100 | G43: =COUNTIFS(Pipeline_Completo!$D$2:$D$8801,$C43,Pipeline_Completo!$O$2:$O$8801,"Engaging") -> 88 | H43: =COUNTIFS(Pipeline_Completo!$D$2:$D$8801,$C43,Pipeline_Completo!$O$2:$O$8801,"Prospecting") -> 0 | I43: =IFERROR(E43/(E43+F43),"") -> 0.61685824 | J43: =SUMIFS(Pipeline_Completo!$R$2:$R$8801,Pipeline_Completo!$D$2:$D$8801,$C43,Pipeline_Completo!$O$2:$O$8801,"Won") -> 430068 | K43: =IFERROR(J43/E43,"") -> 2671.2298 | L43: =SUMIFS(Pipeline_Completo!$S$2:$S$8801,Pipeline_Completo!$D$2:$D$8801,$C43,Pipeline_Completo!$O$2:$O$8801,"Engaging")+SUMIFS(Pipeline_Completo!$S$2:$S$8801,Pipeline_Completo!$D$2:$D$8801,$C43,Pipeline_Completo!$O$2:$O$8801,"Prospecting") -> 193348 | M43: =COUNTIFS(Pipeline_Completo!$D$2:$D$8801,$C43,Pipeline_Completo!$V$2:$V$8801,"Saudável")+COUNTIFS(Pipeline_Completo!$D$2:$D$8801,$C43,Pipeline_Completo!$V$2:$V$8801,"Esfriando")+COUNTIFS(Pipeline_Completo!$D$2:$D$8801,$C43,Pipeline_Completo!$V$2:$V$8801,"Última chance") -> 31 | N43: =SUMIFS(Pipeline_Completo!$S$2:$S$8801,Pipeline_Completo!$D$2:$D$8801,$C43,Pipeline_Completo!$V$2:$V$8801,"Saudável")+SUMIFS(Pipeline_Completo!$S$2:$S$8801,Pipeline_Completo!$D$2:$D$8801,$C43,Pipeline_Completo!$V$2:$V$8801,"Esfriando")+SUMIFS(Pipeline_Completo!$S$2:$S$8801,Pipeline_Completo!$D$2:$D$8801,$C43,Pipeline_Completo!$V$2:$V$8801,"Última chance") -> 65831 | O43: =COUNTIFS(Pipeline_Completo!$D$2:$D$8801,$C43,Pipeline_Completo!$V$2:$V$8801,"Zumbi") -> 57 | P43: =SUMIFS(Pipeline_Completo!$S$2:$S$8801,Pipeline_Completo!$D$2:$D$8801,$C43,Pipeline_Completo!$V$2:$V$8801,"Zumbi") -> 127517 | Q43: =IFERROR(P43/(N43+P43),"") -> 0.65952066 | R43: =COUNTIFS(Pipeline_Completo!$D$2:$D$8801,$C43,Pipeline_Completo!$O$2:$O$8801,"Engaging",Pipeline_Completo!$E$2:$E$8801,"")+COUNTIFS(Pipeline_Completo!$D$2:$D$8801,$C43,Pipeline_Completo!$O$2:$O$8801,"Prospecting",Pipeline_Completo!$E$2:$E$8801,"") -> 59
A44: West | B44: Summer Sewald | C44: Maureen Marcano | D44: =COUNTIFS(Pipeline_Completo!$D$2:$D$8801,$C44) -> 285 | E44: =COUNTIFS(Pipeline_Completo!$D$2:$D$8801,$C44,Pipeline_Completo!$O$2:$O$8801,"Won") -> 149 | F44: =COUNTIFS(Pipeline_Completo!$D$2:$D$8801,$C44,Pipeline_Completo!$O$2:$O$8801,"Lost") -> 64 | G44: =COUNTIFS(Pipeline_Completo!$D$2:$D$8801,$C44,Pipeline_Completo!$O$2:$O$8801,"Engaging") -> 72 | H44: =COUNTIFS(Pipeline_Completo!$D$2:$D$8801,$C44,Pipeline_Completo!$O$2:$O$8801,"Prospecting") -> 0 | I44: =IFERROR(E44/(E44+F44),"") -> 0.69953052 | J44: =SUMIFS(Pipeline_Completo!$R$2:$R$8801,Pipeline_Completo!$D$2:$D$8801,$C44,Pipeline_Completo!$O$2:$O$8801,"Won") -> 350395 | K44: =IFERROR(J44/E44,"") -> 2351.6443 | L44: =SUMIFS(Pipeline_Completo!$S$2:$S$8801,Pipeline_Completo!$D$2:$D$8801,$C44,Pipeline_Completo!$O$2:$O$8801,"Engaging")+SUMIFS(Pipeline_Completo!$S$2:$S$8801,Pipeline_Completo!$D$2:$D$8801,$C44,Pipeline_Completo!$O$2:$O$8801,"Prospecting") -> 140225 | M44: =COUNTIFS(Pipeline_Completo!$D$2:$D$8801,$C44,Pipeline_Completo!$V$2:$V$8801,"Saudável")+COUNTIFS(Pipeline_Completo!$D$2:$D$8801,$C44,Pipeline_Completo!$V$2:$V$8801,"Esfriando")+COUNTIFS(Pipeline_Completo!$D$2:$D$8801,$C44,Pipeline_Completo!$V$2:$V$8801,"Última chance") -> 18 | N44: =SUMIFS(Pipeline_Completo!$S$2:$S$8801,Pipeline_Completo!$D$2:$D$8801,$C44,Pipeline_Completo!$V$2:$V$8801,"Saudável")+SUMIFS(Pipeline_Completo!$S$2:$S$8801,Pipeline_Completo!$D$2:$D$8801,$C44,Pipeline_Completo!$V$2:$V$8801,"Esfriando")+SUMIFS(Pipeline_Completo!$S$2:$S$8801,Pipeline_Completo!$D$2:$D$8801,$C44,Pipeline_Completo!$V$2:$V$8801,"Última chance") -> 40823 | O44: =COUNTIFS(Pipeline_Completo!$D$2:$D$8801,$C44,Pipeline_Completo!$V$2:$V$8801,"Zumbi") -> 54 | P44: =SUMIFS(Pipeline_Completo!$S$2:$S$8801,Pipeline_Completo!$D$2:$D$8801,$C44,Pipeline_Completo!$V$2:$V$8801,"Zumbi") -> 99402 | Q44: =IFERROR(P44/(N44+P44),"") -> 0.70887502 | R44: =COUNTIFS(Pipeline_Completo!$D$2:$D$8801,$C44,Pipeline_Completo!$O$2:$O$8801,"Engaging",Pipeline_Completo!$E$2:$E$8801,"")+COUNTIFS(Pipeline_Completo!$D$2:$D$8801,$C44,Pipeline_Completo!$O$2:$O$8801,"Prospecting",Pipeline_Completo!$E$2:$E$8801,"") -> 56
A45: West | B45: Summer Sewald | C45: Carl Lin | D45: =COUNTIFS(Pipeline_Completo!$D$2:$D$8801,$C45) -> 0 | E45: =COUNTIFS(Pipeline_Completo!$D$2:$D$8801,$C45,Pipeline_Completo!$O$2:$O$8801,"Won") -> 0 | F45: =COUNTIFS(Pipeline_Completo!$D$2:$D$8801,$C45,Pipeline_Completo!$O$2:$O$8801,"Lost") -> 0 | G45: =COUNTIFS(Pipeline_Completo!$D$2:$D$8801,$C45,Pipeline_Completo!$O$2:$O$8801,"Engaging") -> 0 | H45: =COUNTIFS(Pipeline_Completo!$D$2:$D$8801,$C45,Pipeline_Completo!$O$2:$O$8801,"Prospecting") -> 0 | I45: =IFERROR(E45/(E45+F45),"") | J45: =SUMIFS(Pipeline_Completo!$R$2:$R$8801,Pipeline_Completo!$D$2:$D$8801,$C45,Pipeline_Completo!$O$2:$O$8801,"Won") -> 0 | K45: =IFERROR(J45/E45,"") | L45: =SUMIFS(Pipeline_Completo!$S$2:$S$8801,Pipeline_Completo!$D$2:$D$8801,$C45,Pipeline_Completo!$O$2:$O$8801,"Engaging")+SUMIFS(Pipeline_Completo!$S$2:$S$8801,Pipeline_Completo!$D$2:$D$8801,$C45,Pipeline_Completo!$O$2:$O$8801,"Prospecting") -> 0 | M45: =COUNTIFS(Pipeline_Completo!$D$2:$D$8801,$C45,Pipeline_Completo!$V$2:$V$8801,"Saudável")+COUNTIFS(Pipeline_Completo!$D$2:$D$8801,$C45,Pipeline_Completo!$V$2:$V$8801,"Esfriando")+COUNTIFS(Pipeline_Completo!$D$2:$D$8801,$C45,Pipeline_Completo!$V$2:$V$8801,"Última chance") -> 0 | N45: =SUMIFS(Pipeline_Completo!$S$2:$S$8801,Pipeline_Completo!$D$2:$D$8801,$C45,Pipeline_Completo!$V$2:$V$8801,"Saudável")+SUMIFS(Pipeline_Completo!$S$2:$S$8801,Pipeline_Completo!$D$2:$D$8801,$C45,Pipeline_Completo!$V$2:$V$8801,"Esfriando")+SUMIFS(Pipeline_Completo!$S$2:$S$8801,Pipeline_Completo!$D$2:$D$8801,$C45,Pipeline_Completo!$V$2:$V$8801,"Última chance") -> 0 | O45: =COUNTIFS(Pipeline_Completo!$D$2:$D$8801,$C45,Pipeline_Completo!$V$2:$V$8801,"Zumbi") -> 0 | P45: =SUMIFS(Pipeline_Completo!$S$2:$S$8801,Pipeline_Completo!$D$2:$D$8801,$C45,Pipeline_Completo!$V$2:$V$8801,"Zumbi") -> 0 | Q45: =IFERROR(P45/(N45+P45),"") | R45: =COUNTIFS(Pipeline_Completo!$D$2:$D$8801,$C45,Pipeline_Completo!$O$2:$O$8801,"Engaging",Pipeline_Completo!$E$2:$E$8801,"")+COUNTIFS(Pipeline_Completo!$D$2:$D$8801,$C45,Pipeline_Completo!$O$2:$O$8801,"Prospecting",Pipeline_Completo!$E$2:$E$8801,"") -> 0
A46: West | B46: Summer Sewald | C46: Subtotal Summer Sewald | D46: =COUNTIFS(Pipeline_Completo!$C$2:$C$8801,$B46) -> 1701 | E46: =COUNTIFS(Pipeline_Completo!$C$2:$C$8801,$B46,Pipeline_Completo!$O$2:$O$8801,"Won") -> 828 | F46: =COUNTIFS(Pipeline_Completo!$C$2:$C$8801,$B46,Pipeline_Completo!$O$2:$O$8801,"Lost") -> 459 | G46: =COUNTIFS(Pipeline_Completo!$C$2:$C$8801,$B46,Pipeline_Completo!$O$2:$O$8801,"Engaging") -> 414 | H46: =COUNTIFS(Pipeline_Completo!$C$2:$C$8801,$B46,Pipeline_Completo!$O$2:$O$8801,"Prospecting") -> 0 | I46: =IFERROR(E46/(E46+F46),"") -> 0.64335664 | J46: =SUMIFS(Pipeline_Completo!$R$2:$R$8801,Pipeline_Completo!$C$2:$C$8801,$B46,Pipeline_Completo!$O$2:$O$8801,"Won") -> 1964750 | K46: =IFERROR(J46/E46,"") -> 2372.8865 | L46: =SUMIFS(Pipeline_Completo!$S$2:$S$8801,Pipeline_Completo!$C$2:$C$8801,$B46,Pipeline_Completo!$O$2:$O$8801,"Engaging")+SUMIFS(Pipeline_Completo!$S$2:$S$8801,Pipeline_Completo!$C$2:$C$8801,$B46,Pipeline_Completo!$O$2:$O$8801,"Prospecting") -> 993296 | M46: =COUNTIFS(Pipeline_Completo!$C$2:$C$8801,$B46,Pipeline_Completo!$V$2:$V$8801,"Saudável")+COUNTIFS(Pipeline_Completo!$C$2:$C$8801,$B46,Pipeline_Completo!$V$2:$V$8801,"Esfriando")+COUNTIFS(Pipeline_Completo!$C$2:$C$8801,$B46,Pipeline_Completo!$V$2:$V$8801,"Última chance") -> 109 | N46: =SUMIFS(Pipeline_Completo!$S$2:$S$8801,Pipeline_Completo!$C$2:$C$8801,$B46,Pipeline_Completo!$V$2:$V$8801,"Saudável")+SUMIFS(Pipeline_Completo!$S$2:$S$8801,Pipeline_Completo!$C$2:$C$8801,$B46,Pipeline_Completo!$V$2:$V$8801,"Esfriando")+SUMIFS(Pipeline_Completo!$S$2:$S$8801,Pipeline_Completo!$C$2:$C$8801,$B46,Pipeline_Completo!$V$2:$V$8801,"Última chance") -> 275175 | O46: =COUNTIFS(Pipeline_Completo!$C$2:$C$8801,$B46,Pipeline_Completo!$V$2:$V$8801,"Zumbi") -> 305 | P46: =SUMIFS(Pipeline_Completo!$S$2:$S$8801,Pipeline_Completo!$C$2:$C$8801,$B46,Pipeline_Completo!$V$2:$V$8801,"Zumbi") -> 718121 | Q46: =IFERROR(P46/(N46+P46),"") -> 0.72296778 | R46: =COUNTIFS(Pipeline_Completo!$C$2:$C$8801,$B46,Pipeline_Completo!$O$2:$O$8801,"Engaging",Pipeline_Completo!$E$2:$E$8801,"")+COUNTIFS(Pipeline_Completo!$C$2:$C$8801,$B46,Pipeline_Completo!$O$2:$O$8801,"Prospecting",Pipeline_Completo!$E$2:$E$8801,"") -> 286
A47: West | C47: TOTAL escritório West | D47: =COUNTIFS(Pipeline_Completo!$B$2:$B$8801,$A47) -> 2997 | E47: =COUNTIFS(Pipeline_Completo!$B$2:$B$8801,$A47,Pipeline_Completo!$O$2:$O$8801,"Won") -> 1438 | F47: =COUNTIFS(Pipeline_Completo!$B$2:$B$8801,$A47,Pipeline_Completo!$O$2:$O$8801,"Lost") -> 811 | G47: =COUNTIFS(Pipeline_Completo!$B$2:$B$8801,$A47,Pipeline_Completo!$O$2:$O$8801,"Engaging") -> 748 | H47: =COUNTIFS(Pipeline_Completo!$B$2:$B$8801,$A47,Pipeline_Completo!$O$2:$O$8801,"Prospecting") -> 0 | I47: =IFERROR(E47/(E47+F47),"") -> 0.63939529 | J47: =SUMIFS(Pipeline_Completo!$R$2:$R$8801,Pipeline_Completo!$B$2:$B$8801,$A47,Pipeline_Completo!$O$2:$O$8801,"Won") -> 3568647 | K47: =IFERROR(J47/E47,"") -> 2481.6739 | L47: =SUMIFS(Pipeline_Completo!$S$2:$S$8801,Pipeline_Completo!$B$2:$B$8801,$A47,Pipeline_Completo!$O$2:$O$8801,"Engaging")+SUMIFS(Pipeline_Completo!$S$2:$S$8801,Pipeline_Completo!$B$2:$B$8801,$A47,Pipeline_Completo!$O$2:$O$8801,"Prospecting") -> 1998221 | M47: =COUNTIFS(Pipeline_Completo!$B$2:$B$8801,$A47,Pipeline_Completo!$V$2:$V$8801,"Saudável")+COUNTIFS(Pipeline_Completo!$B$2:$B$8801,$A47,Pipeline_Completo!$V$2:$V$8801,"Esfriando")+COUNTIFS(Pipeline_Completo!$B$2:$B$8801,$A47,Pipeline_Completo!$V$2:$V$8801,"Última chance") -> 186 | N47: =SUMIFS(Pipeline_Completo!$S$2:$S$8801,Pipeline_Completo!$B$2:$B$8801,$A47,Pipeline_Completo!$V$2:$V$8801,"Saudável")+SUMIFS(Pipeline_Completo!$S$2:$S$8801,Pipeline_Completo!$B$2:$B$8801,$A47,Pipeline_Completo!$V$2:$V$8801,"Esfriando")+SUMIFS(Pipeline_Completo!$S$2:$S$8801,Pipeline_Completo!$B$2:$B$8801,$A47,Pipeline_Completo!$V$2:$V$8801,"Última chance") -> 426330 | O47: =COUNTIFS(Pipeline_Completo!$B$2:$B$8801,$A47,Pipeline_Completo!$V$2:$V$8801,"Zumbi") -> 562 | P47: =SUMIFS(Pipeline_Completo!$S$2:$S$8801,Pipeline_Completo!$B$2:$B$8801,$A47,Pipeline_Completo!$V$2:$V$8801,"Zumbi") -> 1571891 | Q47: =IFERROR(P47/(N47+P47),"") -> 0.78664522 | R47: =COUNTIFS(Pipeline_Completo!$B$2:$B$8801,$A47,Pipeline_Completo!$O$2:$O$8801,"Engaging",Pipeline_Completo!$E$2:$E$8801,"")+COUNTIFS(Pipeline_Completo!$B$2:$B$8801,$A47,Pipeline_Completo!$O$2:$O$8801,"Prospecting",Pipeline_Completo!$E$2:$E$8801,"") -> 518
C49: TOTAL GERAL | D49: =D15+D31+D47 -> 8800 | E49: =E15+E31+E47 -> 4238 | F49: =F15+F31+F47 -> 2473 | G49: =G15+G31+G47 -> 1589 | H49: =H15+H31+H47 -> 500 | I49: =IFERROR(E49/(E49+F49),"") -> 0.63150052 | J49: =J15+J31+J47 -> 10005534 | K49: =IFERROR(J49/E49,"") -> 2360.9094 | L49: =L15+L31+L47 -> 4966215 | M49: =M15+M31+M47 -> 298 | N49: =N15+N31+N47 -> 693565 | O49: =O15+O31+O47 -> 1291 | P49: =P15+P31+P47 -> 3198664 | Q49: =IFERROR(P49/(N49+P49),"") -> 0.82180776 | R49: =R15+R31+R47 -> 1425
A51: Linhas em laranja (Deals total = 0): vendedores cadastrados em sales_teams sem nenhuma oportunidade no pipeline.
A52: Check: TOTAL GERAL de "Deals total" deve ser 8.800 → | D52: =IF(D49=COUNTA(Pipeline_Completo!$A$2:$A$8801),"OK","ERRO") -> OK

Sheet Pipeline_Completo
A1: opportunity_id | B1: Escritório | C1: Gerente | D1: Vendedor | E1: Conta | F1: Setor | G1: Receita conta (US$ mi) | H1: Funcionários | I1: País sede | J1: Empresa-mãe | K1: Ano fundação | L1: Produto | M1: Série | N1: Preço tabela (US$) | O1: Estágio | P1: engage_date | Q1: close_date | R1: close_value (US$) | S1: Valor considerado (US$) | T1: Ciclo (dias) | U1: Idade aberto (dias) | V1: Relógio | W1: Ganho (1/0) | X1: Produto corrigido? | Y1: Conta faltando?
A2: ZNBS69V1 | B2: Central | C2: Dustin Brinkmann | D2: Anna Snelling | E2: Ron-tech | F2: medical | G2: 3922.42 | H2: 6837 | I2: United States | K2: 1992 | L2: MG Special | M2: MG | N2: 55 | O2: Won | P2: 42672 | Q2: 42795 | R2: 49 | S2: =IF(O2="Won",R2,IF(O2="Lost",0,N2)) -> 49 | T2: =IF(AND(P2<>"",Q2<>""),Q2-P2,"") -> 123 | U2: =IF(AND(O2="Engaging",P2<>""),'Leia-me'!$B$5-P2,"") | V2: =IF(O2<>"Engaging","",IF(U2<='Leia-me'!$B$6,"Saudável",IF(U2<='Leia-me'!$B$7,"Esfriando",IF(U2<='Leia-me'!$B$8,"Última chance","Zumbi")))) | W2: =IF(O2="Won",1,IF(O2="Lost",0,"")) -> 1 | Y2: =IF(E2="","Sim","")
A3: NL3JZH1Z | B3: Central | C3: Dustin Brinkmann | D3: Anna Snelling | E3: Bioholding | F3: medical | G3: 587.34 | H3: 1356 | I3: Philipines | K3: 2012 | L3: MG Special | M3: MG | N3: 55 | O3: Won | P3: 42678 | Q3: 42804 | R3: 53 | S3: =IF(O3="Won",R3,IF(O3="Lost",0,N3)) -> 53 | T3: =IF(AND(P3<>"",Q3<>""),Q3-P3,"") -> 126 | U3: =IF(AND(O3="Engaging",P3<>""),'Leia-me'!$B$5-P3,"") | V3: =IF(O3<>"Engaging","",IF(U3<='Leia-me'!$B$6,"Saudável",IF(U3<='Leia-me'!$B$7,"Esfriando",IF(U3<='Leia-me'!$B$8,"Última chance","Zumbi")))) | W3: =IF(O3="Won",1,IF(O3="Lost",0,"")) -> 1 | Y3: =IF(E3="","Sim","")
A4: 8SOQADK7 | B4: Central | C4: Dustin Brinkmann | D4: Anna Snelling | E4: Gogozoom | F4: telecommunications | G4: 86.68 | H4: 187 | I4: United States | J4: Sonron | K4: 2007 | L4: MG Special | M4: MG | N4: 55 | O4: Lost | P4: 42688 | Q4: 42824 | R4: 0 | S4: =IF(O4="Won",R4,IF(O4="Lost",0,N4)) -> 0 | T4: =IF(AND(P4<>"",Q4<>""),Q4-P4,"") -> 136 | U4: =IF(AND(O4="Engaging",P4<>""),'Leia-me'!$B$5-P4,"") | V4: =IF(O4<>"Engaging","",IF(U4<='Leia-me'!$B$6,"Saudável",IF(U4<='Leia-me'!$B$7,"Esfriando",IF(U4<='Leia-me'!$B$8,"Última chance","Zumbi")))) | W4: =IF(O4="Won",1,IF(O4="Lost",0,"")) -> 0 | Y4: =IF(E4="","Sim","")
A5: HEE6P0QH | B5: Central | C5: Dustin Brinkmann | D5: Anna Snelling | E5: Statholdings | F5: employment | G5: 291.27 | H5: 586 | I5: United States | K5: 1997 | L5: MG Advanced | M5: MG | N5: 3393 | O5: Won | P5: 42698 | Q5: 42819 | R5: 3647 | S5: =IF(O5="Won",R5,IF(O5="Lost",0,N5)) -> 3647 | T5: =IF(AND(P5<>"",Q5<>""),Q5-P5,"") -> 121 | U5: =IF(AND(O5="Engaging",P5<>""),'Leia-me'!$B$5-P5,"") | V5: =IF(O5<>"Engaging","",IF(U5<='Leia-me'!$B$6,"Saudável",IF(U5<='Leia-me'!$B$7,"Esfriando",IF(U5<='Leia-me'!$B$8,"Última chance","Zumbi")))) | W5: =IF(O5="Won",1,IF(O5="Lost",0,"")) -> 1 | Y5: =IF(E5="","Sim","")
A6: TTA9LYBS | B6: Central | C6: Dustin Brinkmann | D6: Anna Snelling | E6: Treequote | F6: telecommunications | G6: 5266.09 | H6: 8595 | I6: United States | J6: Sonron | K6: 1988 | L6: MG Special | M6: MG | N6: 55 | O6: Won | P6: 42699 | Q6: 42795 | R6: 58 | S6: =IF(O6="Won",R6,IF(O6="Lost",0,N6)) -> 58 | T6: =IF(AND(P6<>"",Q6<>""),Q6-P6,"") -> 96 | U6: =IF(AND(O6="Engaging",P6<>""),'Leia-me'!$B$5-P6,"") | V6: =IF(O6<>"Engaging","",IF(U6<='Leia-me'!$B$6,"Saudável",IF(U6<='Leia-me'!$B$7,"Esfriando",IF(U6<='Leia-me'!$B$8,"Última chance","Zumbi")))) | W6: =IF(O6="Won",1,IF(O6="Lost",0,"")) -> 1 | Y6: =IF(E6="","Sim","")
A7: K53BC1T9 | B7: Central | C7: Dustin Brinkmann | D7: Anna Snelling | E7: Domzoom | F7: entertainment | G7: 217.87 | H7: 551 | I7: United States | K7: 1998 | L7: MG Special | M7: MG | N7: 55 | O7: Lost | P7: 42700 | Q7: 42821 | R7: 0 | S7: =IF(O7="Won",R7,IF(O7="Lost",0,N7)) -> 0 | T7: =IF(AND(P7<>"",Q7<>""),Q7-P7,"") -> 121 | U7: =IF(AND(O7="Engaging",P7<>""),'Leia-me'!$B$5-P7,"") | V7: =IF(O7<>"Engaging","",IF(U7<='Leia-me'!$B$6,"Saudável",IF(U7<='Leia-me'!$B$7,"Esfriando",IF(U7<='Leia-me'!$B$8,"Última chance","Zumbi")))) | W7: =IF(O7="Won",1,IF(O7="Lost",0,"")) -> 0 | Y7: =IF(E7="","Sim","")
A8: 3X13866U | B8: Central | C8: Dustin Brinkmann | D8: Anna Snelling | E8: dambase | F8: marketing | G8: 2173.98 | H8: 2928 | I8: United States | J8: Inity | K8: 1995 | L8: GTX Plus Basic | M8: GTX | N8: 1096 | O8: Lost | P8: 42705 | Q8: 42800 | R8: 0 | S8: =IF(O8="Won",R8,IF(O8="Lost",0,N8)) -> 0 | T8: =IF(AND(P8<>"",Q8<>""),Q8-P8,"") -> 95 | U8: =IF(AND(O8="Engaging",P8<>""),'Leia-me'!$B$5-P8,"") | V8: =IF(O8<>"Engaging","",IF(U8<='Leia-me'!$B$6,"Saudável",IF(U8<='Leia-me'!$B$7,"Esfriando",IF(U8<='Leia-me'!$B$8,"Última chance","Zumbi")))) | W8: =IF(O8="Won",1,IF(O8="Lost",0,"")) -> 0 | Y8: =IF(E8="","Sim","")
A9: SKY95DVG | B9: Central | C9: Dustin Brinkmann | D9: Anna Snelling | E9: Betatech | F9: medical | G9: 647.18 | H9: 1185 | I9: Kenya | K9: 1986 | L9: MG Special | M9: MG | N9: 55 | O9: Lost | P9: 42713 | Q9: 42816 | R9: 0 | S9: =IF(O9="Won",R9,IF(O9="Lost",0,N9)) -> 0 | T9: =IF(AND(P9<>"",Q9<>""),Q9-P9,"") -> 103 | U9: =IF(AND(O9="Engaging",P9<>""),'Leia-me'!$B$5-P9,"") | V9: =IF(O9<>"Engaging","",IF(U9<='Leia-me'!$B$6,"Saudável",IF(U9<='Leia-me'!$B$7,"Esfriando",IF(U9<='Leia-me'!$B$8,"Última chance","Zumbi")))) | W9: =IF(O9="Won",1,IF(O9="Lost",0,"")) -> 0 | Y9: =IF(E9="","Sim","")
A10: 94GI0ZJ7 | B10: Central | C10: Dustin Brinkmann | D10: Anna Snelling | E10: Stanredtax | F10: finance | G10: 1698.2 | H10: 3798 | I10: United States | K10: 1987 | L10: GTX Plus Pro | M10: GTX | N10: 5482 | O10: Won | P10: 42719 | Q10: 42809 | R10: 5765 | S10: =IF(O10="Won",R10,IF(O10="Lost",0,N10)) -> 5765 | T10: =IF(AND(P10<>"",Q10<>""),Q10-P10,"") -> 90 | U10: =IF(AND(O10="Engaging",P10<>""),'Leia-me'!$B$5-P10,"") | V10: =IF(O10<>"Engaging","",IF(U10<='Leia-me'!$B$6,"Saudável",IF(U10<='Leia-me'!$B$7,"Esfriando",IF(U10<='Leia-me'!$B$8,"Última chance","Zumbi")))) | W10: =IF(O10="Won",1,IF(O10="Lost",0,"")) -> 1 | Y10: =IF(E10="","Sim","")
A11: W1KLFNE4 | B11: Central | C11: Dustin Brinkmann | D11: Anna Snelling | E11: Isdom | F11: medical | G11: 3178.24 | H11: 4540 | I11: United States | K11: 2002 | L11: MG Advanced | M11: MG | N11: 3393 | O11: Won | P11: 42722 | Q11: 42796 | R11: 3246 | S11: =IF(O11="Won",R11,IF(O11="Lost",0,N11)) -> 3246 | T11: =IF(AND(P11<>"",Q11<>""),Q11-P11,"") -> 74 | U11: =IF(AND(O11="Engaging",P11<>""),'Leia-me'!$B$5-P11,"") | V11: =IF(O11<>"Engaging","",IF(U11<='Leia-me'!$B$6,"Saudável",IF(U11<='Leia-me'!$B$7,"Esfriando",IF(U11<='Leia-me'!$B$8,"Última chance","Zumbi")))) | W11: =IF(O11="Won",1,IF(O11="Lost",0,"")) -> 1 | Y11: =IF(E11="","Sim","")
A12: L62MDI48 | B12: Central | C12: Dustin Brinkmann | D12: Anna Snelling | E12: Isdom | F12: medical | G12: 3178.24 | H12: 4540 | I12: United States | K12: 2002 | L12: MG Advanced | M12: MG | N12: 3393 | O12: Lost | P12: 42724 | Q12: 42795 | R12: 0 | S12: =IF(O12="Won",R12,IF(O12="Lost",0,N12)) -> 0 | T12: =IF(AND(P12<>"",Q12<>""),Q12-P12,"") -> 71 | U12: =IF(AND(O12="Engaging",P12<>""),'Leia-me'!$B$5-P12,"") | V12: =IF(O12<>"Engaging","",IF(U12<='Leia-me'!$B$6,"Saudável",IF(U12<='Leia-me'!$B$7,"Esfriando",IF(U12<='Leia-me'!$B$8,"Última chance","Zumbi")))) | W12: =IF(O12="Won",1,IF(O12="Lost",0,"")) -> 0 | Y12: =IF(E12="","Sim","")
A13: 44H0FJMH | B13: Central | C13: Dustin Brinkmann | D13: Anna Snelling | E13: Bioholding | F13: medical | G13: 587.34 | H13: 1356 | I13: Philipines | K13: 2012 | L13: GTX Plus Pro | M13: GTX | N13: 5482 | O13: Lost | P13: 42726 | Q13: 42821 | R13: 0 | S13: =IF(O13="Won",R13,IF(O13="Lost",0,N13)) -> 0 | T13: =IF(AND(P13<>"",Q13<>""),Q13-P13,"") -> 95 | U13: =IF(AND(O13="Engaging",P13<>""),'Leia-me'!$B$5-P13,"") | V13: =IF(O13<>"Engaging","",IF(U13<='Leia-me'!$B$6,"Saudável",IF(U13<='Leia-me'!$B$7,"Esfriando",IF(U13<='Leia-me'!$B$8,"Última chance","Zumbi")))) | W13: =IF(O13="Won",1,IF(O13="Lost",0,"")) -> 0 | Y13: =IF(E13="","Sim","")
A14: MZAN11FT | B14: Central | C14: Dustin Brinkmann | D14: Anna Snelling | E14: Conecom | F14: technolgy | G14: 1520.66 | H14: 1806 | I14: United States | K14: 2005 | L14: GTX Basic | M14: GTX | N14: 550 | O14: Won | P14: 42732 | Q14: 42795 | R14: 625 | S14: =IF(O14="Won",R14,IF(O14="Lost",0,N14)) -> 625 | T14: =IF(AND(P14<>"",Q14<>""),Q14-P14,"") -> 63 | U14: =IF(AND(O14="Engaging",P14<>""),'Leia-me'!$B$5-P14,"") | V14: =IF(O14<>"Engaging","",IF(U14<='Leia-me'!$B$6,"Saudável",IF(U14<='Leia-me'!$B$7,"Esfriando",IF(U14<='Leia-me'!$B$8,"Última chance","Zumbi")))) | W14: =IF(O14="Won",1,IF(O14="Lost",0,"")) -> 1 | Y14: =IF(E14="","Sim","")
A15: G4F8W039 | B15: Central | C15: Dustin Brinkmann | D15: Anna Snelling | E15: Rundofase | F15: technolgy | G15: 1008.06 | H15: 1238 | I15: United States | K15: 1983 | L15: GTX Plus Pro | M15: GTX | N15: 5482 | O15: Won | P15: 42733 | Q15: 42821 | R15: 5459 | S15: =IF(O15="Won",R15,IF(O15="Lost",0,N15)) -> 5459 | T15: =IF(AND(P15<>"",Q15<>""),Q15-P15,"") -> 88 | U15: =IF(AND(O15="Engaging",P15<>""),'Leia-me'!$B$5-P15,"") | V15: =IF(O15<>"Engaging","",IF(U15<='Leia-me'!$B$6,"Saudável",IF(U15<='Leia-me'!$B$7,"Esfriando",IF(U15<='Leia-me'!$B$8,"Última chance","Zumbi")))) | W15: =IF(O15="Won",1,IF(O15="Lost",0,"")) -> 1 | Y15: =IF(E15="","Sim","")
A16: 4T31MWVO | B16: Central | C16: Dustin Brinkmann | D16: Anna Snelling | E16: Stanredtax | F16: finance | G16: 1698.2 | H16: 3798 | I16: United States | K16: 1987 | L16: MG Advanced | M16: MG | N16: 3393 | O16: Won | P16: 42733 | Q16: 42817 | R16: 4148 | S16: =IF(O16="Won",R16,IF(O16="Lost",0,N16)) -> 4148 | T16: =IF(AND(P16<>"",Q16<>""),Q16-P16,"") -> 84 | U16: =IF(AND(O16="Engaging",P16<>""),'Leia-me'!$B$5-P16,"") | V16: =IF(O16<>"Engaging","",IF(U16<='Leia-me'!$B$6,"Saudável",IF(U16<='Leia-me'!$B$7,"Esfriando",IF(U16<='Leia-me'!$B$8,"Última chance","Zumbi")))) | W16: =IF(O16="Won",1,IF(O16="Lost",0,"")) -> 1 | Y16: =IF(E16="","Sim","")
A17: Q7IRUJK7 | B17: Central | C17: Dustin Brinkmann | D17: Anna Snelling | E17: Codehow | F17: software | G17: 2714.9 | H17: 2641 | I17: United States | J17: Acme Corporation | K17: 1998 | L17: GTX Plus Pro | M17: GTX | N17: 5482 | O17: Won | P17: 42736 | Q17: 42795 | R17: 5087 | S17: =IF(O17="Won",R17,IF(O17="Lost",0,N17)) -> 5087 | T17: =IF(AND(P17<>"",Q17<>""),Q17-P17,"") -> 59 | U17: =IF(AND(O17="Engaging",P17<>""),'Leia-me'!$B$5-P17,"") | V17: =IF(O17<>"Engaging","",IF(U17<='Leia-me'!$B$6,"Saudável",IF(U17<='Leia-me'!$B$7,"Esfriando",IF(U17<='Leia-me'!$B$8,"Última chance","Zumbi")))) | W17: =IF(O17="Won",1,IF(O17="Lost",0,"")) -> 1 | Y17: =IF(E17="","Sim","")
A18: PC1NUL8Q | B18: Central | C18: Dustin Brinkmann | D18: Anna Snelling | E18: Hottechi | F18: technolgy | G18: 8170.38 | H18: 16499 | I18: Korea | K18: 1997 | L18: MG Special | M18: MG | N18: 55 | O18: Won | P18: 42737 | Q18: 42796 | R18: 60 | S18: =IF(O18="Won",R18,IF(O18="Lost",0,N18)) -> 60 | T18: =IF(AND(P18<>"",Q18<>""),Q18-P18,"") -> 59 | U18: =IF(AND(O18="Engaging",P18<>""),'Leia-me'!$B$5-P18,"") | V18: =IF(O18<>"Engaging","",IF(U18<='Leia-me'!$B$6,"Saudável",IF(U18<='Leia-me'!$B$7,"Esfriando",IF(U18<='Leia-me'!$B$8,"Última chance","Zumbi")))) | W18: =IF(O18="Won",1,IF(O18="Lost",0,"")) -> 1 | Y18: =IF(E18="","Sim","")
A19: 279625VN | B19: Central | C19: Dustin Brinkmann | D19: Anna Snelling | E19: Funholding | F19: finance | G19: 2819.5 | H19: 7227 | I19: United States | J19: Golddex | K19: 1991 | L19: MG Advanced | M19: MG | N19: 3393 | O19: Lost | P19: 42740 | Q19: 42819 | R19: 0 | S19: =IF(O19="Won",R19,IF(O19="Lost",0,N19)) -> 0 | T19: =IF(AND(P19<>"",Q19<>""),Q19-P19,"") -> 79 | U19: =IF(AND(O19="Engaging",P19<>""),'Leia-me'!$B$5-P19,"") | V19: =IF(O19<>"Engaging","",IF(U19<='Leia-me'!$B$6,"Saudável",IF(U19<='Leia-me'!$B$7,"Esfriando",IF(U19<='Leia-me'!$B$8,"Última chance","Zumbi")))) | W19: =IF(O19="Won",1,IF(O19="Lost",0,"")) -> 0 | Y19: =IF(E19="","Sim","")
A20: VCA1WAB0 | B20: Central | C20: Dustin Brinkmann | D20: Anna Snelling | E20: Funholding | F20: finance | G20: 2819.5 | H20: 7227 | I20: United States | J20: Golddex | K20: 1991 | L20: MG Advanced | M20: MG | N20: 3393 | O20: Lost | P20: 42741 | Q20: 42815 | R20: 0 | S20: =IF(O20="Won",R20,IF(O20="Lost",0,N20)) -> 0 | T20: =IF(AND(P20<>"",Q20<>""),Q20-P20,"") -> 74 | U20: =IF(AND(O20="Engaging",P20<>""),'Leia-me'!$B$5-P20,"") | V20: =IF(O20<>"Engaging","",IF(U20<='Leia-me'!$B$6,"Saudável",IF(U20<='Leia-me'!$B$7,"Esfriando",IF(U20<='Leia-me'!$B$8,"Última chance","Zumbi")))) | W20: =IF(O20="Won",1,IF(O20="Lost",0,"")) -> 0 | Y20: =IF(E20="","Sim","")
A21: BBC3JB3H | B21: Central | C21: Dustin Brinkmann | D21: Anna Snelling | E21: Isdom | F21: medical | G21: 3178.24 | H21: 4540 | I21: United States | K21: 2002 | L21: GTX Basic | M21: GTX | N21: 550 | O21: Won | P21: 42742 | Q21: 42802 | R21: 622 | S21: =IF(O21="Won",R21,IF(O21="Lost",0,N21)) -> 622 | T21: =IF(AND(P21<>"",Q21<>""),Q21-P21,"") -> 60 | U21: =IF(AND(O21="Engaging",P21<>""),'Leia-me'!$B$5-P21,"") | V21: =IF(O21<>"Engaging","",IF(U21<='Leia-me'!$B$6,"Saudável",IF(U21<='Leia-me'!$B$7,"Esfriando",IF(U21<='Leia-me'!$B$8,"Última chance","Zumbi")))) | W21: =IF(O21="Won",1,IF(O21="Lost",0,"")) -> 1 | Y21: =IF(E21="","Sim","")
A22: S24L8LVR | B22: Central | C22: Dustin Brinkmann | D22: Anna Snelling | E22: dambase | F22: marketing | G22: 2173.98 | H22: 2928 | I22: United States | J22: Inity | K22: 1995 | L22: GTX Plus Pro | M22: GTX | N22: 5482 | O22: Won | P22: 42743 | Q22: 42812 | R22: 5210 | S22: =IF(O22="Won",R22,IF(O22="Lost",0,N22)) -> 5210 | T22: =IF(AND(P22<>"",Q22<>""),Q22-P22,"") -> 69 | U22: =IF(AND(O22="Engaging",P22<>""),'Leia-me'!$B$5-P22,"") | V22: =IF(O22<>"Engaging","",IF(U22<='Leia-me'!$B$6,"Saudável",IF(U22<='Leia-me'!$B$7,"Esfriando",IF(U22<='Leia-me'!$B$8,"Última chance","Zumbi")))) | W22: =IF(O22="Won",1,IF(O22="Lost",0,"")) -> 1 | Y22: =IF(E22="","Sim","")
A23: VT5Y73GX | B23: Central | C23: Dustin Brinkmann | D23: Anna Snelling | E23: Betatech | F23: medical | G23: 647.18 | H23: 1185 | I23: Kenya | K23: 1986 | L23: MG Special | M23: MG | N23: 55 | O23: Won | P23: 42744 | Q23: 42809 | R23: 56 | S23: =IF(O23="Won",R23,IF(O23="Lost",0,N23)) -> 56 | T23: =IF(AND(P23<>"",Q23<>""),Q23-P23,"") -> 65 | U23: =IF(AND(O23="Engaging",P23<>""),'Leia-me'!$B$5-P23,"") | V23: =IF(O23<>"Engaging","",IF(U23<='Leia-me'!$B$6,"Saudável",IF(U23<='Leia-me'!$B$7,"Esfriando",IF(U23<='Leia-me'!$B$8,"Última chance","Zumbi")))) | W23: =IF(O23="Won",1,IF(O23="Lost",0,"")) -> 1 | Y23: =IF(E23="","Sim","")
A24: 8O9V7UOZ | B24: Central | C24: Dustin Brinkmann | D24: Anna Snelling | E24: Rundofase | F24: technolgy | G24: 1008.06 | H24: 1238 | I24: United States | K24: 1983 | L24: MG Special | M24: MG | N24: 55 | O24: Won | P24: 42744 | Q24: 42795 | R24: 65 | S24: =IF(O24="Won",R24,IF(O24="Lost",0,N24)) -> 65 | T24: =IF(AND(P24<>"",Q24<>""),Q24-P24,"") -> 51 | U24: =IF(AND(O24="Engaging",P24<>""),'Leia-me'!$B$5-P24,"") | V24: =IF(O24<>"Engaging","",IF(U24<='Leia-me'!$B$6,"Saudável",IF(U24<='Leia-me'!$B$7,"Esfriando",IF(U24<='Leia-me'!$B$8,"Última chance","Zumbi")))) | W24: =IF(O24="Won",1,IF(O24="Lost",0,"")) -> 1 | Y24: =IF(E24="","Sim","")
A25: ZE84UHHB | B25: Central | C25: Dustin Brinkmann | D25: Anna Snelling | E25: Inity | F25: marketing | G25: 2403.58 | H25: 8801 | I25: United States | K25: 1986 | L25: MG Special | M25: MG | N25: 55 | O25: Won | P25: 42745 | Q25: 42820 | R25: 59 | S25: =IF(O25="Won",R25,IF(O25="Lost",0,N25)) -> 59 | T25: =IF(AND(P25<>"",Q25<>""),Q25-P25,"") -> 75 | U25: =IF(AND(O25="Engaging",P25<>""),'Leia-me'!$B$5-P25,"") | V25: =IF(O25<>"Engaging","",IF(U25<='Leia-me'!$B$6,"Saudável",IF(U25<='Leia-me'!$B$7,"Esfriando",IF(U25<='Leia-me'!$B$8,"Última chance","Zumbi")))) | W25: =IF(O25="Won",1,IF(O25="Lost",0,"")) -> 1 | Y25: =IF(E25="","Sim","")
A26: 5AKGNKX1 | B26: Central | C26: Dustin Brinkmann | D26: Anna Snelling | E26: Konmatfix | F26: marketing | G26: 375.43 | H26: 1190 | I26: United States | K26: 1985 | L26: MG Special | M26: MG | N26: 55 | O26: Won | P26: 42748 | Q26: 42810 | R26: 58 | S26: =IF(O26="Won",R26,IF(O26="Lost",0,N26)) -> 58 | T26: =IF(AND(P26<>"",Q26<>""),Q26-P26,"") -> 62 | U26: =IF(AND(O26="Engaging",P26<>""),'Leia-me'!$B$5-P26,"") | V26: =IF(O26<>"Engaging","",IF(U26<='Leia-me'!$B$6,"Saudável",IF(U26<='Leia-me'!$B$7,"Esfriando",IF(U26<='Leia-me'!$B$8,"Última chance","Zumbi")))) | W26: =IF(O26="Won",1,IF(O26="Lost",0,"")) -> 1 | Y26: =IF(E26="","Sim","")
A27: KNLMLTJH | B27: Central | C27: Dustin Brinkmann | D27: Anna Snelling | E27: Treequote | F27: telecommunications | G27: 5266.09 | H27: 8595 | I27: United States | J27: Sonron | K27: 1988 | L27: MG Special | M27: MG | N27: 55 | O27: Won | P27: 42748 | Q27: 42821 | R27: 58 | S27: =IF(O27="Won",R27,IF(O27="Lost",0,N27)) -> 58 | T27: =IF(AND(P27<>"",Q27<>""),Q27-P27,"") -> 73 | U27: =IF(AND(O27="Engaging",P27<>""),'Leia-me'!$B$5-P27,"") | V27: =IF(O27<>"Engaging","",IF(U27<='Leia-me'!$B$6,"Saudável",IF(U27<='Leia-me'!$B$7,"Esfriando",IF(U27<='Leia-me'!$B$8,"Última chance","Zumbi")))) | W27: =IF(O27="Won",1,IF(O27="Lost",0,"")) -> 1 | Y27: =IF(E27="","Sim","")
A28: 1DDW2GQW | B28: Central | C28: Dustin Brinkmann | D28: Anna Snelling | E28: Cancity | F28: retail | G28: 718.62 | H28: 2448 | I28: United States | K28: 2001 | L28: MG Advanced | M28: MG | N28: 3393 | O28: Lost | P28: 42756 | Q28: 42803 | R28: 0 | S28: =IF(O28="Won",R28,IF(O28="Lost",0,N28)) -> 0 | T28: =IF(AND(P28<>"",Q28<>""),Q28-P28,"") -> 47 | U28: =IF(AND(O28="Engaging",P28<>""),'Leia-me'!$B$5-P28,"") | V28: =IF(O28<>"Engaging","",IF(U28<='Leia-me'!$B$6,"Saudável",IF(U28<='Leia-me'!$B$7,"Esfriando",IF(U28<='Leia-me'!$B$8,"Última chance","Zumbi")))) | W28: =IF(O28="Won",1,IF(O28="Lost",0,"")) -> 0 | Y28: =IF(E28="","Sim","")
A29: AAYV8GV4 | B29: Central | C29: Dustin Brinkmann | D29: Anna Snelling | E29: Inity | F29: marketing | G29: 2403.58 | H29: 8801 | I29: United States | K29: 1986 | L29: MG Advanced | M29: MG | N29: 3393 | O29: Lost | P29: 42758 | Q29: 42860 | R29: 0 | S29: =IF(O29="Won",R29,IF(O29="Lost",0,N29)) -> 0 | T29: =IF(AND(P29<>"",Q29<>""),Q29-P29,"") -> 102 | U29: =IF(AND(O29="Engaging",P29<>""),'Leia-me'!$B$5-P29,"") | V29: =IF(O29<>"Engaging","",IF(U29<='Leia-me'!$B$6,"Saudável",IF(U29<='Leia-me'!$B$7,"Esfriando",IF(U29<='Leia-me'!$B$8,"Última chance","Zumbi")))) | W29: =IF(O29="Won",1,IF(O29="Lost",0,"")) -> 0 | Y29: =IF(E29="","Sim","")
A30: S6BG03TB | B30: Central | C30: Dustin Brinkmann | D30: Anna Snelling | E30: Treequote | F30: telecommunications | G30: 5266.09 | H30: 8595 | I30: United States | J30: Sonron | K30: 1988 | L30: GTX Plus Pro | M30: GTX | N30: 5482 | O30: Won | P30: 42762 | Q30: 42863 | R30: 5883 | S30: =IF(O30="Won",R30,IF(O30="Lost",0,N30)) -> 5883 | T30: =IF(AND(P30<>"",Q30<>""),Q30-P30,"") -> 101 | U30: =IF(AND(O30="Engaging",P30<>""),'Leia-me'!$B$5-P30,"") | V30: =IF(O30<>"Engaging","",IF(U30<='Leia-me'!$B$6,"Saudável",IF(U30<='Leia-me'!$B$7,"Esfriando",IF(U30<='Leia-me'!$B$8,"Última chance","Zumbi")))) | W30: =IF(O30="Won",1,IF(O30="Lost",0,"")) -> 1 | Y30: =IF(E30="","Sim","")
A31: 84V18DBW | B31: Central | C31: Dustin Brinkmann | D31: Anna Snelling | E31: Finhigh | F31: finance | G31: 1102.43 | H31: 1759 | I31: United States | K31: 2006 | L31: GTX Plus Basic | M31: GTX | N31: 1096 | O31: Won | P31: 42763 | Q31: 42887 | R31: 1216 | S31: =IF(O31="Won",R31,IF(O31="Lost",0,N31)) -> 1216 | T31: =IF(AND(P31<>"",Q31<>""),Q31-P31,"") -> 124 | U31: =IF(AND(O31="Engaging",P31<>""),'Leia-me'!$B$5-P31,"") | V31: =IF(O31<>"Engaging","",IF(U31<='Leia-me'!$B$6,"Saudável",IF(U31<='Leia-me'!$B$7,"Esfriando",IF(U31<='Leia-me'!$B$8,"Última chance","Zumbi")))) | W31: =IF(O31="Won",1,IF(O31="Lost",0,"")) -> 1 | Y31: =IF(E31="","Sim","")
A32: WFY0S4WW | B32: Central | C32: Dustin Brinkmann | D32: Anna Snelling | E32: Hottechi | F32: technolgy | G32: 8170.38 | H32: 16499 | I32: Korea | K32: 1997 | L32: GTX Plus Basic | M32: GTX | N32: 1096 | O32: Won | P32: 42763 | Q32: 42857 | R32: 1089 | S32: =IF(O32="Won",R32,IF(O32="Lost",0,N32)) -> 1089 | T32: =IF(AND(P32<>"",Q32<>""),Q32-P32,"") -> 94 | U32: =IF(AND(O32="Engaging",P32<>""),'Leia-me'!$B$5-P32,"") | V32: =IF(O32<>"Engaging","",IF(U32<='Leia-me'!$B$6,"Saudável",IF(U32<='Leia-me'!$B$7,"Esfriando",IF(U32<='Leia-me'!$B$8,"Última chance","Zumbi")))) | W32: =IF(O32="Won",1,IF(O32="Lost",0,"")) -> 1 | Y32: =IF(E32="","Sim","")
A33: QY6HCHDH | B33: Central | C33: Dustin Brinkmann | D33: Anna Snelling | E33: Condax | F33: medical | G33: 4.54 | H33: 9 | I33: United States | K33: 2017 | L33: MG Special | M33: MG | N33: 55 | O33: Won | P33: 42764 | Q33: 42880 | R33: 52 | S33: =IF(O33="Won",R33,IF(O33="Lost",0,N33)) -> 52 | T33: =IF(AND(P33<>"",Q33<>""),Q33-P33,"") -> 116 | U33: =IF(AND(O33="Engaging",P33<>""),'Leia-me'!$B$5-P33,"") | V33: =IF(O33<>"Engaging","",IF(U33<='Leia-me'!$B$6,"Saudável",IF(U33<='Leia-me'!$B$7,"Esfriando",IF(U33<='Leia-me'!$B$8,"Última chance","Zumbi")))) | W33: =IF(O33="Won",1,IF(O33="Lost",0,"")) -> 1 | Y33: =IF(E33="","Sim","")
A34: UK2JIE61 | B34: Central | C34: Dustin Brinkmann | D34: Anna Snelling | E34: Cancity | F34: retail | G34: 718.62 | H34: 2448 | I34: United States | K34: 2001 | L34: MG Special | M34: MG | N34: 55 | O34: Won | P34: 42771 | Q34: 42859 | R34: 55 | S34: =IF(O34="Won",R34,IF(O34="Lost",0,N34)) -> 55 | T34: =IF(AND(P34<>"",Q34<>""),Q34-P34,"") -> 88 | U34: =IF(AND(O34="Engaging",P34<>""),'Leia-me'!$B$5-P34,"") | V34: =IF(O34<>"Engaging","",IF(U34<='Leia-me'!$B$6,"Saudável",IF(U34<='Leia-me'!$B$7,"Esfriando",IF(U34<='Leia-me'!$B$8,"Última chance","Zumbi")))) | W34: =IF(O34="Won",1,IF(O34="Lost",0,"")) -> 1 | Y34: =IF(E34="","Sim","")
A35: L47EPGVT | B35: Central | C35: Dustin Brinkmann | D35: Anna Snelling | E35: Gogozoom | F35: telecommunications | G35: 86.68 | H35: 187 | I35: United States | J35: Sonron | K35: 2007 | L35: GTX Plus Pro | M35: GTX | N35: 5482 | O35: Won | P35: 42775 | Q35: 42795 | R35: 4760 | S35: =IF(O35="Won",R35,IF(O35="Lost",0,N35)) -> 4760 | T35: =IF(AND(P35<>"",Q35<>""),Q35-P35,"") -> 20 | U35: =IF(AND(O35="Engaging",P35<>""),'Leia-me'!$B$5-P35,"") | V35: =IF(O35<>"Engaging","",IF(U35<='Leia-me'!$B$6,"Saudável",IF(U35<='Leia-me'!$B$7,"Esfriando",IF(U35<='Leia-me'!$B$8,"Última chance","Zumbi")))) | W35: =IF(O35="Won",1,IF(O35="Lost",0,"")) -> 1 | Y35: =IF(E35="","Sim","")
A36: P1KS5YFX | B36: Central | C36: Dustin Brinkmann | D36: Anna Snelling | E36: Rundofase | F36: technolgy | G36: 1008.06 | H36: 1238 | I36: United States | K36: 1983 | L36: MG Special | M36: MG | N36: 55 | O36: Won | P36: 42778 | Q36: 42893 | R36: 59 | S36: =IF(O36="Won",R36,IF(O36="Lost",0,N36)) -> 59 | T36: =IF(AND(P36<>"",Q36<>""),Q36-P36,"") -> 115 | U36: =IF(AND(O36="Engaging",P36<>""),'Leia-me'!$B$5-P36,"") | V36: =IF(O36<>"Engaging","",IF(U36<='Leia-me'!$B$6,"Saudável",IF(U36<='Leia-me'!$B$7,"Esfriando",IF(U36<='Leia-me'!$B$8,"Última chance","Zumbi")))) | W36: =IF(O36="Won",1,IF(O36="Lost",0,"")) -> 1 | Y36: =IF(E36="","Sim","")
A37: L5T2HKKO | B37: Central | C37: Dustin Brinkmann | D37: Anna Snelling | E37: Conecom | F37: technolgy | G37: 1520.66 | H37: 1806 | I37: United States | K37: 2005 | L37: GTX Basic | M37: GTX | N37: 550 | O37: Lost | P37: 42780 | Q37: 42860 | R37: 0 | S37: =IF(O37="Won",R37,IF(O37="Lost",0,N37)) -> 0 | T37: =IF(AND(P37<>"",Q37<>""),Q37-P37,"") -> 80 | U37: =IF(AND(O37="Engaging",P37<>""),'Leia-me'!$B$5-P37,"") | V37: =IF(O37<>"Engaging","",IF(U37<='Leia-me'!$B$6,"Saudável",IF(U37<='Leia-me'!$B$7,"Esfriando",IF(U37<='Leia-me'!$B$8,"Última chance","Zumbi")))) | W37: =IF(O37="Won",1,IF(O37="Lost",0,"")) -> 0 | Y37: =IF(E37="","Sim","")
A38: 6CEEGQ8I | B38: Central | C38: Dustin Brinkmann | D38: Anna Snelling | E38: Domzoom | F38: entertainment | G38: 217.87 | H38: 551 | I38: United States | K38: 1998 | L38: MG Special | M38: MG | N38: 55 | O38: Won | P38: 42780 | Q38: 42885 | R38: 63 | S38: =IF(O38="Won",R38,IF(O38="Lost",0,N38)) -> 63 | T38: =IF(AND(P38<>"",Q38<>""),Q38-P38,"") -> 105 | U38: =IF(AND(O38="Engaging",P38<>""),'Leia-me'!$B$5-P38,"") | V38: =IF(O38<>"Engaging","",IF(U38<='Leia-me'!$B$6,"Saudável",IF(U38<='Leia-me'!$B$7,"Esfriando",IF(U38<='Leia-me'!$B$8,"Última chance","Zumbi")))) | W38: =IF(O38="Won",1,IF(O38="Lost",0,"")) -> 1 | Y38: =IF(E38="","Sim","")
A39: N6H58J55 | B39: Central | C39: Dustin Brinkmann | D39: Anna Snelling | E39: Streethex | F39: retail | G39: 1376.8 | H39: 1165 | I39: Belgium | K39: 1988 | L39: GTX Basic | M39: GTX | N39: 550 | O39: Lost | P39: 42781 | Q39: 42868 | R39: 0 | S39: =IF(O39="Won",R39,IF(O39="Lost",0,N39)) -> 0 | T39: =IF(AND(P39<>"",Q39<>""),Q39-P39,"") -> 87 | U39: =IF(AND(O39="Engaging",P39<>""),'Leia-me'!$B$5-P39,"") | V39: =IF(O39<>"Engaging","",IF(U39<='Leia-me'!$B$6,"Saudável",IF(U39<='Leia-me'!$B$7,"Esfriando",IF(U39<='Leia-me'!$B$8,"Última chance","Zumbi")))) | W39: =IF(O39="Won",1,IF(O39="Lost",0,"")) -> 0 | Y39: =IF(E39="","Sim","")
A40: HTD2ME9C | B40: Central | C40: Dustin Brinkmann | D40: Anna Snelling | E40: Betatech | F40: medical | G40: 647.18 | H40: 1185 | I40: Kenya | K40: 1986 | L40: GTX Plus Pro | M40: GTX | N40: 5482 | O40: Won | P40: 42785 | Q40: 42898 | R40: 5370 | S40: =IF(O40="Won",R40,IF(O40="Lost",0,N40)) -> 5370 | T40: =IF(AND(P40<>"",Q40<>""),Q40-P40,"") -> 113 | U40: =IF(AND(O40="Engaging",P40<>""),'Leia-me'!$B$5-P40,"") | V40: =IF(O40<>"Engaging","",IF(U40<='Leia-me'!$B$6,"Saudável",IF(U40<='Leia-me'!$B$7,"Esfriando",IF(U40<='Leia-me'!$B$8,"Última chance","Zumbi")))) | W40: =IF(O40="Won",1,IF(O40="Lost",0,"")) -> 1 | Y40: =IF(E40="","Sim","")
A41: 5ITSLO0E | B41: Central | C41: Dustin Brinkmann | D41: Anna Snelling | E41: Treequote | F41: telecommunications | G41: 5266.09 | H41: 8595 | I41: United States | J41: Sonron | K41: 1988 | L41: GTX Plus Basic | M41: GTX | N41: 1096 | O41: Won | P41: 42787 | Q41: 42798 | R41: 999 | S41: =IF(O41="Won",R41,IF(O41="Lost",0,N41)) -> 999 | T41: =IF(AND(P41<>"",Q41<>""),Q41-P41,"") -> 11 | U41: =IF(AND(O41="Engaging",P41<>""),'Leia-me'!$B$5-P41,"") | V41: =IF(O41<>"Engaging","",IF(U41<='Leia-me'!$B$6,"Saudável",IF(U41<='Leia-me'!$B$7,"Esfriando",IF(U41<='Leia-me'!$B$8,"Última chance","Zumbi")))) | W41: =IF(O41="Won",1,IF(O41="Lost",0,"")) -> 1 | Y41: =IF(E41="","Sim","")
A42: P5EVJUKQ | B42: Central | C42: Dustin Brinkmann | D42: Anna Snelling | E42: Conecom | F42: technolgy | G42: 1520.66 | H42: 1806 | I42: United States | K42: 2005 | L42: GTX Plus Basic | M42: GTX | N42: 1096 | O42: Won | P42: 42789 | Q42: 42896 | R42: 1056 | S42: =IF(O42="Won",R42,IF(O42="Lost",0,N42)) -> 1056 | T42: =IF(AND(P42<>"",Q42<>""),Q42-P42,"") -> 107 | U42: =IF(AND(O42="Engaging",P42<>""),'Leia-me'!$B$5-P42,"") | V42: =IF(O42<>"Engaging","",IF(U42<='Leia-me'!$B$6,"Saudável",IF(U42<='Leia-me'!$B$7,"Esfriando",IF(U42<='Leia-me'!$B$8,"Última chance","Zumbi")))) | W42: =IF(O42="Won",1,IF(O42="Lost",0,"")) -> 1 | Y42: =IF(E42="","Sim","")
A43: U6N053E1 | B43: Central | C43: Dustin Brinkmann | D43: Anna Snelling | E43: Scottech | F43: marketing | G43: 45.39 | H43: 100 | I43: United States | J43: Inity | K43: 2012 | L43: GTX Basic | M43: GTX | N43: 550 | O43: Won | P43: 42791 | Q43: 42796 | R43: 423 | S43: =IF(O43="Won",R43,IF(O43="Lost",0,N43)) -> 423 | T43: =IF(AND(P43<>"",Q43<>""),Q43-P43,"") -> 5 | U43: =IF(AND(O43="Engaging",P43<>""),'Leia-me'!$B$5-P43,"") | V43: =IF(O43<>"Engaging","",IF(U43<='Leia-me'!$B$6,"Saudável",IF(U43<='Leia-me'!$B$7,"Esfriando",IF(U43<='Leia-me'!$B$8,"Última chance","Zumbi")))) | W43: =IF(O43="Won",1,IF(O43="Lost",0,"")) -> 1 | Y43: =IF(E43="","Sim","")
A44: 8DWOWB6Y | B44: Central | C44: Dustin Brinkmann | D44: Anna Snelling | E44: Betatech | F44: medical | G44: 647.18 | H44: 1185 | I44: Kenya | K44: 1986 | L44: GTX Basic | M44: GTX | N44: 550 | O44: Lost | P44: 42792 | Q44: 42810 | R44: 0 | S44: =IF(O44="Won",R44,IF(O44="Lost",0,N44)) -> 0 | T44: =IF(AND(P44<>"",Q44<>""),Q44-P44,"") -> 18 | U44: =IF(AND(O44="Engaging",P44<>""),'Leia-me'!$B$5-P44,"") | V44: =IF(O44<>"Engaging","",IF(U44<='Leia-me'!$B$6,"Saudável",IF(U44<='Leia-me'!$B$7,"Esfriando",IF(U44<='Leia-me'!$B$8,"Última chance","Zumbi")))) | W44: =IF(O44="Won",1,IF(O44="Lost",0,"")) -> 0 | Y44: =IF(E44="","Sim","")
A45: KR4K652E | B45: Central | C45: Dustin Brinkmann | D45: Anna Snelling | E45: dambase | F45: marketing | G45: 2173.98 | H45: 2928 | I45: United States | J45: Inity | K45: 1995 | L45: GTX Basic | M45: GTX | N45: 550 | O45: Won | P45: 42793 | Q45: 42890 | R45: 574 | S45: =IF(O45="Won",R45,IF(O45="Lost",0,N45)) -> 574 | T45: =IF(AND(P45<>"",Q45<>""),Q45-P45,"") -> 97 | U45: =IF(AND(O45="Engaging",P45<>""),'Leia-me'!$B$5-P45,"") | V45: =IF(O45<>"Engaging","",IF(U45<='Leia-me'!$B$6,"Saudável",IF(U45<='Leia-me'!$B$7,"Esfriando",IF(U45<='Leia-me'!$B$8,"Última chance","Zumbi")))) | W45: =IF(O45="Won",1,IF(O45="Lost",0,"")) -> 1 | Y45: =IF(E45="","Sim","")
A46: G0QKNVIJ | B46: Central | C46: Dustin Brinkmann | D46: Anna Snelling | E46: Conecom | F46: technolgy | G46: 1520.66 | H46: 1806 | I46: United States | K46: 2005 | L46: MG Special | M46: MG | N46: 55 | O46: Won | P46: 42795 | Q46: 42883 | R46: 51 | S46: =IF(O46="Won",R46,IF(O46="Lost",0,N46)) -> 51 | T46: =IF(AND(P46<>"",Q46<>""),Q46-P46,"") -> 88 | U46: =IF(AND(O46="Engaging",P46<>""),'Leia-me'!$B$5-P46,"") | V46: =IF(O46<>"Engaging","",IF(U46<='Leia-me'!$B$6,"Saudável",IF(U46<='Leia-me'!$B$7,"Esfriando",IF(U46<='Leia-me'!$B$8,"Última chance","Zumbi")))) | W46: =IF(O46="Won",1,IF(O46="Lost",0,"")) -> 1 | Y46: =IF(E46="","Sim","")
A47: 6HRIX06M | B47: Central | C47: Dustin Brinkmann | D47: Anna Snelling | E47: Hottechi | F47: technolgy | G47: 8170.38 | H47: 16499 | I47: Korea | K47: 1997 | L47: MG Advanced | M47: MG | N47: 3393 | O47: Won | P47: 42795 | Q47: 42912 | R47: 3415 | S47: =IF(O47="Won",R47,IF(O47="Lost",0,N47)) -> 3415 | T47: =IF(AND(P47<>"",Q47<>""),Q47-P47,"") -> 117 | U47: =IF(AND(O47="Engaging",P47<>""),'Leia-me'!$B$5-P47,"") | V47: =IF(O47<>"Engaging","",IF(U47<='Leia-me'!$B$6,"Saudável",IF(U47<='Leia-me'!$B$7,"Esfriando",IF(U47<='Leia-me'!$B$8,"Última chance","Zumbi")))) | W47: =IF(O47="Won",1,IF(O47="Lost",0,"")) -> 1 | Y47: =IF(E47="","Sim","")
A48: G7RCJBVL | B48: Central | C48: Dustin Brinkmann | D48: Anna Snelling | E48: Dontechi | F48: software | G48: 4618 | H48: 10083 | I48: United States | K48: 1982 | L48: MG Advanced | M48: MG | N48: 3393 | O48: Lost | P48: 42796 | Q48: 42886 | R48: 0 | S48: =IF(O48="Won",R48,IF(O48="Lost",0,N48)) -> 0 | T48: =IF(AND(P48<>"",Q48<>""),Q48-P48,"") -> 90 | U48: =IF(AND(O48="Engaging",P48<>""),'Leia-me'!$B$5-P48,"") | V48: =IF(O48<>"Engaging","",IF(U48<='Leia-me'!$B$6,"Saudável",IF(U48<='Leia-me'!$B$7,"Esfriando",IF(U48<='Leia-me'!$B$8,"Última chance","Zumbi")))) | W48: =IF(O48="Won",1,IF(O48="Lost",0,"")) -> 0 | Y48: =IF(E48="","Sim","")
A49: G20IQSA3 | B49: Central | C49: Dustin Brinkmann | D49: Anna Snelling | E49: Conecom | F49: technolgy | G49: 1520.66 | H49: 1806 | I49: United States | K49: 2005 | L49: GTX Basic | M49: GTX | N49: 550 | O49: Won | P49: 42796 | Q49: 42806 | R49: 522 | S49: =IF(O49="Won",R49,IF(O49="Lost",0,N49)) -> 522 | T49: =IF(AND(P49<>"",Q49<>""),Q49-P49,"") -> 10 | U49: =IF(AND(O49="Engaging",P49<>""),'Leia-me'!$B$5-P49,"") | V49: =IF(O49<>"Engaging","",IF(U49<='Leia-me'!$B$6,"Saudável",IF(U49<='Leia-me'!$B$7,"Esfriando",IF(U49<='Leia-me'!$B$8,"Última chance","Zumbi")))) | W49: =IF(O49="Won",1,IF(O49="Lost",0,"")) -> 1 | Y49: =IF(E49="","Sim","")
A50: Q1ZKBGV5 | B50: Central | C50: Dustin Brinkmann | D50: Anna Snelling | E50: Globex Corporation | F50: technolgy | G50: 1223.72 | H50: 2497 | I50: Norway | K50: 2000 | L50: MG Special | M50: MG | N50: 55 | O50: Won | P50: 42797 | Q50: 42878 | R50: 46 | S50: =IF(O50="Won",R50,IF(O50="Lost",0,N50)) -> 46 | T50: =IF(AND(P50<>"",Q50<>""),Q50-P50,"") -> 81 | U50: =IF(AND(O50="Engaging",P50<>""),'Leia-me'!$B$5-P50,"") | V50: =IF(O50<>"Engaging","",IF(U50<='Leia-me'!$B$6,"Saudável",IF(U50<='Leia-me'!$B$7,"Esfriando",IF(U50<='Leia-me'!$B$8,"Última chance","Zumbi")))) | W50: =IF(O50="Won",1,IF(O50="Lost",0,"")) -> 1 | Y50: =IF(E50="","Sim","")
A51: 9JKODCAU | B51: Central | C51: Dustin Brinkmann | D51: Anna Snelling | E51: Rundofase | F51: technolgy | G51: 1008.06 | H51: 1238 | I51: United States | K51: 1983 | L51: MG Special | M51: MG | N51: 55 | O51: Won | P51: 42797 | Q51: 42908 | R51: 54 | S51: =IF(O51="Won",R51,IF(O51="Lost",0,N51)) -> 54 | T51: =IF(AND(P51<>"",Q51<>""),Q51-P51,"") -> 111 | U51: =IF(AND(O51="Engaging",P51<>""),'Leia-me'!$B$5-P51,"") | V51: =IF(O51<>"Engaging","",IF(U51<='Leia-me'!$B$6,"Saudável",IF(U51<='Leia-me'!$B$7,"Esfriando",IF(U51<='Leia-me'!$B$8,"Última chance","Zumbi")))) | W51: =IF(O51="Won",1,IF(O51="Lost",0,"")) -> 1 | Y51: =IF(E51="","Sim","")
A52: JSDGELLK | B52: Central | C52: Dustin Brinkmann | D52: Anna Snelling | E52: Codehow | F52: software | G52: 2714.9 | H52: 2641 | I52: United States | J52: Acme Corporation | K52: 1998 | L52: GTX Basic | M52: GTX | N52: 550 | O52: Won | P52: 42798 | Q52: 42899 | R52: 522 | S52: =IF(O52="Won",R52,IF(O52="Lost",0,N52)) -> 522 | T52: =IF(AND(P52<>"",Q52<>""),Q52-P52,"") -> 101 | U52: =IF(AND(O52="Engaging",P52<>""),'Leia-me'!$B$5-P52,"") | V52: =IF(O52<>"Engaging","",IF(U52<='Leia-me'!$B$6,"Saudável",IF(U52<='Leia-me'!$B$7,"Esfriando",IF(U52<='Leia-me'!$B$8,"Última chance","Zumbi")))) | W52: =IF(O52="Won",1,IF(O52="Lost",0,"")) -> 1 | Y52: =IF(E52="","Sim","")
A53: LV1754PS | B53: Central | C53: Dustin Brinkmann | D53: Anna Snelling | E53: Rangreen | F53: technolgy | G53: 2938.67 | H53: 8775 | I53: Panama | K53: 1987 | L53: GTX Basic | M53: GTX | N53: 550 | O53: Won | P53: 42798 | Q53: 42869 | R53: 544 | S53: =IF(O53="Won",R53,IF(O53="Lost",0,N53)) -> 544 | T53: =IF(AND(P53<>"",Q53<>""),Q53-P53,"") -> 71 | U53: =IF(AND(O53="Engaging",P53<>""),'Leia-me'!$B$5-P53,"") | V53: =IF(O53<>"Engaging","",IF(U53<='Leia-me'!$B$6,"Saudável",IF(U53<='Leia-me'!$B$7,"Esfriando",IF(U53<='Leia-me'!$B$8,"Última chance","Zumbi")))) | W53: =IF(O53="Won",1,IF(O53="Lost",0,"")) -> 1 | Y53: =IF(E53="","Sim","")
A54: JIYYV11P | B54: Central | C54: Dustin Brinkmann | D54: Anna Snelling | E54: Genco Pura Olive Oil Company | F54: retail | G54: 894.33 | H54: 1635 | I54: Italy | K54: 2007 | L54: MG Advanced | M54: MG | N54: 3393 | O54: Won | P54: 42798 | Q54: 42893 | R54: 3081 | S54: =IF(O54="Won",R54,IF(O54="Lost",0,N54)) -> 3081 | T54: =IF(AND(P54<>"",Q54<>""),Q54-P54,"") -> 95 | U54: =IF(AND(O54="Engaging",P54<>""),'Leia-me'!$B$5-P54,"") | V54: =IF(O54<>"Engaging","",IF(U54<='Leia-me'!$B$6,"Saudável",IF(U54<='Leia-me'!$B$7,"Esfriando",IF(U54<='Leia-me'!$B$8,"Última chance","Zumbi")))) | W54: =IF(O54="Won",1,IF(O54="Lost",0,"")) -> 1 | Y54: =IF(E54="","Sim","")
A55: SAUAOZVO | B55: Central | C55: Dustin Brinkmann | D55: Anna Snelling | E55: Toughzap | F55: retail | G55: 332.43 | H55: 799 | I55: United States | K55: 1995 | L55: GTX Plus Pro | M55: GTX | N55: 5482 | O55: Won | P55: 42799 | Q55: 42884 | R55: 5092 | S55: =IF(O55="Won",R55,IF(O55="Lost",0,N55)) -> 5092 | T55: =IF(AND(P55<>"",Q55<>""),Q55-P55,"") -> 85 | U55: =IF(AND(O55="Engaging",P55<>""),'Leia-me'!$B$5-P55,"") | V55: =IF(O55<>"Engaging","",IF(U55<='Leia-me'!$B$6,"Saudável",IF(U55<='Leia-me'!$B$7,"Esfriando",IF(U55<='Leia-me'!$B$8,"Última chance","Zumbi")))) | W55: =IF(O55="Won",1,IF(O55="Lost",0,"")) -> 1 | Y55: =IF(E55="","Sim","")
A56: WFJPWN9O | B56: Central | C56: Dustin Brinkmann | D56: Anna Snelling | E56: Globex Corporation | F56: technolgy | G56: 1223.72 | H56: 2497 | I56: Norway | K56: 2000 | L56: GTX Plus Pro | M56: GTX | N56: 5482 | O56: Won | P56: 42801 | Q56: 42897 | R56: 6023 | S56: =IF(O56="Won",R56,IF(O56="Lost",0,N56)) -> 6023 | T56: =IF(AND(P56<>"",Q56<>""),Q56-P56,"") -> 96 | U56: =IF(AND(O56="Engaging",P56<>""),'Leia-me'!$B$5-P56,"") | V56: =IF(O56<>"Engaging","",IF(U56<='Leia-me'!$B$6,"Saudável",IF(U56<='Leia-me'!$B$7,"Esfriando",IF(U56<='Leia-me'!$B$8,"Última chance","Zumbi")))) | W56: =IF(O56="Won",1,IF(O56="Lost",0,"")) -> 1 | Y56: =IF(E56="","Sim","")
A57: COOYICXU | B57: Central | C57: Dustin Brinkmann | D57: Anna Snelling | E57: Inity | F57: marketing | G57: 2403.58 | H57: 8801 | I57: United States | K57: 1986 | L57: GTX Basic | M57: GTX | N57: 550 | O57: Lost | P57: 42803 | Q57: 42877 | R57: 0 | S57: =IF(O57="Won",R57,IF(O57="Lost",0,N57)) -> 0 | T57: =IF(AND(P57<>"",Q57<>""),Q57-P57,"") -> 74 | U57: =IF(AND(O57="Engaging",P57<>""),'Leia-me'!$B$5-P57,"") | V57: =IF(O57<>"Engaging","",IF(U57<='Leia-me'!$B$6,"Saudável",IF(U57<='Leia-me'!$B$7,"Esfriando",IF(U57<='Leia-me'!$B$8,"Última chance","Zumbi")))) | W57: =IF(O57="Won",1,IF(O57="Lost",0,"")) -> 0 | Y57: =IF(E57="","Sim","")
A58: UALNIVAY | B58: Central | C58: Dustin Brinkmann | D58: Anna Snelling | E58: Hottechi | F58: technolgy | G58: 8170.38 | H58: 16499 | I58: Korea | K58: 1997 | L58: GTX Plus Pro | M58: GTX | N58: 5482 | O58: Lost | P58: 42803 | Q58: 42866 | R58: 0 | S58: =IF(O58="Won",R58,IF(O58="Lost",0,N58)) -> 0 | T58: =IF(AND(P58<>"",Q58<>""),Q58-P58,"") -> 63 | U58: =IF(AND(O58="Engaging",P58<>""),'Leia-me'!$B$5-P58,"") | V58: =IF(O58<>"Engaging","",IF(U58<='Leia-me'!$B$6,"Saudável",IF(U58<='Leia-me'!$B$7,"Esfriando",IF(U58<='Leia-me'!$B$8,"Última chance","Zumbi")))) | W58: =IF(O58="Won",1,IF(O58="Lost",0,"")) -> 0 | Y58: =IF(E58="","Sim","")
A59: E5UW8AGQ | B59: Central | C59: Dustin Brinkmann | D59: Anna Snelling | E59: Streethex | F59: retail | G59: 1376.8 | H59: 1165 | I59: Belgium | K59: 1988 | L59: GTX Basic | M59: GTX | N59: 550 | O59: Won | P59: 42803 | Q59: 42897 | R59: 595 | S59: =IF(O59="Won",R59,IF(O59="Lost",0,N59)) -> 595 | T59: =IF(AND(P59<>"",Q59<>""),Q59-P59,"") -> 94 | U59: =IF(AND(O59="Engaging",P59<>""),'Leia-me'!$B$5-P59,"") | V59: =IF(O59<>"Engaging","",IF(U59<='Leia-me'!$B$6,"Saudável",IF(U59<='Leia-me'!$B$7,"Esfriando",IF(U59<='Leia-me'!$B$8,"Última chance","Zumbi")))) | W59: =IF(O59="Won",1,IF(O59="Lost",0,"")) -> 1 | Y59: =IF(E59="","Sim","")
A60: EWA9JFBA | B60: Central | C60: Dustin Brinkmann | D60: Anna Snelling | E60: Zumgoity | F60: medical | G60: 441.08 | H60: 1210 | I60: United States | K60: 1984 | L60: MG Special | M60: MG | N60: 55 | O60: Won | P60: 42803 | Q60: 42887 | R60: 51 | S60: =IF(O60="Won",R60,IF(O60="Lost",0,N60)) -> 51 | T60: =IF(AND(P60<>"",Q60<>""),Q60-P60,"") -> 84 | U60: =IF(AND(O60="Engaging",P60<>""),'Leia-me'!$B$5-P60,"") | V60: =IF(O60<>"Engaging","",IF(U60<='Leia-me'!$B$6,"Saudável",IF(U60<='Leia-me'!$B$7,"Esfriando",IF(U60<='Leia-me'!$B$8,"Última chance","Zumbi")))) | W60: =IF(O60="Won",1,IF(O60="Lost",0,"")) -> 1 | Y60: =IF(E60="","Sim","")
A61: RCQ32MXL | B61: Central | C61: Dustin Brinkmann | D61: Anna Snelling | E61: Streethex | F61: retail | G61: 1376.8 | H61: 1165 | I61: Belgium | K61: 1988 | L61: GTX Plus Basic | M61: GTX | N61: 1096 | O61: Lost | P61: 42804 | Q61: 42867 | R61: 0 | S61: =IF(O61="Won",R61,IF(O61="Lost",0,N61)) -> 0 | T61: =IF(AND(P61<>"",Q61<>""),Q61-P61,"") -> 63 | U61: =IF(AND(O61="Engaging",P61<>""),'Leia-me'!$B$5-P61,"") | V61: =IF(O61<>"Engaging","",IF(U61<='Leia-me'!$B$6,"Saudável",IF(U61<='Leia-me'!$B$7,"Esfriando",IF(U61<='Leia-me'!$B$8,"Última chance","Zumbi")))) | W61: =IF(O61="Won",1,IF(O61="Lost",0,"")) -> 0 | Y61: =IF(E61="","Sim","")
A62: 396WP6JS | B62: Central | C62: Dustin Brinkmann | D62: Anna Snelling | E62: Gogozoom | F62: telecommunications | G62: 86.68 | H62: 187 | I62: United States | J62: Sonron | K62: 2007 | L62: MG Special | M62: MG | N62: 55 | O62: Won | P62: 42804 | Q62: 42813 | R62: 58 | S62: =IF(O62="Won",R62,IF(O62="Lost",0,N62)) -> 58 | T62: =IF(AND(P62<>"",Q62<>""),Q62-P62,"") -> 9 | U62: =IF(AND(O62="Engaging",P62<>""),'Leia-me'!$B$5-P62,"") | V62: =IF(O62<>"Engaging","",IF(U62<='Leia-me'!$B$6,"Saudável",IF(U62<='Leia-me'!$B$7,"Esfriando",IF(U62<='Leia-me'!$B$8,"Última chance","Zumbi")))) | W62: =IF(O62="Won",1,IF(O62="Lost",0,"")) -> 1 | Y62: =IF(E62="","Sim","")
A63: 6XHE52MV | B63: Central | C63: Dustin Brinkmann | D63: Anna Snelling | E63: Inity | F63: marketing | G63: 2403.58 | H63: 8801 | I63: United States | K63: 1986 | L63: MG Special | M63: MG | N63: 55 | O63: Lost | P63: 42805 | Q63: 42885 | R63: 0 | S63: =IF(O63="Won",R63,IF(O63="Lost",0,N63)) -> 0 | T63: =IF(AND(P63<>"",Q63<>""),Q63-P63,"") -> 80 | U63: =IF(AND(O63="Engaging",P63<>""),'Leia-me'!$B$5-P63,"") | V63: =IF(O63<>"Engaging","",IF(U63<='Leia-me'!$B$6,"Saudável",IF(U63<='Leia-me'!$B$7,"Esfriando",IF(U63<='Leia-me'!$B$8,"Última chance","Zumbi")))) | W63: =IF(O63="Won",1,IF(O63="Lost",0,"")) -> 0 | Y63: =IF(E63="","Sim","")
A64: 0YN6EALP | B64: Central | C64: Dustin Brinkmann | D64: Anna Snelling | E64: Scottech | F64: marketing | G64: 45.39 | H64: 100 | I64: United States | J64: Inity | K64: 2012 | L64: MG Special | M64: MG | N64: 55 | O64: Won | P64: 42805 | Q64: 42811 | R64: 57 | S64: =IF(O64="Won",R64,IF(O64="Lost",0,N64)) -> 57 | T64: =IF(AND(P64<>"",Q64<>""),Q64-P64,"") -> 6 | U64: =IF(AND(O64="Engaging",P64<>""),'Leia-me'!$B$5-P64,"") | V64: =IF(O64<>"Engaging","",IF(U64<='Leia-me'!$B$6,"Saudável",IF(U64<='Leia-me'!$B$7,"Esfriando",IF(U64<='Leia-me'!$B$8,"Última chance","Zumbi")))) | W64: =IF(O64="Won",1,IF(O64="Lost",0,"")) -> 1 | Y64: =IF(E64="","Sim","")
A65: NH0WGTR4 | B65: Central | C65: Dustin Brinkmann | D65: Anna Snelling | E65: Funholding | F65: finance | G65: 2819.5 | H65: 7227 | I65: United States | J65: Golddex | K65: 1991 | L65: MG Special | M65: MG | N65: 55 | O65: Lost | P65: 42806 | Q65: 42880 | R65: 0 | S65: =IF(O65="Won",R65,IF(O65="Lost",0,N65)) -> 0 | T65: =IF(AND(P65<>"",Q65<>""),Q65-P65,"") -> 74 | U65: =IF(AND(O65="Engaging",P65<>""),'Leia-me'!$B$5-P65,"") | V65: =IF(O65<>"Engaging","",IF(U65<='Leia-me'!$B$6,"Saudável",IF(U65<='Leia-me'!$B$7,"Esfriando",IF(U65<='Leia-me'!$B$8,"Última chance","Zumbi")))) | W65: =IF(O65="Won",1,IF(O65="Lost",0,"")) -> 0 | Y65: =IF(E65="","Sim","")
A66: HEG8WPQF | B66: Central | C66: Dustin Brinkmann | D66: Anna Snelling | E66: Inity | F66: marketing | G66: 2403.58 | H66: 8801 | I66: United States | K66: 1986 | L66: GTX Plus Basic | M66: GTX | N66: 1096 | O66: Won | P66: 42807 | Q66: 42864 | R66: 1140 | S66: =IF(O66="Won",R66,IF(O66="Lost",0,N66)) -> 1140 | T66: =IF(AND(P66<>"",Q66<>""),Q66-P66,"") -> 57 | U66: =IF(AND(O66="Engaging",P66<>""),'Leia-me'!$B$5-P66,"") | V66: =IF(O66<>"Engaging","",IF(U66<='Leia-me'!$B$6,"Saudável",IF(U66<='Leia-me'!$B$7,"Esfriando",IF(U66<='Leia-me'!$B$8,"Última chance","Zumbi")))) | W66: =IF(O66="Won",1,IF(O66="Lost",0,"")) -> 1 | Y66: =IF(E66="","Sim","")
A67: 0FST40LV | B67: Central | C67: Dustin Brinkmann | D67: Anna Snelling | E67: Streethex | F67: retail | G67: 1376.8 | H67: 1165 | I67: Belgium | K67: 1988 | L67: MG Special | M67: MG | N67: 55 | O67: Won | P67: 42807 | Q67: 42880 | R67: 52 | S67: =IF(O67="Won",R67,IF(O67="Lost",0,N67)) -> 52 | T67: =IF(AND(P67<>"",Q67<>""),Q67-P67,"") -> 73 | U67: =IF(AND(O67="Engaging",P67<>""),'Leia-me'!$B$5-P67,"") | V67: =IF(O67<>"Engaging","",IF(U67<='Leia-me'!$B$6,"Saudável",IF(U67<='Leia-me'!$B$7,"Esfriando",IF(U67<='Leia-me'!$B$8,"Última chance","Zumbi")))) | W67: =IF(O67="Won",1,IF(O67="Lost",0,"")) -> 1 | Y67: =IF(E67="","Sim","")
A68: I7WERQ6B | B68: Central | C68: Dustin Brinkmann | D68: Anna Snelling | E68: Warephase | F68: services | G68: 2041.73 | H68: 5276 | I68: United States | K68: 1997 | L68: MG Special | M68: MG | N68: 55 | O68: Won | P68: 42807 | Q68: 42894 | R68: 52 | S68: =IF(O68="Won",R68,IF(O68="Lost",0,N68)) -> 52 | T68: =IF(AND(P68<>"",Q68<>""),Q68-P68,"") -> 87 | U68: =IF(AND(O68="Engaging",P68<>""),'Leia-me'!$B$5-P68,"") | V68: =IF(O68<>"Engaging","",IF(U68<='Leia-me'!$B$6,"Saudável",IF(U68<='Leia-me'!$B$7,"Esfriando",IF(U68<='Leia-me'!$B$8,"Última chance","Zumbi")))) | W68: =IF(O68="Won",1,IF(O68="Lost",0,"")) -> 1 | Y68: =IF(E68="","Sim","")
A69: K2KK9SW2 | B69: Central | C69: Dustin Brinkmann | D69: Anna Snelling | E69: Inity | F69: marketing | G69: 2403.58 | H69: 8801 | I69: United States | K69: 1986 | L69: GTX Basic | M69: GTX | N69: 550 | O69: Won | P69: 42810 | Q69: 42857 | R69: 550 | S69: =IF(O69="Won",R69,IF(O69="Lost",0,N69)) -> 550 | T69: =IF(AND(P69<>"",Q69<>""),Q69-P69,"") -> 47 | U69: =IF(AND(O69="Engaging",P69<>""),'Leia-me'!$B$5-P69,"") | V69: =IF(O69<>"Engaging","",IF(U69<='Leia-me'!$B$6,"Saudável",IF(U69<='Leia-me'!$B$7,"Esfriando",IF(U69<='Leia-me'!$B$8,"Última chance","Zumbi")))) | W69: =IF(O69="Won",1,IF(O69="Lost",0,"")) -> 1 | Y69: =IF(E69="","Sim","")
A70: IDIMBX0N | B70: Central | C70: Dustin Brinkmann | D70: Anna Snelling | E70: Genco Pura Olive Oil Company | F70: retail | G70: 894.33 | H70: 1635 | I70: Italy | K70: 2007 | L70: GTX Plus Pro | M70: GTX | N70: 5482 | O70: Won | P70: 42811 | Q70: 42820 | R70: 6064 | S70: =IF(O70="Won",R70,IF(O70="Lost",0,N70)) -> 6064 | T70: =IF(AND(P70<>"",Q70<>""),Q70-P70,"") -> 9 | U70: =IF(AND(O70="Engaging",P70<>""),'Leia-me'!$B$5-P70,"") | V70: =IF(O70<>"Engaging","",IF(U70<='Leia-me'!$B$6,"Saudável",IF(U70<='Leia-me'!$B$7,"Esfriando",IF(U70<='Leia-me'!$B$8,"Última chance","Zumbi")))) | W70: =IF(O70="Won",1,IF(O70="Lost",0,"")) -> 1 | Y70: =IF(E70="","Sim","")
A71: G7PNQB9M | B71: Central | C71: Dustin Brinkmann | D71: Anna Snelling | E71: Warephase | F71: services | G71: 2041.73 | H71: 5276 | I71: United States | K71: 1997 | L71: GTX Plus Basic | M71: GTX | N71: 1096 | O71: Lost | P71: 42812 | Q71: 42880 | R71: 0 | S71: =IF(O71="Won",R71,IF(O71="Lost",0,N71)) -> 0 | T71: =IF(AND(P71<>"",Q71<>""),Q71-P71,"") -> 68 | U71: =IF(AND(O71="Engaging",P71<>""),'Leia-me'!$B$5-P71,"") | V71: =IF(O71<>"Engaging","",IF(U71<='Leia-me'!$B$6,"Saudável",IF(U71<='Leia-me'!$B$7,"Esfriando",IF(U71<='Leia-me'!$B$8,"Última chance","Zumbi")))) | W71: =IF(O71="Won",1,IF(O71="Lost",0,"")) -> 0 | Y71: =IF(E71="","Sim","")
A72: 2BYD4WQ7 | B72: Central | C72: Dustin Brinkmann | D72: Anna Snelling | E72: Funholding | F72: finance | G72: 2819.5 | H72: 7227 | I72: United States | J72: Golddex | K72: 1991 | L72: MG Special | M72: MG | N72: 55 | O72: Lost | P72: 42814 | Q72: 42874 | R72: 0 | S72: =IF(O72="Won",R72,IF(O72="Lost",0,N72)) -> 0 | T72: =IF(AND(P72<>"",Q72<>""),Q72-P72,"") -> 60 | U72: =IF(AND(O72="Engaging",P72<>""),'Leia-me'!$B$5-P72,"") | V72: =IF(O72<>"Engaging","",IF(U72<='Leia-me'!$B$6,"Saudável",IF(U72<='Leia-me'!$B$7,"Esfriando",IF(U72<='Leia-me'!$B$8,"Última chance","Zumbi")))) | W72: =IF(O72="Won",1,IF(O72="Lost",0,"")) -> 0 | Y72: =IF(E72="","Sim","")
A73: DDBH2FPP | B73: Central | C73: Dustin Brinkmann | D73: Anna Snelling | E73: Rangreen | F73: technolgy | G73: 2938.67 | H73: 8775 | I73: Panama | K73: 1987 | L73: GTX Plus Basic | M73: GTX | N73: 1096 | O73: Won | P73: 42815 | Q73: 42902 | R73: 1037 | S73: =IF(O73="Won",R73,IF(O73="Lost",0,N73)) -> 1037 | T73: =IF(AND(P73<>"",Q73<>""),Q73-P73,"") -> 87 | U73: =IF(AND(O73="Engaging",P73<>""),'Leia-me'!$B$5-P73,"") | V73: =IF(O73<>"Engaging","",IF(U73<='Leia-me'!$B$6,"Saudável",IF(U73<='Leia-me'!$B$7,"Esfriando",IF(U73<='Leia-me'!$B$8,"Última chance","Zumbi")))) | W73: =IF(O73="Won",1,IF(O73="Lost",0,"")) -> 1 | Y73: =IF(E73="","Sim","")
A74: ECOU1XXZ | B74: Central | C74: Dustin Brinkmann | D74: Anna Snelling | E74: Ron-tech | F74: medical | G74: 3922.42 | H74: 6837 | I74: United States | K74: 1992 | L74: MG Special | M74: MG | N74: 55 | O74: Won | P74: 42816 | Q74: 42885 | R74: 52 | S74: =IF(O74="Won",R74,IF(O74="Lost",0,N74)) -> 52 | T74: =IF(AND(P74<>"",Q74<>""),Q74-P74,"") -> 69 | U74: =IF(AND(O74="Engaging",P74<>""),'Leia-me'!$B$5-P74,"") | V74: =IF(O74<>"Engaging","",IF(U74<='Leia-me'!$B$6,"Saudável",IF(U74<='Leia-me'!$B$7,"Esfriando",IF(U74<='Leia-me'!$B$8,"Última chance","Zumbi")))) | W74: =IF(O74="Won",1,IF(O74="Lost",0,"")) -> 1 | Y74: =IF(E74="","Sim","")
A75: WNMF0OHM | B75: Central | C75: Dustin Brinkmann | D75: Anna Snelling | E75: dambase | F75: marketing | G75: 2173.98 | H75: 2928 | I75: United States | J75: Inity | K75: 1995 | L75: GTX Plus Pro | M75: GTX | N75: 5482 | O75: Won | P75: 42817 | Q75: 42826 | R75: 5060 | S75: =IF(O75="Won",R75,IF(O75="Lost",0,N75)) -> 5060 | T75: =IF(AND(P75<>"",Q75<>""),Q75-P75,"") -> 9 | U75: =IF(AND(O75="Engaging",P75<>""),'Leia-me'!$B$5-P75,"") | V75: =IF(O75<>"Engaging","",IF(U75<='Leia-me'!$B$6,"Saudável",IF(U75<='Leia-me'!$B$7,"Esfriando",IF(U75<='Leia-me'!$B$8,"Última chance","Zumbi")))) | W75: =IF(O75="Won",1,IF(O75="Lost",0,"")) -> 1 | Y75: =IF(E75="","Sim","")
A76: PHP5V833 | B76: Central | C76: Dustin Brinkmann | D76: Anna Snelling | E76: Cancity | F76: retail | G76: 718.62 | H76: 2448 | I76: United States | K76: 2001 | L76: GTX Basic | M76: GTX | N76: 550 | O76: Lost | P76: 42818 | Q76: 42873 | R76: 0 | S76: =IF(O76="Won",R76,IF(O76="Lost",0,N76)) -> 0 | T76: =IF(AND(P76<>"",Q76<>""),Q76-P76,"") -> 55 | U76: =IF(AND(O76="Engaging",P76<>""),'Leia-me'!$B$5-P76,"") | V76: =IF(O76<>"Engaging","",IF(U76<='Leia-me'!$B$6,"Saudável",IF(U76<='Leia-me'!$B$7,"Esfriando",IF(U76<='Leia-me'!$B$8,"Última chance","Zumbi")))) | W76: =IF(O76="Won",1,IF(O76="Lost",0,"")) -> 0 | Y76: =IF(E76="","Sim","")
A77: 7XEB6TFB | B77: Central | C77: Dustin Brinkmann | D77: Anna Snelling | E77: Scottech | F77: marketing | G77: 45.39 | H77: 100 | I77: United States | J77: Inity | K77: 2012 | L77: MG Special | M77: MG | N77: 55 | O77: Won | P77: 42818 | Q77: 42892 | R77: 56 | S77: =IF(O77="Won",R77,IF(O77="Lost",0,N77)) -> 56 | T77: =IF(AND(P77<>"",Q77<>""),Q77-P77,"") -> 74 | U77: =IF(AND(O77="Engaging",P77<>""),'Leia-me'!$B$5-P77,"") | V77: =IF(O77<>"Engaging","",IF(U77<='Leia-me'!$B$6,"Saudável",IF(U77<='Leia-me'!$B$7,"Esfriando",IF(U77<='Leia-me'!$B$8,"Última chance","Zumbi")))) | W77: =IF(O77="Won",1,IF(O77="Lost",0,"")) -> 1 | Y77: =IF(E77="","Sim","")
A78: KV9LW061 | B78: Central | C78: Dustin Brinkmann | D78: Anna Snelling | E78: Codehow | F78: software | G78: 2714.9 | H78: 2641 | I78: United States | J78: Acme Corporation | K78: 1998 | L78: MG Advanced | M78: MG | N78: 3393 | O78: Won | P78: 42818 | Q78: 42829 | R78: 3445 | S78: =IF(O78="Won",R78,IF(O78="Lost",0,N78)) -> 3445 | T78: =IF(AND(P78<>"",Q78<>""),Q78-P78,"") -> 11 | U78: =IF(AND(O78="Engaging",P78<>""),'Leia-me'!$B$5-P78,"") | V78: =IF(O78<>"Engaging","",IF(U78<='Leia-me'!$B$6,"Saudável",IF(U78<='Leia-me'!$B$7,"Esfriando",IF(U78<='Leia-me'!$B$8,"Última chance","Zumbi")))) | W78: =IF(O78="Won",1,IF(O78="Lost",0,"")) -> 1 | Y78: =IF(E78="","Sim","")
A79: 9BGKQZ3H | B79: Central | C79: Dustin Brinkmann | D79: Anna Snelling | E79: Domzoom | F79: entertainment | G79: 217.87 | H79: 551 | I79: United States | K79: 1998 | L79: MG Special | M79: MG | N79: 55 | O79: Lost | P79: 42819 | Q79: 42828 | R79: 0 | S79: =IF(O79="Won",R79,IF(O79="Lost",0,N79)) -> 0 | T79: =IF(AND(P79<>"",Q79<>""),Q79-P79,"") -> 9 | U79: =IF(AND(O79="Engaging",P79<>""),'Leia-me'!$B$5-P79,"") | V79: =IF(O79<>"Engaging","",IF(U79<='Leia-me'!$B$6,"Saudável",IF(U79<='Leia-me'!$B$7,"Esfriando",IF(U79<='Leia-me'!$B$8,"Última chance","Zumbi")))) | W79: =IF(O79="Won",1,IF(O79="Lost",0,"")) -> 0 | Y79: =IF(E79="","Sim","")
A80: M52B4VC5 | B80: Central | C80: Dustin Brinkmann | D80: Anna Snelling | E80: Globex Corporation | F80: technolgy | G80: 1223.72 | H80: 2497 | I80: Norway | K80: 2000 | L80: MG Special | M80: MG | N80: 55 | O80: Lost | P80: 42820 | Q80: 42829 | R80: 0 | S80: =IF(O80="Won",R80,IF(O80="Lost",0,N80)) -> 0 | T80: =IF(AND(P80<>"",Q80<>""),Q80-P80,"") -> 9 | U80: =IF(AND(O80="Engaging",P80<>""),'Leia-me'!$B$5-P80,"") | V80: =IF(O80<>"Engaging","",IF(U80<='Leia-me'!$B$6,"Saudável",IF(U80<='Leia-me'!$B$7,"Esfriando",IF(U80<='Leia-me'!$B$8,"Última chance","Zumbi")))) | W80: =IF(O80="Won",1,IF(O80="Lost",0,"")) -> 0 | Y80: =IF(E80="","Sim","")
A81: Z72Y3C3C | B81: Central | C81: Dustin Brinkmann | D81: Anna Snelling | E81: Dontechi | F81: software | G81: 4618 | H81: 10083 | I81: United States | K81: 1982 | L81: MG Special | M81: MG | N81: 55 | O81: Won | P81: 42820 | Q81: 42829 | R81: 54 | S81: =IF(O81="Won",R81,IF(O81="Lost",0,N81)) -> 54 | T81: =IF(AND(P81<>"",Q81<>""),Q81-P81,"") -> 9 | U81: =IF(AND(O81="Engaging",P81<>""),'Leia-me'!$B$5-P81,"") | V81: =IF(O81<>"Engaging","",IF(U81<='Leia-me'!$B$6,"Saudável",IF(U81<='Leia-me'!$B$7,"Esfriando",IF(U81<='Leia-me'!$B$8,"Última chance","Zumbi")))) | W81: =IF(O81="Won",1,IF(O81="Lost",0,"")) -> 1 | Y81: =IF(E81="","Sim","")
A82: X8QV83G1 | B82: Central | C82: Dustin Brinkmann | D82: Anna Snelling | E82: Codehow | F82: software | G82: 2714.9 | H82: 2641 | I82: United States | J82: Acme Corporation | K82: 1998 | L82: MG Special | M82: MG | N82: 55 | O82: Lost | P82: 42822 | Q82: 42833 | R82: 0 | S82: =IF(O82="Won",R82,IF(O82="Lost",0,N82)) -> 0 | T82: =IF(AND(P82<>"",Q82<>""),Q82-P82,"") -> 11 | U82: =IF(AND(O82="Engaging",P82<>""),'Leia-me'!$B$5-P82,"") | V82: =IF(O82<>"Engaging","",IF(U82<='Leia-me'!$B$6,"Saudável",IF(U82<='Leia-me'!$B$7,"Esfriando",IF(U82<='Leia-me'!$B$8,"Última chance","Zumbi")))) | W82: =IF(O82="Won",1,IF(O82="Lost",0,"")) -> 0 | Y82: =IF(E82="","Sim","")
A83: T1ZYZ70B | B83: Central | C83: Dustin Brinkmann | D83: Anna Snelling | E83: Codehow | F83: software | G83: 2714.9 | H83: 2641 | I83: United States | J83: Acme Corporation | K83: 1998 | L83: MG Special | M83: MG | N83: 55 | O83: Lost | P83: 42822 | Q83: 42894 | R83: 0 | S83: =IF(O83="Won",R83,IF(O83="Lost",0,N83)) -> 0 | T83: =IF(AND(P83<>"",Q83<>""),Q83-P83,"") -> 72 | U83: =IF(AND(O83="Engaging",P83<>""),'Leia-me'!$B$5-P83,"") | V83: =IF(O83<>"Engaging","",IF(U83<='Leia-me'!$B$6,"Saudável",IF(U83<='Leia-me'!$B$7,"Esfriando",IF(U83<='Leia-me'!$B$8,"Última chance","Zumbi")))) | W83: =IF(O83="Won",1,IF(O83="Lost",0,"")) -> 0 | Y83: =IF(E83="","Sim","")
A84: SFFFNT6B | B84: Central | C84: Dustin Brinkmann | D84: Anna Snelling | E84: Treequote | F84: telecommunications | G84: 5266.09 | H84: 8595 | I84: United States | J84: Sonron | K84: 1988 | L84: MG Special | M84: MG | N84: 55 | O84: Lost | P84: 42825 | Q84: 42832 | R84: 0 | S84: =IF(O84="Won",R84,IF(O84="Lost",0,N84)) -> 0 | T84: =IF(AND(P84<>"",Q84<>""),Q84-P84,"") -> 7 | U84: =IF(AND(O84="Engaging",P84<>""),'Leia-me'!$B$5-P84,"") | V84: =IF(O84<>"Engaging","",IF(U84<='Leia-me'!$B$6,"Saudável",IF(U84<='Leia-me'!$B$7,"Esfriando",IF(U84<='Leia-me'!$B$8,"Última chance","Zumbi")))) | W84: =IF(O84="Won",1,IF(O84="Lost",0,"")) -> 0 | Y84: =IF(E84="","Sim","")
A85: 99AAJPQN | B85: Central | C85: Dustin Brinkmann | D85: Anna Snelling | E85: Condax | F85: medical | G85: 4.54 | H85: 9 | I85: United States | K85: 2017 | L85: MG Special | M85: MG | N85: 55 | O85: Won | P85: 42825 | Q85: 42901 | R85: 58 | S85: =IF(O85="Won",R85,IF(O85="Lost",0,N85)) -> 58 | T85: =IF(AND(P85<>"",Q85<>""),Q85-P85,"") -> 76 | U85: =IF(AND(O85="Engaging",P85<>""),'Leia-me'!$B$5-P85,"") | V85: =IF(O85<>"Engaging","",IF(U85<='Leia-me'!$B$6,"Saudável",IF(U85<='Leia-me'!$B$7,"Esfriando",IF(U85<='Leia-me'!$B$8,"Última chance","Zumbi")))) | W85: =IF(O85="Won",1,IF(O85="Lost",0,"")) -> 1 | Y85: =IF(E85="","Sim","")
A86: JW2FHT1G | B86: Central | C86: Dustin Brinkmann | D86: Anna Snelling | E86: dambase | F86: marketing | G86: 2173.98 | H86: 2928 | I86: United States | J86: Inity | K86: 1995 | L86: MG Advanced | M86: MG | N86: 3393 | O86: Won | P86: 42825 | Q86: 42833 | R86: 3626 | S86: =IF(O86="Won",R86,IF(O86="Lost",0,N86)) -> 3626 | T86: =IF(AND(P86<>"",Q86<>""),Q86-P86,"") -> 8 | U86: =IF(AND(O86="Engaging",P86<>""),'Leia-me'!$B$5-P86,"") | V86: =IF(O86<>"Engaging","",IF(U86<='Leia-me'!$B$6,"Saudável",IF(U86<='Leia-me'!$B$7,"Esfriando",IF(U86<='Leia-me'!$B$8,"Última chance","Zumbi")))) | W86: =IF(O86="Won",1,IF(O86="Lost",0,"")) -> 1 | Y86: =IF(E86="","Sim","")
A87: ZZJ4I52J | B87: Central | C87: Dustin Brinkmann | D87: Anna Snelling | E87: Hottechi | F87: technolgy | G87: 8170.38 | H87: 16499 | I87: Korea | K87: 1997 | L87: GTX Basic | M87: GTX | N87: 550 | O87: Won | P87: 42826 | Q87: 42860 | R87: 518 | S87: =IF(O87="Won",R87,IF(O87="Lost",0,N87)) -> 518 | T87: =IF(AND(P87<>"",Q87<>""),Q87-P87,"") -> 34 | U87: =IF(AND(O87="Engaging",P87<>""),'Leia-me'!$B$5-P87,"") | V87: =IF(O87<>"Engaging","",IF(U87<='Leia-me'!$B$6,"Saudável",IF(U87<='Leia-me'!$B$7,"Esfriando",IF(U87<='Leia-me'!$B$8,"Última chance","Zumbi")))) | W87: =IF(O87="Won",1,IF(O87="Lost",0,"")) -> 1 | Y87: =IF(E87="","Sim","")
A88: 7RI58VF7 | B88: Central | C88: Dustin Brinkmann | D88: Anna Snelling | E88: Streethex | F88: retail | G88: 1376.8 | H88: 1165 | I88: Belgium | K88: 1988 | L88: GTX Basic | M88: GTX | N88: 550 | O88: Won | P88: 42827 | Q88: 42906 | R88: 460 | S88: =IF(O88="Won",R88,IF(O88="Lost",0,N88)) -> 460 | T88: =IF(AND(P88<>"",Q88<>""),Q88-P88,"") -> 79 | U88: =IF(AND(O88="Engaging",P88<>""),'Leia-me'!$B$5-P88,"") | V88: =IF(O88<>"Engaging","",IF(U88<='Leia-me'!$B$6,"Saudável",IF(U88<='Leia-me'!$B$7,"Esfriando",IF(U88<='Leia-me'!$B$8,"Última chance","Zumbi")))) | W88: =IF(O88="Won",1,IF(O88="Lost",0,"")) -> 1 | Y88: =IF(E88="","Sim","")
A89: 4AHNCJ2Y | B89: Central | C89: Dustin Brinkmann | D89: Anna Snelling | E89: Rangreen | F89: technolgy | G89: 2938.67 | H89: 8775 | I89: Panama | K89: 1987 | L89: GTX Basic | M89: GTX | N89: 550 | O89: Won | P89: 42828 | Q89: 42913 | R89: 524 | S89: =IF(O89="Won",R89,IF(O89="Lost",0,N89)) -> 524 | T89: =IF(AND(P89<>"",Q89<>""),Q89-P89,"") -> 85 | U89: =IF(AND(O89="Engaging",P89<>""),'Leia-me'!$B$5-P89,"") | V89: =IF(O89<>"Engaging","",IF(U89<='Leia-me'!$B$6,"Saudável",IF(U89<='Leia-me'!$B$7,"Esfriando",IF(U89<='Leia-me'!$B$8,"Última chance","Zumbi")))) | W89: =IF(O89="Won",1,IF(O89="Lost",0,"")) -> 1 | Y89: =IF(E89="","Sim","")
A90: VIV0OXU6 | B90: Central | C90: Dustin Brinkmann | D90: Anna Snelling | E90: Domzoom | F90: entertainment | G90: 217.87 | H90: 551 | I90: United States | K90: 1998 | L90: GTX Basic | M90: GTX | N90: 550 | O90: Won | P90: 42829 | Q90: 42836 | R90: 582 | S90: =IF(O90="Won",R90,IF(O90="Lost",0,N90)) -> 582 | T90: =IF(AND(P90<>"",Q90<>""),Q90-P90,"") -> 7 | U90: =IF(AND(O90="Engaging",P90<>""),'Leia-me'!$B$5-P90,"") | V90: =IF(O90<>"Engaging","",IF(U90<='Leia-me'!$B$6,"Saudável",IF(U90<='Leia-me'!$B$7,"Esfriando",IF(U90<='Leia-me'!$B$8,"Última chance","Zumbi")))) | W90: =IF(O90="Won",1,IF(O90="Lost",0,"")) -> 1 | Y90: =IF(E90="","Sim","")
A91: KVF0HK8S | B91: Central | C91: Dustin Brinkmann | D91: Anna Snelling | E91: Domzoom | F91: entertainment | G91: 217.87 | H91: 551 | I91: United States | K91: 1998 | L91: MG Special | M91: MG | N91: 55 | O91: Won | P91: 42829 | Q91: 42837 | R91: 59 | S91: =IF(O91="Won",R91,IF(O91="Lost",0,N91)) -> 59 | T91: =IF(AND(P91<>"",Q91<>""),Q91-P91,"") -> 8 | U91: =IF(AND(O91="Engaging",P91<>""),'Leia-me'!$B$5-P91,"") | V91: =IF(O91<>"Engaging","",IF(U91<='Leia-me'!$B$6,"Saudável",IF(U91<='Leia-me'!$B$7,"Esfriando",IF(U91<='Leia-me'!$B$8,"Última chance","Zumbi")))) | W91: =IF(O91="Won",1,IF(O91="Lost",0,"")) -> 1 | Y91: =IF(E91="","Sim","")
A92: U9E3G8UT | B92: Central | C92: Dustin Brinkmann | D92: Anna Snelling | E92: Conecom | F92: technolgy | G92: 1520.66 | H92: 1806 | I92: United States | K92: 2005 | L92: GTX Plus Basic | M92: GTX | N92: 1096 | O92: Lost | P92: 42830 | Q92: 42831 | R92: 0 | S92: =IF(O92="Won",R92,IF(O92="Lost",0,N92)) -> 0 | T92: =IF(AND(P92<>"",Q92<>""),Q92-P92,"") -> 1 | U92: =IF(AND(O92="Engaging",P92<>""),'Leia-me'!$B$5-P92,"") | V92: =IF(O92<>"Engaging","",IF(U92<='Leia-me'!$B$6,"Saudável",IF(U92<='Leia-me'!$B$7,"Esfriando",IF(U92<='Leia-me'!$B$8,"Última chance","Zumbi")))) | W92: =IF(O92="Won",1,IF(O92="Lost",0,"")) -> 0 | Y92: =IF(E92="","Sim","")
A93: FB1AO8SL | B93: Central | C93: Dustin Brinkmann | D93: Anna Snelling | E93: Betatech | F93: medical | G93: 647.18 | H93: 1185 | I93: Kenya | K93: 1986 | L93: MG Special | M93: MG | N93: 55 | O93: Won | P93: 42830 | Q93: 42839 | R93: 57 | S93: =IF(O93="Won",R93,IF(O93="Lost",0,N93)) -> 57 | T93: =IF(AND(P93<>"",Q93<>""),Q93-P93,"") -> 9 | U93: =IF(AND(O93="Engaging",P93<>""),'Leia-me'!$B$5-P93,"") | V93: =IF(O93<>"Engaging","",IF(U93<='Leia-me'!$B$6,"Saudável",IF(U93<='Leia-me'!$B$7,"Esfriando",IF(U93<='Leia-me'!$B$8,"Última chance","Zumbi")))) | W93: =IF(O93="Won",1,IF(O93="Lost",0,"")) -> 1 | Y93: =IF(E93="","Sim","")
A94: HJP5X1MT | B94: Central | C94: Dustin Brinkmann | D94: Anna Snelling | E94: Dontechi | F94: software | G94: 4618 | H94: 10083 | I94: United States | K94: 1982 | L94: GTX Basic | M94: GTX | N94: 550 | O94: Won | P94: 42831 | Q94: 42895 | R94: 527 | S94: =IF(O94="Won",R94,IF(O94="Lost",0,N94)) -> 527 | T94: =IF(AND(P94<>"",Q94<>""),Q94-P94,"") -> 64 | U94: =IF(AND(O94="Engaging",P94<>""),'Leia-me'!$B$5-P94,"") | V94: =IF(O94<>"Engaging","",IF(U94<='Leia-me'!$B$6,"Saudável",IF(U94<='Leia-me'!$B$7,"Esfriando",IF(U94<='Leia-me'!$B$8,"Última chance","Zumbi")))) | W94: =IF(O94="Won",1,IF(O94="Lost",0,"")) -> 1 | Y94: =IF(E94="","Sim","")
A95: X9BUD48V | B95: Central | C95: Dustin Brinkmann | D95: Anna Snelling | E95: Warephase | F95: services | G95: 2041.73 | H95: 5276 | I95: United States | K95: 1997 | L95: GTX Basic | M95: GTX | N95: 550 | O95: Won | P95: 42832 | Q95: 42833 | R95: 596 | S95: =IF(O95="Won",R95,IF(O95="Lost",0,N95)) -> 596 | T95: =IF(AND(P95<>"",Q95<>""),Q95-P95,"") -> 1 | U95: =IF(AND(O95="Engaging",P95<>""),'Leia-me'!$B$5-P95,"") | V95: =IF(O95<>"Engaging","",IF(U95<='Leia-me'!$B$6,"Saudável",IF(U95<='Leia-me'!$B$7,"Esfriando",IF(U95<='Leia-me'!$B$8,"Última chance","Zumbi")))) | W95: =IF(O95="Won",1,IF(O95="Lost",0,"")) -> 1 | Y95: =IF(E95="","Sim","")
A96: 8LTQ9ESQ | B96: Central | C96: Dustin Brinkmann | D96: Anna Snelling | E96: dambase | F96: marketing | G96: 2173.98 | H96: 2928 | I96: United States | J96: Inity | K96: 1995 | L96: MG Advanced | M96: MG | N96: 3393 | O96: Lost | P96: 42833 | Q96: 42840 | R96: 0 | S96: =IF(O96="Won",R96,IF(O96="Lost",0,N96)) -> 0 | T96: =IF(AND(P96<>"",Q96<>""),Q96-P96,"") -> 7 | U96: =IF(AND(O96="Engaging",P96<>""),'Leia-me'!$B$5-P96,"") | V96: =IF(O96<>"Engaging","",IF(U96<='Leia-me'!$B$6,"Saudável",IF(U96<='Leia-me'!$B$7,"Esfriando",IF(U96<='Leia-me'!$B$8,"Última chance","Zumbi")))) | W96: =IF(O96="Won",1,IF(O96="Lost",0,"")) -> 0 | Y96: =IF(E96="","Sim","")
A97: EBBIJKLT | B97: Central | C97: Dustin Brinkmann | D97: Anna Snelling | E97: Stanredtax | F97: finance | G97: 1698.2 | H97: 3798 | I97: United States | K97: 1987 | L97: GTX Plus Basic | M97: GTX | N97: 1096 | O97: Won | P97: 42833 | Q97: 42840 | R97: 1142 | S97: =IF(O97="Won",R97,IF(O97="Lost",0,N97)) -> 1142 | T97: =IF(AND(P97<>"",Q97<>""),Q97-P97,"") -> 7 | U97: =IF(AND(O97="Engaging",P97<>""),'Leia-me'!$B$5-P97,"") | V97: =IF(O97<>"Engaging","",IF(U97<='Leia-me'!$B$6,"Saudável",IF(U97<='Leia-me'!$B$7,"Esfriando",IF(U97<='Leia-me'!$B$8,"Última chance","Zumbi")))) | W97: =IF(O97="Won",1,IF(O97="Lost",0,"")) -> 1 | Y97: =IF(E97="","Sim","")
A98: 93X2W24Q | B98: Central | C98: Dustin Brinkmann | D98: Anna Snelling | E98: Betatech | F98: medical | G98: 647.18 | H98: 1185 | I98: Kenya | K98: 1986 | L98: MG Advanced | M98: MG | N98: 3393 | O98: Won | P98: 42834 | Q98: 42888 | R98: 3666 | S98: =IF(O98="Won",R98,IF(O98="Lost",0,N98)) -> 3666 | T98: =IF(AND(P98<>"",Q98<>""),Q98-P98,"") -> 54 | U98: =IF(AND(O98="Engaging",P98<>""),'Leia-me'!$B$5-P98,"") | V98: =IF(O98<>"Engaging","",IF(U98<='Leia-me'!$B$6,"Saudável",IF(U98<='Leia-me'!$B$7,"Esfriando",IF(U98<='Leia-me'!$B$8,"Última chance","Zumbi")))) | W98: =IF(O98="Won",1,IF(O98="Lost",0,"")) -> 1 | Y98: =IF(E98="","Sim","")
A99: YXOM4S7G | B99: Central | C99: Dustin Brinkmann | D99: Anna Snelling | E99: Finhigh | F99: finance | G99: 1102.43 | H99: 1759 | I99: United States | K99: 2006 | L99: MG Special | M99: MG | N99: 55 | O99: Lost | P99: 42835 | Q99: 42836 | R99: 0 | S99: =IF(O99="Won",R99,IF(O99="Lost",0,N99)) -> 0 | T99: =IF(AND(P99<>"",Q99<>""),Q99-P99,"") -> 1 | U99: =IF(AND(O99="Engaging",P99<>""),'Leia-me'!$B$5-P99,"") | V99: =IF(O99<>"Engaging","",IF(U99<='Leia-me'!$B$6,"Saudável",IF(U99<='Leia-me'!$B$7,"Esfriando",IF(U99<='Leia-me'!$B$8,"Última chance","Zumbi")))) | W99: =IF(O99="Won",1,IF(O99="Lost",0,"")) -> 0 | Y99: =IF(E99="","Sim","")
A100: 2K8H292S | B100: Central | C100: Dustin Brinkmann | D100: Anna Snelling | E100: Rundofase | F100: technolgy | G100: 1008.06 | H100: 1238 | I100: United States | K100: 1983 | L100: GTX Basic | M100: GTX | N100: 550 | O100: Lost | P100: 42837 | Q100: 42843 | R100: 0 | S100: =IF(O100="Won",R100,IF(O100="Lost",0,N100)) -> 0 | T100: =IF(AND(P100<>"",Q100<>""),Q100-P100,"") -> 6 | U100: =IF(AND(O100="Engaging",P100<>""),'Leia-me'!$B$5-P100,"") | V100: =IF(O100<>"Engaging","",IF(U100<='Leia-me'!$B$6,"Saudável",IF(U100<='Leia-me'!$B$7,"Esfriando",IF(U100<='Leia-me'!$B$8,"Última chance","Zumbi")))) | W100: =IF(O100="Won",1,IF(O100="Lost",0,"")) -> 0 | Y100: =IF(E100="","Sim","")
...

Sheet Resumo_Escritorio
A1: Escritório | B1: Vendedores (cadastrados) | C1: Vendedores ativos | D1: Deals total | E1: Won | F1: Lost | G1: Engaging | H1: Prospecting | I1: Win rate | J1: Receita ganha (US$) | K1: Ticket médio ganho (US$) | L1: Pipeline aberto (US$) | M1: Engaging vivos (≤ limite zumbi) | N1: Valor vivos (US$) | O1: Zumbis | P1: Valor zumbi (US$) | Q1: % pipeline Engaging zumbi | R1: Abertos sem conta
A2: Central | B2: 11 | C2: 10 | D2: =COUNTIFS(Pipeline_Completo!$B$2:$B$8801,$A2) -> 3512 | E2: =COUNTIFS(Pipeline_Completo!$B$2:$B$8801,$A2,Pipeline_Completo!$O$2:$O$8801,"Won") -> 1629 | F2: =COUNTIFS(Pipeline_Completo!$B$2:$B$8801,$A2,Pipeline_Completo!$O$2:$O$8801,"Lost") -> 975 | G2: =COUNTIFS(Pipeline_Completo!$B$2:$B$8801,$A2,Pipeline_Completo!$O$2:$O$8801,"Engaging") -> 408 | H2: =COUNTIFS(Pipeline_Completo!$B$2:$B$8801,$A2,Pipeline_Completo!$O$2:$O$8801,"Prospecting") -> 500 | I2: =IFERROR(E2/(E2+F2),"") -> 0.62557604 | J2: =SUMIFS(Pipeline_Completo!$R$2:$R$8801,Pipeline_Completo!$B$2:$B$8801,$A2,Pipeline_Completo!$O$2:$O$8801,"Won") -> 3346293 | K2: =IFERROR(J2/E2,"") -> 2054.2007 | L2: =SUMIFS(Pipeline_Completo!$S$2:$S$8801,Pipeline_Completo!$B$2:$B$8801,$A2,Pipeline_Completo!$O$2:$O$8801,"Engaging")+SUMIFS(Pipeline_Completo!$S$2:$S$8801,Pipeline_Completo!$B$2:$B$8801,$A2,Pipeline_Completo!$O$2:$O$8801,"Prospecting") -> 1898408 | M2: =COUNTIFS(Pipeline_Completo!$B$2:$B$8801,$A2,Pipeline_Completo!$V$2:$V$8801,"Saudável")+COUNTIFS(Pipeline_Completo!$B$2:$B$8801,$A2,Pipeline_Completo!$V$2:$V$8801,"Esfriando")+COUNTIFS(Pipeline_Completo!$B$2:$B$8801,$A2,Pipeline_Completo!$V$2:$V$8801,"Última chance") -> 5 | N2: =SUMIFS(Pipeline_Completo!$S$2:$S$8801,Pipeline_Completo!$B$2:$B$8801,$A2,Pipeline_Completo!$V$2:$V$8801,"Saudável")+SUMIFS(Pipeline_Completo!$S$2:$S$8801,Pipeline_Completo!$B$2:$B$8801,$A2,Pipeline_Completo!$V$2:$V$8801,"Esfriando")+SUMIFS(Pipeline_Completo!$S$2:$S$8801,Pipeline_Completo!$B$2:$B$8801,$A2,Pipeline_Completo!$V$2:$V$8801,"Última chance") -> 6577 | O2: =COUNTIFS(Pipeline_Completo!$B$2:$B$8801,$A2,Pipeline_Completo!$V$2:$V$8801,"Zumbi") -> 403 | P2: =SUMIFS(Pipeline_Completo!$S$2:$S$8801,Pipeline_Completo!$B$2:$B$8801,$A2,Pipeline_Completo!$V$2:$V$8801,"Zumbi") -> 817845 | Q2: =IFERROR(P2/(N2+P2),"") -> 0.99202229 | R2: =COUNTIFS(Pipeline_Completo!$B$2:$B$8801,$A2,Pipeline_Completo!$O$2:$O$8801,"Engaging",Pipeline_Completo!$E$2:$E$8801,"")+COUNTIFS(Pipeline_Completo!$B$2:$B$8801,$A2,Pipeline_Completo!$O$2:$O$8801,"Prospecting",Pipeline_Completo!$E$2:$E$8801,"") -> 611
A3: East | B3: 12 | C3: 10 | D3: =COUNTIFS(Pipeline_Completo!$B$2:$B$8801,$A3) -> 2291 | E3: =COUNTIFS(Pipeline_Completo!$B$2:$B$8801,$A3,Pipeline_Completo!$O$2:$O$8801,"Won") -> 1171 | F3: =COUNTIFS(Pipeline_Completo!$B$2:$B$8801,$A3,Pipeline_Completo!$O$2:$O$8801,"Lost") -> 687 | G3: =COUNTIFS(Pipeline_Completo!$B$2:$B$8801,$A3,Pipeline_Completo!$O$2:$O$8801,"Engaging") -> 433 | H3: =COUNTIFS(Pipeline_Completo!$B$2:$B$8801,$A3,Pipeline_Completo!$O$2:$O$8801,"Prospecting") -> 0 | I3: =IFERROR(E3/(E3+F3),"") -> 0.63024758 | J3: =SUMIFS(Pipeline_Completo!$R$2:$R$8801,Pipeline_Completo!$B$2:$B$8801,$A3,Pipeline_Completo!$O$2:$O$8801,"Won") -> 3090594 | K3: =IFERROR(J3/E3,"") -> 2639.2775 | L3: =SUMIFS(Pipeline_Completo!$S$2:$S$8801,Pipeline_Completo!$B$2:$B$8801,$A3,Pipeline_Completo!$O$2:$O$8801,"Engaging")+SUMIFS(Pipeline_Completo!$S$2:$S$8801,Pipeline_Completo!$B$2:$B$8801,$A3,Pipeline_Completo!$O$2:$O$8801,"Prospecting") -> 1069586 | M3: =COUNTIFS(Pipeline_Completo!$B$2:$B$8801,$A3,Pipeline_Completo!$V$2:$V$8801,"Saudável")+COUNTIFS(Pipeline_Completo!$B$2:$B$8801,$A3,Pipeline_Completo!$V$2:$V$8801,"Esfriando")+COUNTIFS(Pipeline_Completo!$B$2:$B$8801,$A3,Pipeline_Completo!$V$2:$V$8801,"Última chance") -> 107 | N3: =SUMIFS(Pipeline_Completo!$S$2:$S$8801,Pipeline_Completo!$B$2:$B$8801,$A3,Pipeline_Completo!$V$2:$V$8801,"Saudável")+SUMIFS(Pipeline_Completo!$S$2:$S$8801,Pipeline_Completo!$B$2:$B$8801,$A3,Pipeline_Completo!$V$2:$V$8801,"Esfriando")+SUMIFS(Pipeline_Completo!$S$2:$S$8801,Pipeline_Completo!$B$2:$B$8801,$A3,Pipeline_Completo!$V$2:$V$8801,"Última chance") -> 260658 | O3: =COUNTIFS(Pipeline_Completo!$B$2:$B$8801,$A3,Pipeline_Completo!$V$2:$V$8801,"Zumbi") -> 326 | P3: =SUMIFS(Pipeline_Completo!$S$2:$S$8801,Pipeline_Completo!$B$2:$B$8801,$A3,Pipeline_Completo!$V$2:$V$8801,"Zumbi") -> 808928 | Q3: =IFERROR(P3/(N3+P3),"") -> 0.7563001 | R3: =COUNTIFS(Pipeline_Completo!$B$2:$B$8801,$A3,Pipeline_Completo!$O$2:$O$8801,"Engaging",Pipeline_Completo!$E$2:$E$8801,"")+COUNTIFS(Pipeline_Completo!$B$2:$B$8801,$A3,Pipeline_Completo!$O$2:$O$8801,"Prospecting",Pipeline_Completo!$E$2:$E$8801,"") -> 296
A4: West | B4: 12 | C4: 10 | D4: =COUNTIFS(Pipeline_Completo!$B$2:$B$8801,$A4) -> 2997 | E4: =COUNTIFS(Pipeline_Completo!$B$2:$B$8801,$A4,Pipeline_Completo!$O$2:$O$8801,"Won") -> 1438 | F4: =COUNTIFS(Pipeline_Completo!$B$2:$B$8801,$A4,Pipeline_Completo!$O$2:$O$8801,"Lost") -> 811 | G4: =COUNTIFS(Pipeline_Completo!$B$2:$B$8801,$A4,Pipeline_Completo!$O$2:$O$8801,"Engaging") -> 748 | H4: =COUNTIFS(Pipeline_Completo!$B$2:$B$8801,$A4,Pipeline_Completo!$O$2:$O$8801,"Prospecting") -> 0 | I4: =IFERROR(E4/(E4+F4),"") -> 0.63939529 | J4: =SUMIFS(Pipeline_Completo!$R$2:$R$8801,Pipeline_Completo!$B$2:$B$8801,$A4,Pipeline_Completo!$O$2:$O$8801,"Won") -> 3568647 | K4: =IFERROR(J4/E4,"") -> 2481.6739 | L4: =SUMIFS(Pipeline_Completo!$S$2:$S$8801,Pipeline_Completo!$B$2:$B$8801,$A4,Pipeline_Completo!$O$2:$O$8801,"Engaging")+SUMIFS(Pipeline_Completo!$S$2:$S$8801,Pipeline_Completo!$B$2:$B$8801,$A4,Pipeline_Completo!$O$2:$O$8801,"Prospecting") -> 1998221 | M4: =COUNTIFS(Pipeline_Completo!$B$2:$B$8801,$A4,Pipeline_Completo!$V$2:$V$8801,"Saudável")+COUNTIFS(Pipeline_Completo!$B$2:$B$8801,$A4,Pipeline_Completo!$V$2:$V$8801,"Esfriando")+COUNTIFS(Pipeline_Completo!$B$2:$B$8801,$A4,Pipeline_Completo!$V$2:$V$8801,"Última chance") -> 186 | N4: =SUMIFS(Pipeline_Completo!$S$2:$S$8801,Pipeline_Completo!$B$2:$B$8801,$A4,Pipeline_Completo!$V$2:$V$8801,"Saudável")+SUMIFS(Pipeline_Completo!$S$2:$S$8801,Pipeline_Completo!$B$2:$B$8801,$A4,Pipeline_Completo!$V$2:$V$8801,"Esfriando")+SUMIFS(Pipeline_Completo!$S$2:$S$8801,Pipeline_Completo!$B$2:$B$8801,$A4,Pipeline_Completo!$V$2:$V$8801,"Última chance") -> 426330 | O4: =COUNTIFS(Pipeline_Completo!$B$2:$B$8801,$A4,Pipeline_Completo!$V$2:$V$8801,"Zumbi") -> 562 | P4: =SUMIFS(Pipeline_Completo!$S$2:$S$8801,Pipeline_Completo!$B$2:$B$8801,$A4,Pipeline_Completo!$V$2:$V$8801,"Zumbi") -> 1571891 | Q4: =IFERROR(P4/(N4+P4),"") -> 0.78664522 | R4: =COUNTIFS(Pipeline_Completo!$B$2:$B$8801,$A4,Pipeline_Completo!$O$2:$O$8801,"Engaging",Pipeline_Completo!$E$2:$E$8801,"")+COUNTIFS(Pipeline_Completo!$B$2:$B$8801,$A4,Pipeline_Completo!$O$2:$O$8801,"Prospecting",Pipeline_Completo!$E$2:$E$8801,"") -> 518
A5: TOTAL | B5: =SUM(B2:B4) -> 35 | C5: =SUM(C2:C4) -> 30 | D5: =D2+D3+D4 -> 8800 | E5: =E2+E3+E4 -> 4238 | F5: =F2+F3+F4 -> 2473 | G5: =G2+G3+G4 -> 1589 | H5: =H2+H3+H4 -> 500 | I5: =IFERROR(E5/(E5+F5),"") -> 0.63150052 | J5: =J2+J3+J4 -> 10005534 | K5: =IFERROR(J5/E5,"") -> 2360.9094 | L5: =L2+L3+L4 -> 4966215 | M5: =M2+M3+M4 -> 298 | N5: =N2+N3+N4 -> 693565 | O5: =O2+O3+O4 -> 1291 | P5: =P2+P3+P4 -> 3198664 | Q5: =IFERROR(P5/(N5+P5),"") -> 0.82180776 | R5: =R2+R3+R4 -> 1425 | S5: =SUM(S2:S4) -> 0
A7: "Vendedores cadastrados"/"ativos" são contagens fixas (sales_teams.csv e vendedores com ≥1 deal).

Sheet Resumo_Gerente
A1: Gerente | B1: Escritório | C1: Vendedores (cadastrados) | D1: Vendedores ativos | E1: Deals total | F1: Won | G1: Lost | H1: Engaging | I1: Prospecting | J1: Win rate | K1: Receita ganha (US$) | L1: Ticket médio ganho (US$) | M1: Pipeline aberto (US$) | N1: Engaging vivos (≤ limite zumbi) | O1: Valor vivos (US$) | P1: Zumbis | Q1: Valor zumbi (US$) | R1: % pipeline Engaging zumbi | S1: Abertos sem conta
A2: Dustin Brinkmann | B2: Central | C2: 5 | D2: 5 | E2: =COUNTIFS(Pipeline_Completo!$C$2:$C$8801,$A2) -> 1583 | F2: =COUNTIFS(Pipeline_Completo!$C$2:$C$8801,$A2,Pipeline_Completo!$O$2:$O$8801,"Won") -> 747 | G2: =COUNTIFS(Pipeline_Completo!$C$2:$C$8801,$A2,Pipeline_Completo!$O$2:$O$8801,"Lost") -> 439 | H2: =COUNTIFS(Pipeline_Completo!$C$2:$C$8801,$A2,Pipeline_Completo!$O$2:$O$8801,"Engaging") -> 193 | I2: =COUNTIFS(Pipeline_Completo!$C$2:$C$8801,$A2,Pipeline_Completo!$O$2:$O$8801,"Prospecting") -> 204 | J2: =IFERROR(F2/(F2+G2),"") -> 0.62984823 | K2: =SUMIFS(Pipeline_Completo!$R$2:$R$8801,Pipeline_Completo!$C$2:$C$8801,$A2,Pipeline_Completo!$O$2:$O$8801,"Won") -> 1094363 | L2: =IFERROR(K2/F2,"") -> 1465.0107 | M2: =SUMIFS(Pipeline_Completo!$S$2:$S$8801,Pipeline_Completo!$C$2:$C$8801,$A2,Pipeline_Completo!$O$2:$O$8801,"Engaging")+SUMIFS(Pipeline_Completo!$S$2:$S$8801,Pipeline_Completo!$C$2:$C$8801,$A2,Pipeline_Completo!$O$2:$O$8801,"Prospecting") -> 585616 | N2: =COUNTIFS(Pipeline_Completo!$C$2:$C$8801,$A2,Pipeline_Completo!$V$2:$V$8801,"Saudável")+COUNTIFS(Pipeline_Completo!$C$2:$C$8801,$A2,Pipeline_Completo!$V$2:$V$8801,"Esfriando")+COUNTIFS(Pipeline_Completo!$C$2:$C$8801,$A2,Pipeline_Completo!$V$2:$V$8801,"Última chance") -> 3 | O2: =SUMIFS(Pipeline_Completo!$S$2:$S$8801,Pipeline_Completo!$C$2:$C$8801,$A2,Pipeline_Completo!$V$2:$V$8801,"Saudável")+SUMIFS(Pipeline_Completo!$S$2:$S$8801,Pipeline_Completo!$C$2:$C$8801,$A2,Pipeline_Completo!$V$2:$V$8801,"Esfriando")+SUMIFS(Pipeline_Completo!$S$2:$S$8801,Pipeline_Completo!$C$2:$C$8801,$A2,Pipeline_Completo!$V$2:$V$8801,"Última chance") -> 660 | P2: =COUNTIFS(Pipeline_Completo!$C$2:$C$8801,$A2,Pipeline_Completo!$V$2:$V$8801,"Zumbi") -> 190 | Q2: =SUMIFS(Pipeline_Completo!$S$2:$S$8801,Pipeline_Completo!$C$2:$C$8801,$A2,Pipeline_Completo!$V$2:$V$8801,"Zumbi") -> 282047 | R2: =IFERROR(Q2/(O2+Q2),"") -> 0.99766543 | S2: =COUNTIFS(Pipeline_Completo!$C$2:$C$8801,$A2,Pipeline_Completo!$O$2:$O$8801,"Engaging",Pipeline_Completo!$E$2:$E$8801,"")+COUNTIFS(Pipeline_Completo!$C$2:$C$8801,$A2,Pipeline_Completo!$O$2:$O$8801,"Prospecting",Pipeline_Completo!$E$2:$E$8801,"") -> 272
A3: Melvin Marxen | B3: Central | C3: 6 | D3: 5 | E3: =COUNTIFS(Pipeline_Completo!$C$2:$C$8801,$A3) -> 1929 | F3: =COUNTIFS(Pipeline_Completo!$C$2:$C$8801,$A3,Pipeline_Completo!$O$2:$O$8801,"Won") -> 882 | G3: =COUNTIFS(Pipeline_Completo!$C$2:$C$8801,$A3,Pipeline_Completo!$O$2:$O$8801,"Lost") -> 536 | H3: =COUNTIFS(Pipeline_Completo!$C$2:$C$8801,$A3,Pipeline_Completo!$O$2:$O$8801,"Engaging") -> 215 | I3: =COUNTIFS(Pipeline_Completo!$C$2:$C$8801,$A3,Pipeline_Completo!$O$2:$O$8801,"Prospecting") -> 296 | J3: =IFERROR(F3/(F3+G3),"") -> 0.62200282 | K3: =SUMIFS(Pipeline_Completo!$R$2:$R$8801,Pipeline_Completo!$C$2:$C$8801,$A3,Pipeline_Completo!$O$2:$O$8801,"Won") -> 2251930 | L3: =IFERROR(K3/F3,"") -> 2553.2086 | M3: =SUMIFS(Pipeline_Completo!$S$2:$S$8801,Pipeline_Completo!$C$2:$C$8801,$A3,Pipeline_Completo!$O$2:$O$8801,"Engaging")+SUMIFS(Pipeline_Completo!$S$2:$S$8801,Pipeline_Completo!$C$2:$C$8801,$A3,Pipeline_Completo!$O$2:$O$8801,"Prospecting") -> 1312792 | N3: =COUNTIFS(Pipeline_Completo!$C$2:$C$8801,$A3,Pipeline_Completo!$V$2:$V$8801,"Saudável")+COUNTIFS(Pipeline_Completo!$C$2:$C$8801,$A3,Pipeline_Completo!$V$2:$V$8801,"Esfriando")+COUNTIFS(Pipeline_Completo!$C$2:$C$8801,$A3,Pipeline_Completo!$V$2:$V$8801,"Última chance") -> 2 | O3: =SUMIFS(Pipeline_Completo!$S$2:$S$8801,Pipeline_Completo!$C$2:$C$8801,$A3,Pipeline_Completo!$V$2:$V$8801,"Saudável")+SUMIFS(Pipeline_Completo!$S$2:$S$8801,Pipeline_Completo!$C$2:$C$8801,$A3,Pipeline_Completo!$V$2:$V$8801,"Esfriando")+SUMIFS(Pipeline_Completo!$S$2:$S$8801,Pipeline_Completo!$C$2:$C$8801,$A3,Pipeline_Completo!$V$2:$V$8801,"Última chance") -> 5917 | P3: =COUNTIFS(Pipeline_Completo!$C$2:$C$8801,$A3,Pipeline_Completo!$V$2:$V$8801,"Zumbi") -> 213 | Q3: =SUMIFS(Pipeline_Completo!$S$2:$S$8801,Pipeline_Completo!$C$2:$C$8801,$A3,Pipeline_Completo!$V$2:$V$8801,"Zumbi") -> 535798 | R3: =IFERROR(Q3/(O3+Q3),"") -> 0.98907728 | S3: =COUNTIFS(Pipeline_Completo!$C$2:$C$8801,$A3,Pipeline_Completo!$O$2:$O$8801,"Engaging",Pipeline_Completo!$E$2:$E$8801,"")+COUNTIFS(Pipeline_Completo!$C$2:$C$8801,$A3,Pipeline_Completo!$O$2:$O$8801,"Prospecting",Pipeline_Completo!$E$2:$E$8801,"") -> 339
A4: Cara Losch | B4: East | C4: 6 | D4: 5 | E4: =COUNTIFS(Pipeline_Completo!$C$2:$C$8801,$A4) -> 964 | F4: =COUNTIFS(Pipeline_Completo!$C$2:$C$8801,$A4,Pipeline_Completo!$O$2:$O$8801,"Won") -> 480 | G4: =COUNTIFS(Pipeline_Completo!$C$2:$C$8801,$A4,Pipeline_Completo!$O$2:$O$8801,"Lost") -> 265 | H4: =COUNTIFS(Pipeline_Completo!$C$2:$C$8801,$A4,Pipeline_Completo!$O$2:$O$8801,"Engaging") -> 219 | I4: =COUNTIFS(Pipeline_Completo!$C$2:$C$8801,$A4,Pipeline_Completo!$O$2:$O$8801,"Prospecting") -> 0 | J4: =IFERROR(F4/(F4+G4),"") -> 0.6442953 | K4: =SUMIFS(Pipeline_Completo!$R$2:$R$8801,Pipeline_Completo!$C$2:$C$8801,$A4,Pipeline_Completo!$O$2:$O$8801,"Won") -> 1130049 | L4: =IFERROR(K4/F4,"") -> 2354.2688 | M4: =SUMIFS(Pipeline_Completo!$S$2:$S$8801,Pipeline_Completo!$C$2:$C$8801,$A4,Pipeline_Completo!$O$2:$O$8801,"Engaging")+SUMIFS(Pipeline_Completo!$S$2:$S$8801,Pipeline_Completo!$C$2:$C$8801,$A4,Pipeline_Completo!$O$2:$O$8801,"Prospecting") -> 495950 | N4: =COUNTIFS(Pipeline_Completo!$C$2:$C$8801,$A4,Pipeline_Completo!$V$2:$V$8801,"Saudável")+COUNTIFS(Pipeline_Completo!$C$2:$C$8801,$A4,Pipeline_Completo!$V$2:$V$8801,"Esfriando")+COUNTIFS(Pipeline_Completo!$C$2:$C$8801,$A4,Pipeline_Completo!$V$2:$V$8801,"Última chance") -> 50 | O4: =SUMIFS(Pipeline_Completo!$S$2:$S$8801,Pipeline_Completo!$C$2:$C$8801,$A4,Pipeline_Completo!$V$2:$V$8801,"Saudável")+SUMIFS(Pipeline_Completo!$S$2:$S$8801,Pipeline_Completo!$C$2:$C$8801,$A4,Pipeline_Completo!$V$2:$V$8801,"Esfriando")+SUMIFS(Pipeline_Completo!$S$2:$S$8801,Pipeline_Completo!$C$2:$C$8801,$A4,Pipeline_Completo!$V$2:$V$8801,"Última chance") -> 123514 | P4: =COUNTIFS(Pipeline_Completo!$C$2:$C$8801,$A4,Pipeline_Completo!$V$2:$V$8801,"Zumbi") -> 169 | Q4: =SUMIFS(Pipeline_Completo!$S$2:$S$8801,Pipeline_Completo!$C$2:$C$8801,$A4,Pipeline_Completo!$V$2:$V$8801,"Zumbi") -> 372436 | R4: =IFERROR(Q4/(O4+Q4),"") -> 0.75095473 | S4: =COUNTIFS(Pipeline_Completo!$C$2:$C$8801,$A4,Pipeline_Completo!$O$2:$O$8801,"Engaging",Pipeline_Completo!$E$2:$E$8801,"")+COUNTIFS(Pipeline_Completo!$C$2:$C$8801,$A4,Pipeline_Completo!$O$2:$O$8801,"Prospecting",Pipeline_Completo!$E$2:$E$8801,"") -> 154
A5: Rocco Neubert | B5: East | C5: 6 | D5: 5 | E5: =COUNTIFS(Pipeline_Completo!$C$2:$C$8801,$A5) -> 1327 | F5: =COUNTIFS(Pipeline_Completo!$C$2:$C$8801,$A5,Pipeline_Completo!$O$2:$O$8801,"Won") -> 691 | G5: =COUNTIFS(Pipeline_Completo!$C$2:$C$8801,$A5,Pipeline_Completo!$O$2:$O$8801,"Lost") -> 422 | H5: =COUNTIFS(Pipeline_Completo!$C$2:$C$8801,$A5,Pipeline_Completo!$O$2:$O$8801,"Engaging") -> 214 | I5: =COUNTIFS(Pipeline_Completo!$C$2:$C$8801,$A5,Pipeline_Completo!$O$2:$O$8801,"Prospecting") -> 0 | J5: =IFERROR(F5/(F5+G5),"") -> 0.62084456 | K5: =SUMIFS(Pipeline_Completo!$R$2:$R$8801,Pipeline_Completo!$C$2:$C$8801,$A5,Pipeline_Completo!$O$2:$O$8801,"Won") -> 1960545 | L5: =IFERROR(K5/F5,"") -> 2837.2576 | M5: =SUMIFS(Pipeline_Completo!$S$2:$S$8801,Pipeline_Completo!$C$2:$C$8801,$A5,Pipeline_Completo!$O$2:$O$8801,"Engaging")+SUMIFS(Pipeline_Completo!$S$2:$S$8801,Pipeline_Completo!$C$2:$C$8801,$A5,Pipeline_Completo!$O$2:$O$8801,"Prospecting") -> 573636 | N5: =COUNTIFS(Pipeline_Completo!$C$2:$C$8801,$A5,Pipeline_Completo!$V$2:$V$8801,"Saudável")+COUNTIFS(Pipeline_Completo!$C$2:$C$8801,$A5,Pipeline_Completo!$V$2:$V$8801,"Esfriando")+COUNTIFS(Pipeline_Completo!$C$2:$C$8801,$A5,Pipeline_Completo!$V$2:$V$8801,"Última chance") -> 57 | O5: =SUMIFS(Pipeline_Completo!$S$2:$S$8801,Pipeline_Completo!$C$2:$C$8801,$A5,Pipeline_Completo!$V$2:$V$8801,"Saudável")+SUMIFS(Pipeline_Completo!$S$2:$S$8801,Pipeline_Completo!$C$2:$C$8801,$A5,Pipeline_Completo!$V$2:$V$8801,"Esfriando")+SUMIFS(Pipeline_Completo!$S$2:$S$8801,Pipeline_Completo!$C$2:$C$8801,$A5,Pipeline_Completo!$V$2:$V$8801,"Última chance") -> 137144 | P5: =COUNTIFS(Pipeline_Completo!$C$2:$C$8801,$A5,Pipeline_Completo!$V$2:$V$8801,"Zumbi") -> 157 | Q5: =SUMIFS(Pipeline_Completo!$S$2:$S$8801,Pipeline_Completo!$C$2:$C$8801,$A5,Pipeline_Completo!$V$2:$V$8801,"Zumbi") -> 436492 | R5: =IFERROR(Q5/(O5+Q5),"") -> 0.76092156 | S5: =COUNTIFS(Pipeline_Completo!$C$2:$C$8801,$A5,Pipeline_Completo!$O$2:$O$8801,"Engaging",Pipeline_Completo!$E$2:$E$8801,"")+COUNTIFS(Pipeline_Completo!$C$2:$C$8801,$A5,Pipeline_Completo!$O$2:$O$8801,"Prospecting",Pipeline_Completo!$E$2:$E$8801,"") -> 142
A6: Celia Rouche | B6: West | C6: 6 | D6: 5 | E6: =COUNTIFS(Pipeline_Completo!$C$2:$C$8801,$A6) -> 1296 | F6: =COUNTIFS(Pipeline_Completo!$C$2:$C$8801,$A6,Pipeline_Completo!$O$2:$O$8801,"Won") -> 610 | G6: =COUNTIFS(Pipeline_Completo!$C$2:$C$8801,$A6,Pipeline_Completo!$O$2:$O$8801,"Lost") -> 352 | H6: =COUNTIFS(Pipeline_Completo!$C$2:$C$8801,$A6,Pipeline_Completo!$O$2:$O$8801,"Engaging") -> 334 | I6: =COUNTIFS(Pipeline_Completo!$C$2:$C$8801,$A6,Pipeline_Completo!$O$2:$O$8801,"Prospecting") -> 0 | J6: =IFERROR(F6/(F6+G6),"") -> 0.63409563 | K6: =SUMIFS(Pipeline_Completo!$R$2:$R$8801,Pipeline_Completo!$C$2:$C$8801,$A6,Pipeline_Completo!$O$2:$O$8801,"Won") -> 1603897 | L6: =IFERROR(K6/F6,"") -> 2629.3393 | M6: =SUMIFS(Pipeline_Completo!$S$2:$S$8801,Pipeline_Completo!$C$2:$C$8801,$A6,Pipeline_Completo!$O$2:$O$8801,"Engaging")+SUMIFS(Pipeline_Completo!$S$2:$S$8801,Pipeline_Completo!$C$2:$C$8801,$A6,Pipeline_Completo!$O$2:$O$8801,"Prospecting") -> 1004925 | N6: =COUNTIFS(Pipeline_Completo!$C$2:$C$8801,$A6,Pipeline_Completo!$V$2:$V$8801,"Saudável")+COUNTIFS(Pipeline_Completo!$C$2:$C$8801,$A6,Pipeline_Completo!$V$2:$V$8801,"Esfriando")+COUNTIFS(Pipeline_Completo!$C$2:$C$8801,$A6,Pipeline_Completo!$V$2:$V$8801,"Última chance") -> 77 | O6: =SUMIFS(Pipeline_Completo!$S$2:$S$8801,Pipeline_Completo!$C$2:$C$8801,$A6,Pipeline_Completo!$V$2:$V$8801,"Saudável")+SUMIFS(Pipeline_Completo!$S$2:$S$8801,Pipeline_Completo!$C$2:$C$8801,$A6,Pipeline_Completo!$V$2:$V$8801,"Esfriando")+SUMIFS(Pipeline_Completo!$S$2:$S$8801,Pipeline_Completo!$C$2:$C$8801,$A6,Pipeline_Completo!$V$2:$V$8801,"Última chance") -> 151155 | P6: =COUNTIFS(Pipeline_Completo!$C$2:$C$8801,$A6,Pipeline_Completo!$V$2:$V$8801,"Zumbi") -> 257 | Q6: =SUMIFS(Pipeline_Completo!$S$2:$S$8801,Pipeline_Completo!$C$2:$C$8801,$A6,Pipeline_Completo!$V$2:$V$8801,"Zumbi") -> 853770 | R6: =IFERROR(Q6/(O6+Q6),"") -> 0.84958579 | S6: =COUNTIFS(Pipeline_Completo!$C$2:$C$8801,$A6,Pipeline_Completo!$O$2:$O$8801,"Engaging",Pipeline_Completo!$E$2:$E$8801,"")+COUNTIFS(Pipeline_Completo!$C$2:$C$8801,$A6,Pipeline_Completo!$O$2:$O$8801,"Prospecting",Pipeline_Completo!$E$2:$E$8801,"") -> 232
A7: Summer Sewald | B7: West | C7: 6 | D7: 5 | E7: =COUNTIFS(Pipeline_Completo!$C$2:$C$8801,$A7) -> 1701 | F7: =COUNTIFS(Pipeline_Completo!$C$2:$C$8801,$A7,Pipeline_Completo!$O$2:$O$8801,"Won") -> 828 | G7: =COUNTIFS(Pipeline_Completo!$C$2:$C$8801,$A7,Pipeline_Completo!$O$2:$O$8801,"Lost") -> 459 | H7: =COUNTIFS(Pipeline_Completo!$C$2:$C$8801,$A7,Pipeline_Completo!$O$2:$O$8801,"Engaging") -> 414 | I7: =COUNTIFS(Pipeline_Completo!$C$2:$C$8801,$A7,Pipeline_Completo!$O$2:$O$8801,"Prospecting") -> 0 | J7: =IFERROR(F7/(F7+G7),"") -> 0.64335664 | K7: =SUMIFS(Pipeline_Completo!$R$2:$R$8801,Pipeline_Completo!$C$2:$C$8801,$A7,Pipeline_Completo!$O$2:$O$8801,"Won") -> 1964750 | L7: =IFERROR(K7/F7,"") -> 2372.8865 | M7: =SUMIFS(Pipeline_Completo!$S$2:$S$8801,Pipeline_Completo!$C$2:$C$8801,$A7,Pipeline_Completo!$O$2:$O$8801,"Engaging")+SUMIFS(Pipeline_Completo!$S$2:$S$8801,Pipeline_Completo!$C$2:$C$8801,$A7,Pipeline_Completo!$O$2:$O$8801,"Prospecting") -> 993296 | N7: =COUNTIFS(Pipeline_Completo!$C$2:$C$8801,$A7,Pipeline_Completo!$V$2:$V$8801,"Saudável")+COUNTIFS(Pipeline_Completo!$C$2:$C$8801,$A7,Pipeline_Completo!$V$2:$V$8801,"Esfriando")+COUNTIFS(Pipeline_Completo!$C$2:$C$8801,$A7,Pipeline_Completo!$V$2:$V$8801,"Última chance") -> 109 | O7: =SUMIFS(Pipeline_Completo!$S$2:$S$8801,Pipeline_Completo!$C$2:$C$8801,$A7,Pipeline_Completo!$V$2:$V$8801,"Saudável")+SUMIFS(Pipeline_Completo!$S$2:$S$8801,Pipeline_Completo!$C$2:$C$8801,$A7,Pipeline_Completo!$V$2:$V$8801,"Esfriando")+SUMIFS(Pipeline_Completo!$S$2:$S$8801,Pipeline_Completo!$C$2:$C$8801,$A7,Pipeline_Completo!$V$2:$V$8801,"Última chance") -> 275175 | P7: =COUNTIFS(Pipeline_Completo!$C$2:$C$8801,$A7,Pipeline_Completo!$V$2:$V$8801,"Zumbi") -> 305 | Q7: =SUMIFS(Pipeline_Completo!$S$2:$S$8801,Pipeline_Completo!$C$2:$C$8801,$A7,Pipeline_Completo!$V$2:$V$8801,"Zumbi") -> 718121 | R7: =IFERROR(Q7/(O7+Q7),"") -> 0.72296778 | S7: =COUNTIFS(Pipeline_Completo!$C$2:$C$8801,$A7,Pipeline_Completo!$O$2:$O$8801,"Engaging",Pipeline_Completo!$E$2:$E$8801,"")+COUNTIFS(Pipeline_Completo!$C$2:$C$8801,$A7,Pipeline_Completo!$O$2:$O$8801,"Prospecting",Pipeline_Completo!$E$2:$E$8801,"") -> 286
A8: TOTAL | C8: =SUM(C2:C7) -> 35 | D8: =SUM(D2:D7) -> 30 | E8: =E2+E3+E4+E5+E6+E7 -> 8800 | F8: =F2+F3+F4+F5+F6+F7 -> 4238 | G8: =G2+G3+G4+G5+G6+G7 -> 2473 | H8: =H2+H3+H4+H5+H6+H7 -> 1589 | I8: =I2+I3+I4+I5+I6+I7 -> 500 | J8: =IFERROR(F8/(F8+G8),"") -> 0.63150052 | K8: =K2+K3+K4+K5+K6+K7 -> 10005534 | L8: =IFERROR(K8/F8,"") -> 2360.9094 | M8: =M2+M3+M4+M5+M6+M7 -> 4966215 | N8: =N2+N3+N4+N5+N6+N7 -> 298 | O8: =O2+O3+O4+O5+O6+O7 -> 693565 | P8: =P2+P3+P4+P5+P6+P7 -> 1291 | Q8: =Q2+Q3+Q4+Q5+Q6+Q7 -> 3198664 | R8: =IFERROR(Q8/(O8+Q8),"") -> 0.82180776 | S8: =S2+S3+S4+S5+S6+S7 -> 1425 | T8: =SUM(T2:T7) -> 0
A10: "Vendedores cadastrados"/"ativos" são contagens fixas (sales_teams.csv e vendedores com ≥1 deal).

Sheet Produto_x_Gerente
A1: Receita ganha (US$) — produto × gerente
C3: Central | D3: Central | E3: East | F3: East | G3: West | H3: West
A4: Produto | B4: Preço tabela | C4: Dustin Brinkmann | D4: Melvin Marxen | E4: Cara Losch | F4: Rocco Neubert | G4: Celia Rouche | H4: Summer Sewald | I4: Total
A5: MG Special | B5: 55 | C5: =SUMIFS(Pipeline_Completo!$R$2:$R$8801,Pipeline_Completo!$L$2:$L$8801,$A5,Pipeline_Completo!$C$2:$C$8801,C$4,Pipeline_Completo!$O$2:$O$8801,"Won") -> 15993 | D5: =SUMIFS(Pipeline_Completo!$R$2:$R$8801,Pipeline_Completo!$L$2:$L$8801,$A5,Pipeline_Completo!$C$2:$C$8801,D$4,Pipeline_Completo!$O$2:$O$8801,"Won") -> 5989 | E5: =SUMIFS(Pipeline_Completo!$R$2:$R$8801,Pipeline_Completo!$L$2:$L$8801,$A5,Pipeline_Completo!$C$2:$C$8801,E$4,Pipeline_Completo!$O$2:$O$8801,"Won") -> 6508 | F5: =SUMIFS(Pipeline_Completo!$R$2:$R$8801,Pipeline_Completo!$L$2:$L$8801,$A5,Pipeline_Completo!$C$2:$C$8801,F$4,Pipeline_Completo!$O$2:$O$8801,"Won") -> 2347 | G5: =SUMIFS(Pipeline_Completo!$R$2:$R$8801,Pipeline_Completo!$L$2:$L$8801,$A5,Pipeline_Completo!$C$2:$C$8801,G$4,Pipeline_Completo!$O$2:$O$8801,"Won") -> 8715 | H5: =SUMIFS(Pipeline_Completo!$R$2:$R$8801,Pipeline_Completo!$L$2:$L$8801,$A5,Pipeline_Completo!$C$2:$C$8801,H$4,Pipeline_Completo!$O$2:$O$8801,"Won") -> 4216 | I5: =SUM(C5:H5) -> 43768
A6: GTX Basic | B6: 550 | C6: =SUMIFS(Pipeline_Completo!$R$2:$R$8801,Pipeline_Completo!$L$2:$L$8801,$A6,Pipeline_Completo!$C$2:$C$8801,C$4,Pipeline_Completo!$O$2:$O$8801,"Won") -> 88756 | D6: =SUMIFS(Pipeline_Completo!$R$2:$R$8801,Pipeline_Completo!$L$2:$L$8801,$A6,Pipeline_Completo!$C$2:$C$8801,D$4,Pipeline_Completo!$O$2:$O$8801,"Won") -> 94083 | E6: =SUMIFS(Pipeline_Completo!$R$2:$R$8801,Pipeline_Completo!$L$2:$L$8801,$A6,Pipeline_Completo!$C$2:$C$8801,E$4,Pipeline_Completo!$O$2:$O$8801,"Won") -> 45137 | F6: =SUMIFS(Pipeline_Completo!$R$2:$R$8801,Pipeline_Completo!$L$2:$L$8801,$A6,Pipeline_Completo!$C$2:$C$8801,F$4,Pipeline_Completo!$O$2:$O$8801,"Won") -> 72194 | G6: =SUMIFS(Pipeline_Completo!$R$2:$R$8801,Pipeline_Completo!$L$2:$L$8801,$A6,Pipeline_Completo!$C$2:$C$8801,G$4,Pipeline_Completo!$O$2:$O$8801,"Won") -> 59072 | H6: =SUMIFS(Pipeline_Completo!$R$2:$R$8801,Pipeline_Completo!$L$2:$L$8801,$A6,Pipeline_Completo!$C$2:$C$8801,H$4,Pipeline_Completo!$O$2:$O$8801,"Won") -> 140021 | I6: =SUM(C6:H6) -> 499263
A7: GTX Plus Basic | B7: 1096 | C7: =SUMIFS(Pipeline_Completo!$R$2:$R$8801,Pipeline_Completo!$L$2:$L$8801,$A7,Pipeline_Completo!$C$2:$C$8801,C$4,Pipeline_Completo!$O$2:$O$8801,"Won") -> 82882 | D7: =SUMIFS(Pipeline_Completo!$R$2:$R$8801,Pipeline_Completo!$L$2:$L$8801,$A7,Pipeline_Completo!$C$2:$C$8801,D$4,Pipeline_Completo!$O$2:$O$8801,"Won") -> 193630 | E7: =SUMIFS(Pipeline_Completo!$R$2:$R$8801,Pipeline_Completo!$L$2:$L$8801,$A7,Pipeline_Completo!$C$2:$C$8801,E$4,Pipeline_Completo!$O$2:$O$8801,"Won") -> 54265 | F7: =SUMIFS(Pipeline_Completo!$R$2:$R$8801,Pipeline_Completo!$L$2:$L$8801,$A7,Pipeline_Completo!$C$2:$C$8801,F$4,Pipeline_Completo!$O$2:$O$8801,"Won") -> 146414 | G7: =SUMIFS(Pipeline_Completo!$R$2:$R$8801,Pipeline_Completo!$L$2:$L$8801,$A7,Pipeline_Completo!$C$2:$C$8801,G$4,Pipeline_Completo!$O$2:$O$8801,"Won") -> 69891 | H7: =SUMIFS(Pipeline_Completo!$R$2:$R$8801,Pipeline_Completo!$L$2:$L$8801,$A7,Pipeline_Completo!$C$2:$C$8801,H$4,Pipeline_Completo!$O$2:$O$8801,"Won") -> 158193 | I7: =SUM(C7:H7) -> 705275
A8: MG Advanced | B8: 3393 | C8: =SUMIFS(Pipeline_Completo!$R$2:$R$8801,Pipeline_Completo!$L$2:$L$8801,$A8,Pipeline_Completo!$C$2:$C$8801,C$4,Pipeline_Completo!$O$2:$O$8801,"Won") -> 458229 | D8: =SUMIFS(Pipeline_Completo!$R$2:$R$8801,Pipeline_Completo!$L$2:$L$8801,$A8,Pipeline_Completo!$C$2:$C$8801,D$4,Pipeline_Completo!$O$2:$O$8801,"Won") -> 370718 | E8: =SUMIFS(Pipeline_Completo!$R$2:$R$8801,Pipeline_Completo!$L$2:$L$8801,$A8,Pipeline_Completo!$C$2:$C$8801,E$4,Pipeline_Completo!$O$2:$O$8801,"Won") -> 262360 | F8: =SUMIFS(Pipeline_Completo!$R$2:$R$8801,Pipeline_Completo!$L$2:$L$8801,$A8,Pipeline_Completo!$C$2:$C$8801,F$4,Pipeline_Completo!$O$2:$O$8801,"Won") -> 393554 | G8: =SUMIFS(Pipeline_Completo!$R$2:$R$8801,Pipeline_Completo!$L$2:$L$8801,$A8,Pipeline_Completo!$C$2:$C$8801,G$4,Pipeline_Completo!$O$2:$O$8801,"Won") -> 535414 | H8: =SUMIFS(Pipeline_Completo!$R$2:$R$8801,Pipeline_Completo!$L$2:$L$8801,$A8,Pipeline_Completo!$C$2:$C$8801,H$4,Pipeline_Completo!$O$2:$O$8801,"Won") -> 196112 | I8: =SUM(C8:H8) -> 2216387
A9: GTX Pro | B9: 4821 | C9: =SUMIFS(Pipeline_Completo!$R$2:$R$8801,Pipeline_Completo!$L$2:$L$8801,$A9,Pipeline_Completo!$C$2:$C$8801,C$4,Pipeline_Completo!$O$2:$O$8801,"Won") -> 0 | D9: =SUMIFS(Pipeline_Completo!$R$2:$R$8801,Pipeline_Completo!$L$2:$L$8801,$A9,Pipeline_Completo!$C$2:$C$8801,D$4,Pipeline_Completo!$O$2:$O$8801,"Won") -> 1104109 | E9: =SUMIFS(Pipeline_Completo!$R$2:$R$8801,Pipeline_Completo!$L$2:$L$8801,$A9,Pipeline_Completo!$C$2:$C$8801,E$4,Pipeline_Completo!$O$2:$O$8801,"Won") -> 435354 | F9: =SUMIFS(Pipeline_Completo!$R$2:$R$8801,Pipeline_Completo!$L$2:$L$8801,$A9,Pipeline_Completo!$C$2:$C$8801,F$4,Pipeline_Completo!$O$2:$O$8801,"Won") -> 850293 | G9: =SUMIFS(Pipeline_Completo!$R$2:$R$8801,Pipeline_Completo!$L$2:$L$8801,$A9,Pipeline_Completo!$C$2:$C$8801,G$4,Pipeline_Completo!$O$2:$O$8801,"Won") -> 344111 | H9: =SUMIFS(Pipeline_Completo!$R$2:$R$8801,Pipeline_Completo!$L$2:$L$8801,$A9,Pipeline_Completo!$C$2:$C$8801,H$4,Pipeline_Completo!$O$2:$O$8801,"Won") -> 776711 | I9: =SUM(C9:H9) -> 3510578
A10: GTX Plus Pro | B10: 5482 | C10: =SUMIFS(Pipeline_Completo!$R$2:$R$8801,Pipeline_Completo!$L$2:$L$8801,$A10,Pipeline_Completo!$C$2:$C$8801,C$4,Pipeline_Completo!$O$2:$O$8801,"Won") -> 448503 | D10: =SUMIFS(Pipeline_Completo!$R$2:$R$8801,Pipeline_Completo!$L$2:$L$8801,$A10,Pipeline_Completo!$C$2:$C$8801,D$4,Pipeline_Completo!$O$2:$O$8801,"Won") -> 483401 | E10: =SUMIFS(Pipeline_Completo!$R$2:$R$8801,Pipeline_Completo!$L$2:$L$8801,$A10,Pipeline_Completo!$C$2:$C$8801,E$4,Pipeline_Completo!$O$2:$O$8801,"Won") -> 326425 | F10: =SUMIFS(Pipeline_Completo!$R$2:$R$8801,Pipeline_Completo!$L$2:$L$8801,$A10,Pipeline_Completo!$C$2:$C$8801,F$4,Pipeline_Completo!$O$2:$O$8801,"Won") -> 495743 | G10: =SUMIFS(Pipeline_Completo!$R$2:$R$8801,Pipeline_Completo!$L$2:$L$8801,$A10,Pipeline_Completo!$C$2:$C$8801,G$4,Pipeline_Completo!$O$2:$O$8801,"Won") -> 186082 | H10: =SUMIFS(Pipeline_Completo!$R$2:$R$8801,Pipeline_Completo!$L$2:$L$8801,$A10,Pipeline_Completo!$C$2:$C$8801,H$4,Pipeline_Completo!$O$2:$O$8801,"Won") -> 689497 | I10: =SUM(C10:H10) -> 2629651
A11: GTK 500 | B11: 26768 | C11: =SUMIFS(Pipeline_Completo!$R$2:$R$8801,Pipeline_Completo!$L$2:$L$8801,$A11,Pipeline_Completo!$C$2:$C$8801,C$4,Pipeline_Completo!$O$2:$O$8801,"Won") -> 0 | D11: =SUMIFS(Pipeline_Completo!$R$2:$R$8801,Pipeline_Completo!$L$2:$L$8801,$A11,Pipeline_Completo!$C$2:$C$8801,D$4,Pipeline_Completo!$O$2:$O$8801,"Won") -> 0 | E11: =SUMIFS(Pipeline_Completo!$R$2:$R$8801,Pipeline_Completo!$L$2:$L$8801,$A11,Pipeline_Completo!$C$2:$C$8801,E$4,Pipeline_Completo!$O$2:$O$8801,"Won") -> 0 | F11: =SUMIFS(Pipeline_Completo!$R$2:$R$8801,Pipeline_Completo!$L$2:$L$8801,$A11,Pipeline_Completo!$C$2:$C$8801,F$4,Pipeline_Completo!$O$2:$O$8801,"Won") -> 0 | G11: =SUMIFS(Pipeline_Completo!$R$2:$R$8801,Pipeline_Completo!$L$2:$L$8801,$A11,Pipeline_Completo!$C$2:$C$8801,G$4,Pipeline_Completo!$O$2:$O$8801,"Won") -> 400612 | H11: =SUMIFS(Pipeline_Completo!$R$2:$R$8801,Pipeline_Completo!$L$2:$L$8801,$A11,Pipeline_Completo!$C$2:$C$8801,H$4,Pipeline_Completo!$O$2:$O$8801,"Won") -> 0 | I11: =SUM(C11:H11) -> 400612
A12: Total | C12: =SUM(C5:C11) -> 1094363 | D12: =SUM(D5:D11) -> 2251930 | E12: =SUM(E5:E11) -> 1130049 | F12: =SUM(F5:F11) -> 1960545 | G12: =SUM(G5:G11) -> 1603897 | H12: =SUM(H5:H11) -> 1964750 | I12: =SUM(I5:I11) -> 10005534
A14: Pipeline aberto (US$, preço de tabela) — produto × gerente
C16: Central | D16: Central | E16: East | F16: East | G16: West | H16: West
A17: Produto | B17: Preço tabela | C17: Dustin Brinkmann | D17: Melvin Marxen | E17: Cara Losch | F17: Rocco Neubert | G17: Celia Rouche | H17: Summer Sewald | I17: Total
A18: MG Special | B18: 55 | C18: =SUMIFS(Pipeline_Completo!$S$2:$S$8801,Pipeline_Completo!$L$2:$L$8801,$A18,Pipeline_Completo!$C$2:$C$8801,C$17,Pipeline_Completo!$O$2:$O$8801,"Engaging")+SUMIFS(Pipeline_Completo!$S$2:$S$8801,Pipeline_Completo!$L$2:$L$8801,$A18,Pipeline_Completo!$C$2:$C$8801,C$17,Pipeline_Completo!$O$2:$O$8801,"Prospecting") -> 8690 | D18: =SUMIFS(Pipeline_Completo!$S$2:$S$8801,Pipeline_Completo!$L$2:$L$8801,$A18,Pipeline_Completo!$C$2:$C$8801,D$17,Pipeline_Completo!$O$2:$O$8801,"Engaging")+SUMIFS(Pipeline_Completo!$S$2:$S$8801,Pipeline_Completo!$L$2:$L$8801,$A18,Pipeline_Completo!$C$2:$C$8801,D$17,Pipeline_Completo!$O$2:$O$8801,"Prospecting") -> 3850 | E18: =SUMIFS(Pipeline_Completo!$S$2:$S$8801,Pipeline_Completo!$L$2:$L$8801,$A18,Pipeline_Completo!$C$2:$C$8801,E$17,Pipeline_Completo!$O$2:$O$8801,"Engaging")+SUMIFS(Pipeline_Completo!$S$2:$S$8801,Pipeline_Completo!$L$2:$L$8801,$A18,Pipeline_Completo!$C$2:$C$8801,E$17,Pipeline_Completo!$O$2:$O$8801,"Prospecting") -> 2750 | F18: =SUMIFS(Pipeline_Completo!$S$2:$S$8801,Pipeline_Completo!$L$2:$L$8801,$A18,Pipeline_Completo!$C$2:$C$8801,F$17,Pipeline_Completo!$O$2:$O$8801,"Engaging")+SUMIFS(Pipeline_Completo!$S$2:$S$8801,Pipeline_Completo!$L$2:$L$8801,$A18,Pipeline_Completo!$C$2:$C$8801,F$17,Pipeline_Completo!$O$2:$O$8801,"Prospecting") -> 935 | G18: =SUMIFS(Pipeline_Completo!$S$2:$S$8801,Pipeline_Completo!$L$2:$L$8801,$A18,Pipeline_Completo!$C$2:$C$8801,G$17,Pipeline_Completo!$O$2:$O$8801,"Engaging")+SUMIFS(Pipeline_Completo!$S$2:$S$8801,Pipeline_Completo!$L$2:$L$8801,$A18,Pipeline_Completo!$C$2:$C$8801,G$17,Pipeline_Completo!$O$2:$O$8801,"Prospecting") -> 5390 | H18: =SUMIFS(Pipeline_Completo!$S$2:$S$8801,Pipeline_Completo!$L$2:$L$8801,$A18,Pipeline_Completo!$C$2:$C$8801,H$17,Pipeline_Completo!$O$2:$O$8801,"Engaging")+SUMIFS(Pipeline_Completo!$S$2:$S$8801,Pipeline_Completo!$L$2:$L$8801,$A18,Pipeline_Completo!$C$2:$C$8801,H$17,Pipeline_Completo!$O$2:$O$8801,"Prospecting") -> 1925 | I18: =SUM(C18:H18) -> 23540
A19: GTX Basic | B19: 550 | C19: =SUMIFS(Pipeline_Completo!$S$2:$S$8801,Pipeline_Completo!$L$2:$L$8801,$A19,Pipeline_Completo!$C$2:$C$8801,C$17,Pipeline_Completo!$O$2:$O$8801,"Engaging")+SUMIFS(Pipeline_Completo!$S$2:$S$8801,Pipeline_Completo!$L$2:$L$8801,$A19,Pipeline_Completo!$C$2:$C$8801,C$17,Pipeline_Completo!$O$2:$O$8801,"Prospecting") -> 41800 | D19: =SUMIFS(Pipeline_Completo!$S$2:$S$8801,Pipeline_Completo!$L$2:$L$8801,$A19,Pipeline_Completo!$C$2:$C$8801,D$17,Pipeline_Completo!$O$2:$O$8801,"Engaging")+SUMIFS(Pipeline_Completo!$S$2:$S$8801,Pipeline_Completo!$L$2:$L$8801,$A19,Pipeline_Completo!$C$2:$C$8801,D$17,Pipeline_Completo!$O$2:$O$8801,"Prospecting") -> 53350 | E19: =SUMIFS(Pipeline_Completo!$S$2:$S$8801,Pipeline_Completo!$L$2:$L$8801,$A19,Pipeline_Completo!$C$2:$C$8801,E$17,Pipeline_Completo!$O$2:$O$8801,"Engaging")+SUMIFS(Pipeline_Completo!$S$2:$S$8801,Pipeline_Completo!$L$2:$L$8801,$A19,Pipeline_Completo!$C$2:$C$8801,E$17,Pipeline_Completo!$O$2:$O$8801,"Prospecting") -> 22000 | F19: =SUMIFS(Pipeline_Completo!$S$2:$S$8801,Pipeline_Completo!$L$2:$L$8801,$A19,Pipeline_Completo!$C$2:$C$8801,F$17,Pipeline_Completo!$O$2:$O$8801,"Engaging")+SUMIFS(Pipeline_Completo!$S$2:$S$8801,Pipeline_Completo!$L$2:$L$8801,$A19,Pipeline_Completo!$C$2:$C$8801,F$17,Pipeline_Completo!$O$2:$O$8801,"Prospecting") -> 18700 | G19: =SUMIFS(Pipeline_Completo!$S$2:$S$8801,Pipeline_Completo!$L$2:$L$8801,$A19,Pipeline_Completo!$C$2:$C$8801,G$17,Pipeline_Completo!$O$2:$O$8801,"Engaging")+SUMIFS(Pipeline_Completo!$S$2:$S$8801,Pipeline_Completo!$L$2:$L$8801,$A19,Pipeline_Completo!$C$2:$C$8801,G$17,Pipeline_Completo!$O$2:$O$8801,"Prospecting") -> 33550 | H19: =SUMIFS(Pipeline_Completo!$S$2:$S$8801,Pipeline_Completo!$L$2:$L$8801,$A19,Pipeline_Completo!$C$2:$C$8801,H$17,Pipeline_Completo!$O$2:$O$8801,"Engaging")+SUMIFS(Pipeline_Completo!$S$2:$S$8801,Pipeline_Completo!$L$2:$L$8801,$A19,Pipeline_Completo!$C$2:$C$8801,H$17,Pipeline_Completo!$O$2:$O$8801,"Prospecting") -> 67100 | I19: =SUM(C19:H19) -> 236500
A20: GTX Plus Basic | B20: 1096 | C20: =SUMIFS(Pipeline_Completo!$S$2:$S$8801,Pipeline_Completo!$L$2:$L$8801,$A20,Pipeline_Completo!$C$2:$C$8801,C$17,Pipeline_Completo!$O$2:$O$8801,"Engaging")+SUMIFS(Pipeline_Completo!$S$2:$S$8801,Pipeline_Completo!$L$2:$L$8801,$A20,Pipeline_Completo!$C$2:$C$8801,C$17,Pipeline_Completo!$O$2:$O$8801,"Prospecting") -> 39456 | D20: =SUMIFS(Pipeline_Completo!$S$2:$S$8801,Pipeline_Completo!$L$2:$L$8801,$A20,Pipeline_Completo!$C$2:$C$8801,D$17,Pipeline_Completo!$O$2:$O$8801,"Engaging")+SUMIFS(Pipeline_Completo!$S$2:$S$8801,Pipeline_Completo!$L$2:$L$8801,$A20,Pipeline_Completo!$C$2:$C$8801,D$17,Pipeline_Completo!$O$2:$O$8801,"Prospecting") -> 111792 | E20: =SUMIFS(Pipeline_Completo!$S$2:$S$8801,Pipeline_Completo!$L$2:$L$8801,$A20,Pipeline_Completo!$C$2:$C$8801,E$17,Pipeline_Completo!$O$2:$O$8801,"Engaging")+SUMIFS(Pipeline_Completo!$S$2:$S$8801,Pipeline_Completo!$L$2:$L$8801,$A20,Pipeline_Completo!$C$2:$C$8801,E$17,Pipeline_Completo!$O$2:$O$8801,"Prospecting") -> 31784 | F20: =SUMIFS(Pipeline_Completo!$S$2:$S$8801,Pipeline_Completo!$L$2:$L$8801,$A20,Pipeline_Completo!$C$2:$C$8801,F$17,Pipeline_Completo!$O$2:$O$8801,"Engaging")+SUMIFS(Pipeline_Completo!$S$2:$S$8801,Pipeline_Completo!$L$2:$L$8801,$A20,Pipeline_Completo!$C$2:$C$8801,F$17,Pipeline_Completo!$O$2:$O$8801,"Prospecting") -> 61376 | G20: =SUMIFS(Pipeline_Completo!$S$2:$S$8801,Pipeline_Completo!$L$2:$L$8801,$A20,Pipeline_Completo!$C$2:$C$8801,G$17,Pipeline_Completo!$O$2:$O$8801,"Engaging")+SUMIFS(Pipeline_Completo!$S$2:$S$8801,Pipeline_Completo!$L$2:$L$8801,$A20,Pipeline_Completo!$C$2:$C$8801,G$17,Pipeline_Completo!$O$2:$O$8801,"Prospecting") -> 33976 | H20: =SUMIFS(Pipeline_Completo!$S$2:$S$8801,Pipeline_Completo!$L$2:$L$8801,$A20,Pipeline_Completo!$C$2:$C$8801,H$17,Pipeline_Completo!$O$2:$O$8801,"Engaging")+SUMIFS(Pipeline_Completo!$S$2:$S$8801,Pipeline_Completo!$L$2:$L$8801,$A20,Pipeline_Completo!$C$2:$C$8801,H$17,Pipeline_Completo!$O$2:$O$8801,"Prospecting") -> 85488 | I20: =SUM(C20:H20) -> 363872
